Workbook

Sheet Dashboard_Accounting
A1: ACCOUNTING WORKBOOK DASHBOARD – PT SINAR NIAGA INDONESIA
A2: Panel kontrol workbook latihan: volume latihan, tie-out, performa, dan saldo utama.
A4: KPI | B4: Nilai | C4: Status | D4: Sumber | F4: P&L Snapshot | G4: Rp
A5: Jurnal Umum | B5: 80 soal | C5: READY | D5: Soal_dan_Jurnal | F5: Penjualan Bersih | G5: =Laba_Rugi!$B$8 -> 669400000
A6: Jurnal Penyesuaian | B6: 30 soal | C6: READY | D6: Jurnal_Penyesuaian | F6: HPP | G6: =Laba_Rugi!$B$9 -> 391400000
A7: COA | B7: 88 akun | C7: READY | D7: COA | F7: Laba Kotor | G7: =Laba_Rugi!$B$10 -> 278000000
A8: Saldo Awal | B8: 569.000.000 | C8: BALANCE | D8: Saldo_Awal | F8: Beban Operasi | G8: =Laba_Rugi!$B$37 -> 138550000
A9: Neraca Saldo | B9: =Neraca_Saldo!E92 -> 5752570000 | C9: =IF(ABS(Neraca_Saldo!E92-Neraca_Saldo!F92)<0.01,"BALANCE","PERIKSA") -> BALANCE | D9: Neraca_Saldo | F9: Laba Operasi | G9: =Laba_Rugi!$B$38 -> 139450000
A10: NS Setelah Penyesuaian | B10: =NS_Setelah_Penyesuaian!E92 -> 5899864000 | C10: =IF(ABS(NS_Setelah_Penyesuaian!E92-NS_Setelah_Penyesuaian!F92)<0.01,"BALANCE","PERIKSA") -> BALANCE | D10: NS_Setelah_Penyesuaian | F10: Laba Bersih | G10: =Laba_Rugi!$B$45 -> 134800000
A11: NS Setelah Penutupan | B11: =NS_Setelah_Penutupan!E92 -> 2514400000 | C11: =IF(ABS(NS_Setelah_Penutupan!E92-NS_Setelah_Penutupan!F92)<0.01,"BALANCE","PERIKSA") -> BALANCE | D11: NS_Setelah_Penutupan
A12: Rekonsiliasi Bank | B12: =Rekonsiliasi_Bank!B13 -> BALANCE | C12: =B12 -> BALANCE | D12: Rekonsiliasi_Bank
A13: AP Subledger | B13: =Rekap_AP!G11 -> 148400000 | C13: =Rekonsiliasi_Akun!E4 -> TIED | D13: Rekap_AP
A14: AR Subledger | B14: =Rekap_AR!I8 -> 116140000 | C14: =Rekonsiliasi_Akun!E5 -> TIED | D14: Rekap_AR
A15: Laba Bersih | B15: =Laba_Rugi!$B$45 -> 134800000 | C15: =IF(B15>=0,"PROFIT","LOSS") -> PROFIT | D15: Laba_Rugi
A16: Total Aset | B16: =Posisi_Keuangan!B28 -> 2456150000 | C16: =Posisi_Keuangan!E33 -> BALANCE | D16: Posisi_Keuangan

Sheet Petunjuk
A1: LATIHAN AKUNTANSI PERUSAHAAN DAGANG – WORKBOOK SIMULASI ACCOUNTING END-TO-END
A3: 1 | B3: Mulai dari Dashboard_Accounting untuk melihat status tie-out dan ringkasan workbook.
A4: 2 | B4: Baca Parameter_Latihan sebelum mengerjakan: periode, kebijakan perpetual/accrual, PPN/PPh, dan asumsi latihan.
A5: 3 | B5: Gunakan COA sebagai daftar akun resmi 88 akun. Jangan membuat akun baru sembarangan; gunakan akun yang paling spesifik.
A6: 4 | B6: Data_Master berisi supplier, customer, SKU, dan dokumen master untuk membuat kasus lebih realistis.
A7: 5 | B7: Saldo_Awal berisi posisi per 31-Des-2026 dan harus balance sebelum transaksi Januari dimasukkan.
A8: 6 | B8: Soal_dan_Jurnal berisi 80 kasus Basic → Intermediate → Advanced. Kolom J:L adalah area jawaban siswa.
A9: 7 | B9: Selesaikan setiap jurnal dengan menentukan tanggal, akun, debit, kredit, counterparty, dan dokumen pendukung.
A10: 8 | B10: Kolom M:P di Soal_dan_Jurnal adalah self-check otomatis terhadap Kunci_Jurnal_80.
A11: 9 | B11: Kunci_Jurnal_80 adalah jawaban pembanding mentor. Gunakan untuk review setelah latihan, bukan sebelum mengerjakan.
A12: 10 | B12: Buku_Besar memposting Saldo Awal + Jurnal Umum + Penyesuaian + Jurnal Penutup secara formula-driven.
A13: 11 | B13: Rekap_AP melatih invoice supplier, retur, pembayaran, diskon, dan aging saldo utang.
A14: 12 | B14: Rekap_AR melatih invoice customer, retur/rebate, NSF, penerimaan, write-off, dan aging saldo piutang.
... A21: 19 | B21: Gunakan Kamus_Rumus untuk memahami prinsip SUMIF/SUMIFS, saldo normal, rekonsiliasi, dan kontrol balance.

Sheet Parameter_Latihan
A1: PARAMETER & ASUMSI LATIHAN – JANGAN DISAMAKAN OTOMATIS DENGAN PERLAKUAN PAJAK RIIL
A3: Parameter | B3: Nilai | C3: Satuan | D3: Status | E3: Catatan | F3: Sumber
A4: Periode mulai | B4: 46388 | C4: tanggal | D4: Fixed | E4: Awal periode latihan | F4: Workbook
A5: Periode akhir | B5: 46418 | C5: tanggal | D5: Fixed | E5: Akhir periode latihan | F5: Workbook
A6: PPN tarif umum (referensi) | B6: 0.12 | C6: % | D6: Referensi | E6: Tarif umum berdasarkan rezim sejak 2025; konteks objek harus dicek. | F6: https://www.pajak.go.id/id/peraturan/harmonisasi-peraturan-perpajakan
A7: PPN efektif latihan | B7: 0.11 | C7: % | D7: Asumsi latihan | E7: Dipakai pada soal yang secara eksplisit menyatakan PPN latihan efektif 11%. | F7: https://stats.pajak.go.id/id/siaran-pers/pemerintah-terbitkan-aturan-dpp-nilai-lain-dan-besaran-tertentu-pajak-pertambahan-nilai
A8: PPh 23 jasa tertentu | B8: 0.02 | C8: % | D8: Referensi/latihan | E8: 2% dari jumlah bruto untuk jasa tertentu; kasus hanya menggunakan objek yang dinyatakan. | F8: https://www.pajak.go.id/id/pph-pasal-23
A9: PPh Final sewa tanah/bangunan | B9: 0.1 | C9: % | D9: Referensi | E9: 10% dari jumlah bruto sewa tanah/bangunan. | F9: https://pajak.go.id/id/pph-pasal-4-ayat-2
A10: PPh 22 pembelian oleh pemungut tertentu | B10: 0.015 | C10: % | D10: Referensi/latihan | E10: 1,5% dari harga pembelian tidak termasuk PPN pada konteks pemungut tertentu. | F10: https://pajak.go.id/pph-pasal-22
A11: PPh 22 impor API | B11: 0.025 | C11: % | D11: Referensi/latihan | E11: 2,5% dari nilai impor untuk impor dengan API. | F11: https://pajak.go.id/pph-pasal-22
A12: PPh 21 | C12: Rp | D12: Asumsi latihan | E12: Nominal pajak ditetapkan per soal; simulasi detail payroll ada di sheet Payroll. | F12: https://stats.pajak.go.id/id/artikel/tarif-efektif-rata-rata-penyempurnaan-perhitungan-pph-pasal-21
A13: Metode persediaan | B13: Perpetual | C13: metode | D13: Fixed | E13: HPP dicatat saat penjualan. | F13: Workbook
A14: Metode kartu persediaan | B14: FIFO | C14: metode | D14: Asumsi latihan | E14: Untuk modul kartu persediaan per SKU. | F14: Workbook
A15: Dasar pencatatan | B15: Accrual basis | C15: basis | D15: Fixed | E15: Akui hak/kewajiban saat terjadi. | F15: Workbook
A16: Mata uang | B16: Rupiah | C16: IDR | D16: Fixed | E16: Semua angka dalam Rp. | F16: Workbook

Sheet COA
A1: CHART OF ACCOUNTS – PT SINAR NIAGA INDONESIA
A4: Kode Akun | B4: Nama Akun | C4: Kategori | D4: Saldo Normal | E4: Kelompok Laporan
A5: 1-001 | B5: Bank | C5: Aset | D5: Debit | E5: Posisi Keuangan - Aset Lancar
A6: 1-002 | B6: Kas Kecil | C6: Aset | D6: Debit | E6: Posisi Keuangan - Aset Lancar
A7: 1-003 | B7: Piutang Usaha | C7: Aset | D7: Debit | E7: Posisi Keuangan - Aset Lancar
A8: 1-004 | B8: Piutang Karyawan | C8: Aset | D8: Debit | E8: Posisi Keuangan - Aset Lancar
A9: 1-005 | B9: Piutang Bunga | C9: Aset | D9: Debit | E9: Posisi Keuangan - Aset Lancar
A10: 1-006 | B10: Piutang Pendapatan | C10: Aset | D10: Debit | E10: Posisi Keuangan - Aset Lancar
A11: 1-007 | B11: Persediaan Barang Dagang | C11: Aset | D11: Debit | E11: Posisi Keuangan - Aset Lancar
A12: 1-008 | B12: PPN Masukan | C12: Aset | D12: Debit | E12: Posisi Keuangan - Aset Lancar
A13: 1-009 | B13: PPh 22 Dibayar di Muka | C13: Aset | D13: Debit | E13: Posisi Keuangan - Aset Lancar
A14: 1-010 | B14: PPh 23 Dibayar di Muka | C14: Aset | D14: Debit | E14: Posisi Keuangan - Aset Lancar
A15: 1-011 | B15: PPh Final Dibayar di Muka | C15: Aset | D15: Debit | E15: Posisi Keuangan - Aset Lancar
... A92: 2-021 | B92: PPN Keluaran | C92: Liabilitas | D92: Kredit | E92: Posisi Keuangan - Liabilitas Lancar

Sheet Data_Master
A1: DATA MASTER – SUPPLIER, CUSTOMER, SKU, DAN TERMS
A4: Supplier Code | B4: Supplier | C4: Payment Terms | D4: PPh/Pajak Case | E4: Contact / Note | F4: Column1 | G4: Customer Code | H4: Customer | I4: Credit Limit | J4: Terms | K4: Note
A5: SUP-A | B5: Supplier A | C5: 30 hari | D5: Pemasok barang dagang | E5: Supplier utama | G5: CUS-B | H5: Pelanggan B | I5: 300000000 | J5: 30 hari | K5: AR utama
A6: SUP-B | B6: Supplier B | C6: 14 hari | D6: Pemasok barang dagang | E6: Rebate volume | G6: CUS-C | H6: Pelanggan C | I6: 100000000 | J6: DP | K6: Customer advance
A7: SUP-C | B7: PT Perkasa Office | C7: 30 hari | D7: Aset tetap | E7: Peralatan toko | G7: CUS-D | H7: Pelanggan D | I7: 350000000 | J7: 45 hari | K7: Volume rebate
A8: SUP-D | B8: PT Kantor Jaya | C8: 30 hari | D8: Aset tetap | E8: Peralatan kantor | G8: CUS-E | H8: Pelanggan E | I8: 100000000 | J8: 14 hari | K8: Early payment discount
A9: SUP-E | B9: Supplier E | C9: 30 hari | D9: Uang muka | E9: Skenario advance | G9: CUS-F | H9: Pelanggan F | I9: 150000000 | J9: 30 hari | K9: Partial collection
A10: SUP-F | B10: Supplier F | C10: Immediate | D10: Pembelian tunai | E10: Diskon pembelian | G10: CUS-G | H10: Pelanggan Umum | I10: 100000000 | J10: Cash | K10: Retail/cash sales
A11: SUP-G | B11: Supplier G | C11: 14 hari | D11: Pemasok barang dagang | E11: Transaksi akhir | G11: CUS-H | H11: Pelanggan H | I11: 100000000 | J11: 30 hari | K11: Aged AR practice
A12: SUP-H | B12: Toko ATK Nusantara | C12: 30 hari | D12: Perlengkapan | E12: Invoice ATK | G12: CUS-I | H12: Pelanggan I | I12: 100000000 | J12: 30 hari | K12: AR practice
A13: SUP-I | B13: PT Gudang Sentosa | C13: Bulanan | D13: Sewa gedung | E13: PPh Final 4(2)
A14: SUP-J | B14: Kantor Konsultan Prima | C14: 14 hari | D14: Jasa profesional | E14: PPh 23
A15: SUP-K | B15: PT Garda Aman | C15: 14 hari | D15: Jasa keamanan | E15: PPh 23
A17: SKU | B17: Nama Barang | C17: Unit | D17: Cost Awal | E17: Harga Jual | F17: Reorder Point | G17: Keterangan
A18: SKU-01 | B18: Printer Ink | C18: unit | D18: 2500000 | E18: 4000000 | F18: 10 | G18: Barang elektronik kantor
A19: SKU-02 | B19: Laptop Bisnis | C19: unit | D19: 7000000 | E19: 10000000 | F19: 5 | G19: Barang bernilai tinggi
A20: SKU-03 | B20: Kertas A4 | C20: rim | D20: 45000 | E20: 75000 | F20: 100 | G20: Fast moving
A21: SKU-04 | B21: Toner | C21: unit | D21: 1500000 | E21: 2400000 | F21: 20 | G21: Office consumable
A22: SKU-05 | B22: Monitor | C22: unit | D22: 1800000 | E22: 3000000 | F22: 10 | G22: Barang elektronik
A23: SKU-06 | B23: Keyboard | C23: unit | D23: 350000 | E23: 600000 | F23: 25 | G23: Office accessory
A24: SKU-07 | B24: Mouse | C24: unit | D24: 200000 | E24: 350000 | F24: 25 | G24: Office accessory
A25: SKU-08 | B25: Router | C25: unit | D25: 900000 | E25: 1500000 | F25: 15 | G25: Networking

Sheet Soal_dan_Jurnal
A1: LATIHAN 80 SOAL – JURNAL UMUM PERUSAHAAN DAGANG | BASIC → ADVANCED
A2: Isi kolom J:L untuk menjawab. H:I sudah disiapkan sebagai identitas baris. M:O memeriksa akun/debit/kredit terhadap Kunci_Jurnal_80. P menunjukkan status baris.
A3: No | B3: Tanggal | C3: Tingkat / Jenis | D3: Soal | E3: Tambahan / Fakta Penting | F3: Nominal (Rp) | G3: Petunjuk | H3: No2 | I3: Tanggal2 | J3: Akun Jawaban | K3: Debit Jawaban | L3: Kredit Jawaban | M3: Cek Akun | N3: Cek Debit | O3: Cek Kredit
A4: 1 | B4: 46388 | C4: Mudah / Setoran modal | D4: Pemegang saham menyetor modal tunai Rp1.500.000.000 ke rekening bank perusahaan. | E4: Setoran penuh; tidak ada biaya penerbitan saham. | F4: 1500000000 | G4: Debit Bank; kredit Modal Saham. | H4: 1 | I4: 46388 | J4: bank | K4: 1500000000 | L4: 0 | M4: =IF(Table3[[#This Row],[Akun Jawaban]]="","",IF(Table3[[#This Row],[Akun Jawaban]]=Table4[[#This Row],[Akun]],"Benar","salah")) -> Benar | N4: =IF(Table3[[#This Row],[Debit Jawaban]]="","",IF(Table3[[#This Row],[Debit Jawaban]]=Table4[[#This Row],[Debit (Rp)]],"Benar","salah")) -> Benar | O4: =IF(Table3[[#This Row],[Kredit Jawaban]]="","",IF(Table3[[#This Row],[Kredit Jawaban]]=Table4[[#This Row],[Kredit (Rp)]],"Benar","salah")) -> Benar
G5: Debit Bank; kredit Modal Saham. | H5: 1 | I5: 46388 | J5: modal saham | K5: 0 | L5: 1500000000 | M5: =IF(Table3[[#This Row],[Akun Jawaban]]="","",IF(Table3[[#This Row],[Akun Jawaban]]=Table4[[#This Row],[Akun]],"Benar","salah")) -> Benar | N5: =IF(Table3[[#This Row],[Debit Jawaban]]="","",IF(Table3[[#This Row],[Debit Jawaban]]=Table4[[#This Row],[Debit (Rp)]],"Benar","salah")) -> Benar | O5: =IF(Table3[[#This Row],[Kredit Jawaban]]="","",IF(Table3[[#This Row],[Kredit Jawaban]]=Table4[[#This Row],[Kredit (Rp)]],"Benar","salah")) -> Benar
A6: 2 | B6: 46388 | C6: Mudah / Transfer kas kecil | D6: Perusahaan memindahkan Rp20.000.000 dari bank ke kas kecil. | E6: Hanya perpindahan antar akun kas. | F6: 20000000 | G6: Debit Kas Kecil; kredit Bank. | H6: 2 | I6: 46388 | J6: kas kecil | K6: 20000000 | M6: =IF(Table3[[#This Row],[Akun Jawaban]]="","",IF(Table3[[#This Row],[Akun Jawaban]]=Table4[[#This Row],[Akun]],"Benar","salah")) -> Benar | N6: =IF(Table3[[#This Row],[Debit Jawaban]]="","",IF(Table3[[#This Row],[Debit Jawaban]]=Table4[[#This Row],[Debit (Rp)]],"Benar","salah")) -> Benar | O6: =IF(Table3[[#This Row],[Kredit Jawaban]]="","",IF(Table3[[#This Row],[Kredit Jawaban]]=Table4[[#This Row],[Kredit (Rp)]],"Benar","salah"))
G7: Debit Kas Kecil; kredit Bank. | H7: 2 | I7: 46388 | J7: bank | L7: 20000000 | M7: =IF(Table3[[#This Row],[Akun Jawaban]]="","",IF(Table3[[#This Row],[Akun Jawaban]]=Table4[[#This Row],[Akun]],"Benar","salah")) -> Benar | N7: =IF(Table3[[#This Row],[Debit Jawaban]]="","",IF(Table3[[#This Row],[Debit Jawaban]]=Table4[[#This Row],[Debit (Rp)]],"Benar","salah")) | O7: =IF(Table3[[#This Row],[Kredit Jawaban]]="","",IF(Table3[[#This Row],[Kredit Jawaban]]=Table4[[#This Row],[Kredit (Rp)]],"Benar","salah")) -> Benar
A8: 3 | B8: 46389 | C8: Mudah / Pembelian aset tunai | D8: Perusahaan membeli peralatan toko Rp60.000.000 sebelum PPN. PPN latihan efektif 11%. | E8: Dibayar melalui bank; peralatan siap digunakan. | F8: 60000000 | G8: Debit Peralatan Toko, PPN Masukan; kredit Bank. | H8: 3 | I8: 46389 | J8: peralatan toko | K8: 60000000 | M8: =IF(Table3[[#This Row],[Akun Jawaban]]="","",IF(Table3[[#This Row],[Akun Jawaban]]=Table4[[#This Row],[Akun]],"Benar","salah")) -> Benar | N8: =IF(Table3[[#This Row],[Debit Jawaban]]="","",IF(Table3[[#This Row],[Debit Jawaban]]=Table4[[#This Row],[Debit (Rp)]],"Benar","salah")) -> Benar | O8: =IF(Table3[[#This Row],[Kredit Jawaban]]="","",IF(Table3[[#This Row],[Kredit Jawaban]]=Table4[[#This Row],[Kredit (Rp)]],"Benar","salah"))
G9: Debit Peralatan Toko, PPN Masukan; kredit Bank. | H9: 3 | I9: 46389 | J9: ppn masukan | K9: =11%*60000000 -> 6600000 | M9: =IF(Table3[[#This Row],[Akun Jawaban]]="","",IF(Table3[[#This Row],[Akun Jawaban]]=Table4[[#This Row],[Akun]],"Benar","salah")) -> Benar | N9: =IF(Table3[[#This Row],[Debit Jawaban]]="","",IF(Table3[[#This Row],[Debit Jawaban]]=Table4[[#This Row],[Debit (Rp)]],"Benar","salah")) -> Benar | O9: =IF(Table3[[#This Row],[Kredit Jawaban]]="","",IF(Table3[[#This Row],[Kredit Jawaban]]=Table4[[#This Row],[Kredit (Rp)]],"Benar","salah"))
H10: 3 | I10: 46389 | J10: bank | L10: =SUM(K8:K9) -> 66600000 | M10: =IF(Table3[[#This Row],[Akun Jawaban]]="","",IF(Table3[[#This Row],[Akun Jawaban]]=Table4[[#This Row],[Akun]],"Benar","salah")) -> Benar | N10: =IF(Table3[[#This Row],[Debit Jawaban]]="","",IF(Table3[[#This Row],[Debit Jawaban]]=Table4[[#This Row],[Debit (Rp)]],"Benar","salah")) | O10: =IF(Table3[[#This Row],[Kredit Jawaban]]="","",IF(Table3[[#This Row],[Kredit Jawaban]]=Table4[[#This Row],[Kredit (Rp)]],"Benar","salah")) -> Benar
A11: 4 | B11: 46390 | C11: Mudah / Pembelian aset kredit | D11: Perusahaan membeli peralatan kantor Rp40.000.000 sebelum PPN. PPN latihan efektif 11%. | E11: Satu invoice; belum dibayar. | F11: 40000000 | G11: Debit Peralatan Kantor, PPN Masukan; kredit Utang Usaha. | H11: 4 | I11: 46390 | J11: peralatan kantor | K11: 40000000 | M11: =IF(Table3[[#This Row],[Akun Jawaban]]="","",IF(Table3[[#This Row],[Akun Jawaban]]=Table4[[#This Row],[Akun]],"Benar","salah")) -> Benar | N11: =IF(Table3[[#This Row],[Debit Jawaban]]="","",IF(Table3[[#This Row],[Debit Jawaban]]=Table4[[#This Row],[Debit (Rp)]],"Benar","salah")) -> Benar | O11: =IF(Table3[[#This Row],[Kredit Jawaban]]="","",IF(Table3[[#This Row],[Kredit Jawaban]]=Table4[[#This Row],[Kredit (Rp)]],"Benar","salah"))
G12: Debit Peralatan Kantor, PPN Masukan; kredit Utang Usaha. | H12: 4 | I12: 46390 | J12: ppn masukan | K12: =11%*40000000 -> 4400000 | M12: =IF(Table3[[#This Row],[Akun Jawaban]]="","",IF(Table3[[#This Row],[Akun Jawaban]]=Table4[[#This Row],[Akun]],"Benar","salah")) -> Benar | N12: =IF(Table3[[#This Row],[Debit Jawaban]]="","",IF(Table3[[#This Row],[Debit Jawaban]]=Table4[[#This Row],[Debit (Rp)]],"Benar","salah")) -> Benar | O12: =IF(Table3[[#This Row],[Kredit Jawaban]]="","",IF(Table3[[#This Row],[Kredit Jawaban]]=Table4[[#This Row],[Kredit (Rp)]],"Benar","salah"))
H13: 4 | I13: 46390 | J13: utang usaha | L13: =SUM(K11:K12) -> 44400000 | M13: =IF(Table3[[#This Row],[Akun Jawaban]]="","",IF(Table3[[#This Row],[Akun Jawaban]]=Table4[[#This Row],[Akun]],"Benar","salah")) -> Benar | N13: =IF(Table3[[#This Row],[Debit Jawaban]]="","",IF(Table3[[#This Row],[Debit Jawaban]]=Table4[[#This Row],[Debit (Rp)]],"Benar","salah")) | O13: =IF(Table3[[#This Row],[Kredit Jawaban]]="","",IF(Table3[[#This Row],[Kredit Jawaban]]=Table4[[#This Row],[Kredit (Rp)]],"Benar","salah")) -> Benar
A14: 5 | B14: 46390 | C14: Mudah / Pembelian persediaan kredit | D14: Perusahaan membeli persediaan dari Supplier A secara kredit Rp250.000.000 sebelum PPN. | E14: PPN latihan efektif 11%; satu invoice; belum dibayar. | F14: 250000000 | G14: Debit Persediaan, PPN Masukan; kredit Utang Usaha. | H14: 5 | I14: 46390 | J14: persediaan barang dagang | K14: 250000000 | M14: =IF(Table3[[#This Row],[Akun Jawaban]]="","",IF(Table3[[#This Row],[Akun Jawaban]]=Table4[[#This Row],[Akun]],"Benar","salah")) -> Benar | N14: =IF(Table3[[#This Row],[Debit Jawaban]]="","",IF(Table3[[#This Row],[Debit Jawaban]]=Table4[[#This Row],[Debit (Rp)]],"Benar","salah")) -> Benar | O14: =IF(Table3[[#This Row],[Kredit Jawaban]]="","",IF(Table3[[#This Row],[Kredit Jawaban]]=Table4[[#This Row],[Kredit (Rp)]],"Benar","salah"))
G15: Debit Persediaan, PPN Masukan; kredit Utang Usaha. | H15: 5 | I15: 46390 | J15: ppn masukan | K15: =11%*250000000 -> 27500000 | M15: =IF(Table3[[#This Row],[Akun Jawaban]]="","",IF(Table3[[#This Row],[Akun Jawaban]]=Table4[[#This Row],[Akun]],"Benar","salah")) -> Benar | N15: =IF(Table3[[#This Row],[Debit Jawaban]]="","",IF(Table3[[#This Row],[Debit Jawaban]]=Table4[[#This Row],[Debit (Rp)]],"Benar","salah")) -> Benar | O15: =IF(Table3[[#This Row],[Kredit Jawaban]]="","",IF(Table3[[#This Row],[Kredit Jawaban]]=Table4[[#This Row],[Kredit (Rp)]],"Benar","salah"))
H16: 5 | I16: 46390 | J16: utang usaha | L16: =SUM(K14:K15) -> 277500000 | M16: =IF(Table3[[#This Row],[Akun Jawaban]]="","",IF(Table3[[#This Row],[Akun Jawaban]]=Table4[[#This Row],[Akun]],"Benar","salah")) -> Benar | N16: =IF(Table3[[#This Row],[Debit Jawaban]]="","",IF(Table3[[#This Row],[Debit Jawaban]]=Table4[[#This Row],[Debit (Rp)]],"Benar","salah")) | O16: =IF(Table3[[#This Row],[Kredit Jawaban]]="","",IF(Table3[[#This Row],[Kredit Jawaban]]=Table4[[#This Row],[Kredit (Rp)]],"Benar","salah")) -> Benar
A17: 6 | B17: 46391 | C17: Mudah / Pembelian persediaan tunai | D17: Perusahaan membeli persediaan Rp100.000.000 sebelum PPN dari Supplier B secara kredit. | E17: PPN latihan efektif 11%; termin 14 hari. | F17: 100000000 | G17: Debit Persediaan, PPN Masukan; kredit Utang Usaha. | H17: 6 | I17: 46391 | J17: persediaan barang dagang | K17: 100000000 | M17: =IF(Table3[[#This Row],[Akun Jawaban]]="","",IF(Table3[[#This Row],[Akun Jawaban]]=Table4[[#This Row],[Akun]],"Benar","salah")) -> Benar | N17: =IF(Table3[[#This Row],[Debit Jawaban]]="","",IF(Table3[[#This Row],[Debit Jawaban]]=Table4[[#This Row],[Debit (Rp)]],"Benar","salah")) -> Benar | O17: =IF(Table3[[#This Row],[Kredit Jawaban]]="","",IF(Table3[[#This Row],[Kredit Jawaban]]=Table4[[#This Row],[Kredit (Rp)]],"Benar","salah"))
G18: Debit Persediaan, PPN Masukan; kredit Utang Usaha. | H18: 6 | I18: 46391 | J18: ppn masukan | K18: =11%*100000000 -> 11000000 | M18: =IF(Table3[[#This Row],[Akun Jawaban]]="","",IF(Table3[[#This Row],[Akun Jawaban]]=Table4[[#This Row],[Akun]],"Benar","salah")) -> Benar | N18: =IF(Table3[[#This Row],[Debit Jawaban]]="","",IF(Table3[[#This Row],[Debit Jawaban]]=Table4[[#This Row],[Debit (Rp)]],"Benar","salah")) -> Benar | O18: =IF(Table3[[#This Row],[Kredit Jawaban]]="","",IF(Table3[[#This Row],[Kredit Jawaban]]=Table4[[#This Row],[Kredit (Rp)]],"Benar","salah"))
H19: 6 | I19: 46391 | J19: utang usaha | L19: =SUM(K17:K18) -> 111000000 | M19: =IF(Table3[[#This Row],[Akun Jawaban]]="","",IF(Table3[[#This Row],[Akun Jawaban]]=Table4[[#This Row],[Akun]],"Benar","salah")) -> Benar | N19: =IF(Table3[[#This Row],[Debit Jawaban]]="","",IF(Table3[[#This Row],[Debit Jawaban]]=Table4[[#This Row],[Debit (Rp)]],"Benar","salah")) | O19: =IF(Table3[[#This Row],[Kredit Jawaban]]="","",IF(Table3[[#This Row],[Kredit Jawaban]]=Table4[[#This Row],[Kredit (Rp)]],"Benar","salah")) -> Benar
A20: 7 | B20: 46391 | C20: Mudah / Freight-in | D20: Perusahaan membayar ongkos angkut pembelian Rp4.000.000 melalui bank. Ongkos angkut menambah biaya perolehan persediaan. | E20: Sistem perpetual; freight-in dikapitalisasi. | F20: 4000000 | G20: Debit Persediaan; kredit Bank. | H20: 7 | I20: 46391 | J20: persediaan barang dagang | K20: 4000000 | M20: =IF(Table3[[#This Row],[Akun Jawaban]]="","",IF(Table3[[#This Row],[Akun Jawaban]]=Table4[[#This Row],[Akun]],"Benar","salah")) -> Benar | N20: =IF(Table3[[#This Row],[Debit Jawaban]]="","",IF(Table3[[#This Row],[Debit Jawaban]]=Table4[[#This Row],[Debit (Rp)]],"Benar","salah")) -> Benar | O20: =IF(Table3[[#This Row],[Kredit Jawaban]]="","",IF(Table3[[#This Row],[Kredit Jawaban]]=Table4[[#This Row],[Kredit (Rp)]],"Benar","salah"))
G21: Debit Persediaan; kredit Bank. | H21: 7 | I21: 46391 | J21: bank | L21: 4000000 | M21: =IF(Table3[[#This Row],[Akun Jawaban]]="","",IF(Table3[[#This Row],[Akun Jawaban]]=Table4[[#This Row],[Akun]],"Benar","salah")) -> Benar | N21: =IF(Table3[[#This Row],[Debit Jawaban]]="","",IF(Table3[[#This Row],[Debit Jawaban]]=Table4[[#This Row],[Debit (Rp)]],"Benar","salah")) | O21: =IF(Table3[[#This Row],[Kredit Jawaban]]="","",IF(Table3[[#This Row],[Kredit Jawaban]]=Table4[[#This Row],[Kredit (Rp)]],"Benar","salah")) -> Benar
A22: 8 | B22: 46392 | C22: Mudah / Penjualan tunai | D22: Perusahaan menjual barang secara tunai Rp120.000.000 sebelum PPN. HPP Rp70.000.000. | E22: PPN latihan efektif 11%; perpetual. | F22: 120000000 | G22: Buat dua kelompok jurnal: penjualan + PPN dan HPP + persediaan. | H22: 8 | I22: 46392 | J22: bank | K22: =SUM(L23:L24) -> 133200000 | M22: =IF(Table3[[#This Row],[Akun Jawaban]]="","",IF(Table3[[#This Row],[Akun Jawaban]]=Table4[[#This Row],[Akun]],"Benar","salah")) -> Benar | N22: =IF(Table3[[#This Row],[Debit Jawaban]]="","",IF(Table3[[#This Row],[Debit Jawaban]]=Table4[[#This Row],[Debit (Rp)]],"Benar","salah")) -> Benar | O22: =IF(Table3[[#This Row],[Kredit Jawaban]]="","",IF(Table3[[#This Row],[Kredit Jawaban]]=Table4[[#This Row],[Kredit (Rp)]],"Benar","salah"))
G23: Buat dua kelompok jurnal: penjualan + PPN dan HPP + persediaan. | H23: 8 | I23: 46392 | J23: penjualan | L23: 120000000 | M23: =IF(Table3[[#This Row],[Akun Jawaban]]="","",IF(Table3[[#This Row],[Akun Jawaban]]=Table4[[#This Row],[Akun]],"Benar","salah")) -> Benar | N23: =IF(Table3[[#This Row],[Debit Jawaban]]="","",IF(Table3[[#This Row],[Debit Jawaban]]=Table4[[#This Row],[Debit (Rp)]],"Benar","salah")) | O23: =IF(Table3[[#This Row],[Kredit Jawaban]]="","",IF(Table3[[#This Row],[Kredit Jawaban]]=Table4[[#This Row],[Kredit (Rp)]],"Benar","salah")) -> Benar
H24: 8 | I24: 46392 | J24: ppn keluaran | L24: =11%*120000000 -> 13200000 | M24: =IF(Table3[[#This Row],[Akun Jawaban]]="","",IF(Table3[[#This Row],[Akun Jawaban]]=Table4[[#This Row],[Akun]],"Benar","salah")) -> Benar | N24: =IF(Table3[[#This Row],[Debit Jawaban]]="","",IF(Table3[[#This Row],[Debit Jawaban]]=Table4[[#This Row],[Debit (Rp)]],"Benar","salah")) | O24: =IF(Table3[[#This Row],[Kredit Jawaban]]="","",IF(Table3[[#This Row],[Kredit Jawaban]]=Table4[[#This Row],[Kredit (Rp)]],"Benar","salah")) -> Benar
H25: 8 | I25: 46392 | J25: hpp | K25: 70000000 | M25: =IF(Table3[[#This Row],[Akun Jawaban]]="","",IF(Table3[[#This Row],[Akun Jawaban]]=Table4[[#This Row],[Akun]],"Benar","salah")) -> Benar | N25: =IF(Table3[[#This Row],[Debit Jawaban]]="","",IF(Table3[[#This Row],[Debit Jawaban]]=Table4[[#This Row],[Debit (Rp)]],"Benar","salah")) -> Benar | O25: =IF(Table3[[#This Row],[Kredit Jawaban]]="","",IF(Table3[[#This Row],[Kredit Jawaban]]=Table4[[#This Row],[Kredit (Rp)]],"Benar","salah"))
H26: 8 | I26: 46392 | J26: persediaan barang dagang | L26: 70000000 | M26: =IF(Table3[[#This Row],[Akun Jawaban]]="","",IF(Table3[[#This Row],[Akun Jawaban]]=Table4[[#This Row],[Akun]],"Benar","salah")) -> Benar | N26: =IF(Table3[[#This Row],[Debit Jawaban]]="","",IF(Table3[[#This Row],[Debit Jawaban]]=Table4[[#This Row],[Debit (Rp)]],"Benar","salah")) | O26: =IF(Table3[[#This Row],[Kredit Jawaban]]="","",IF(Table3[[#This Row],[Kredit Jawaban]]=Table4[[#This Row],[Kredit (Rp)]],"Benar","salah")) -> Benar
A27: 9 | B27: 46393 | C27: Mudah / Penjualan kredit | D27: Perusahaan menjual barang secara kredit kepada Pelanggan B Rp160.000.000 sebelum PPN. HPP Rp95.000.000. | E27: PPN latihan efektif 11%; termin 30 hari. | F27: 160000000 | G27: Debit Piutang; kredit Penjualan dan PPN Keluaran; lalu HPP dan Persediaan. | H27: 9 | I27: 46393 | J27: piutang usaha | K27: =SUM(L28:L29) -> 177600000 | M27: =IF(Table3[[#This Row],[Akun Jawaban]]="","",IF(Table3[[#This Row],[Akun Jawaban]]=Table4[[#This Row],[Akun]],"Benar","salah")) -> Benar | N27: =IF(Table3[[#This Row],[Debit Jawaban]]="","",IF(Table3[[#This Row],[Debit Jawaban]]=Table4[[#This Row],[Debit (Rp)]],"Benar","salah")) -> Benar | O27: =IF(Table3[[#This Row],[Kredit Jawaban]]="","",IF(Table3[[#This Row],[Kredit Jawaban]]=Table4[[#This Row],[Kredit (Rp)]],"Benar","salah"))
G28: Debit Piutang; kredit Penjualan dan PPN Keluaran; lalu HPP dan Persediaan. | H28: 9 | I28: 46393 | J28: penjualan | L28: 160000000 | M28: =IF(Table3[[#This Row],[Akun Jawaban]]="","",IF(Table3[[#This Row],[Akun Jawaban]]=Table4[[#This Row],[Akun]],"Benar","salah")) -> Benar | N28: =IF(Table3[[#This Row],[Debit Jawaban]]="","",IF(Table3[[#This Row],[Debit Jawaban]]=Table4[[#This Row],[Debit (Rp)]],"Benar","salah")) | O28: =IF(Table3[[#This Row],[Kredit Jawaban]]="","",IF(Table3[[#This Row],[Kredit Jawaban]]=Table4[[#This Row],[Kredit (Rp)]],"Benar","salah")) -> Benar
H29: 9 | I29: 46393 | J29: ppn keluaran | L29: =11%*L28 -> 17600000 | M29: =IF(Table3[[#This Row],[Akun Jawaban]]="","",IF(Table3[[#This Row],[Akun Jawaban]]=Table4[[#This Row],[Akun]],"Benar","salah")) -> Benar | N29: =IF(Table3[[#This Row],[Debit Jawaban]]="","",IF(Table3[[#This Row],[Debit Jawaban]]=Table4[[#This Row],[Debit (Rp)]],"Benar","salah")) | O29: =IF(Table3[[#This Row],[Kredit Jawaban]]="","",IF(Table3[[#This Row],[Kredit Jawaban]]=Table4[[#This Row],[Kredit (Rp)]],"Benar","salah")) -> Benar
H30: 9 | I30: 46393 | J30: hpp | K30: 95000000 | M30: =IF(Table3[[#This Row],[Akun Jawaban]]="","",IF(Table3[[#This Row],[Akun Jawaban]]=Table4[[#This Row],[Akun]],"Benar","salah")) -> Benar | N30: =IF(Table3[[#This Row],[Debit Jawaban]]="","",IF(Table3[[#This Row],[Debit Jawaban]]=Table4[[#This Row],[Debit (Rp)]],"Benar","salah")) -> Benar | O30: =IF(Table3[[#This Row],[Kredit Jawaban]]="","",IF(Table3[[#This Row],[Kredit Jawaban]]=Table4[[#This Row],[Kredit (Rp)]],"Benar","salah"))
H31: 9 | I31: 46393 | J31: persediaan barang dagang | L31: 95000000 | M31: =IF(Table3[[#This Row],[Akun Jawaban]]="","",IF(Table3[[#This Row],[Akun Jawaban]]=Table4[[#This Row],[Akun]],"Benar","salah")) -> Benar | N31: =IF(Table3[[#This Row],[Debit Jawaban]]="","",IF(Table3[[#This Row],[Debit Jawaban]]=Table4[[#This Row],[Debit (Rp)]],"Benar","salah")) | O31: =IF(Table3[[#This Row],[Kredit Jawaban]]="","",IF(Table3[[#This Row],[Kredit Jawaban]]=Table4[[#This Row],[Kredit (Rp)]],"Benar","salah")) -> Benar
A32: 10 | B32: 46394 | C32: Mudah / Penerimaan piutang | D32: Pelanggan B membayar piutang Rp80.000.000 melalui bank. | E32: Tidak ada potongan. | F32: 80000000 | G32: Debit Bank; kredit Piutang Usaha. | H32: 10 | I32: 46394 | J32: bank | K32: 80000000 | M32: =IF(Table3[[#This Row],[Akun Jawaban]]="","",IF(Table3[[#This Row],[Akun Jawaban]]=Table4[[#This Row],[Akun]],"Benar","salah")) -> Benar | N32: =IF(Table3[[#This Row],[Debit Jawaban]]="","",IF(Table3[[#This Row],[Debit Jawaban]]=Table4[[#This Row],[Debit (Rp)]],"Benar","salah")) -> Benar | O32: =IF(Table3[[#This Row],[Kredit Jawaban]]="","",IF(Table3[[#This Row],[Kredit Jawaban]]=Table4[[#This Row],[Kredit (Rp)]],"Benar","salah"))
G33: Debit Bank; kredit Piutang Usaha. | H33: 10 | I33: 46394 | J33: piutang usaha | L33: 80000000 | M33: =IF(Table3[[#This Row],[Akun Jawaban]]="","",IF(Table3[[#This Row],[Akun Jawaban]]=Table4[[#This Row],[Akun]],"Benar","salah")) -> Benar | N33: =IF(Table3[[#This Row],[Debit Jawaban]]="","",IF(Table3[[#This Row],[Debit Jawaban]]=Table4[[#This Row],[Debit (Rp)]],"Benar","salah")) | O33: =IF(Table3[[#This Row],[Kredit Jawaban]]="","",IF(Table3[[#This Row],[Kredit Jawaban]]=Table4[[#This Row],[Kredit (Rp)]],"Benar","salah")) -> Benar
A34: 11 | B34: 46395 | C34: Mudah / Pelunasan utang | D34: Perusahaan membayar Utang Usaha kepada Supplier A sebesar Rp100.000.000 melalui bank. | E34: Pelunasan sebagian. | F34: 100000000 | G34: Debit Utang Usaha; kredit Bank. | H34: 11 | I34: 46395 | J34: utang usaha | K34: 100000000 | M34: =IF(Table3[[#This Row],[Akun Jawaban]]="","",IF(Table3[[#This Row],[Akun Jawaban]]=Table4[[#This Row],[Akun]],"Benar","salah")) -> Benar | N34: =IF(Table3[[#This Row],[Debit Jawaban]]="","",IF(Table3[[#This Row],[Debit Jawaban]]=Table4[[#This Row],[Debit (Rp)]],"Benar","salah")) -> Benar | O34: =IF(Table3[[#This Row],[Kredit Jawaban]]="","",IF(Table3[[#This Row],[Kredit Jawaban]]=Table4[[#This Row],[Kredit (Rp)]],"Benar","salah"))
G35: Debit Utang Usaha; kredit Bank. | H35: 11 | I35: 46395 | J35: bank | L35: 100000000 | M35: =IF(Table3[[#This Row],[Akun Jawaban]]="","",IF(Table3[[#This Row],[Akun Jawaban]]=Table4[[#This Row],[Akun]],"Benar","salah")) -> Benar | N35: =IF(Table3[[#This Row],[Debit Jawaban]]="","",IF(Table3[[#This Row],[Debit Jawaban]]=Table4[[#This Row],[Debit (Rp)]],"Benar","salah")) | O35: =IF(Table3[[#This Row],[Kredit Jawaban]]="","",IF(Table3[[#This Row],[Kredit Jawaban]]=Table4[[#This Row],[Kredit (Rp)]],"Benar","salah")) -> Benar
A36: 12 | B36: 46395 | C36: Mudah / Uang muka pelanggan | D36: Pelanggan C membayar uang muka Rp44.440.000 melalui bank untuk pesanan barang yang akan dikirim kemudian. | E36: Uang muka dicatat sebagai liabilitas sampai barang diserahkan. | F36: 44440000 | G36: Debit Bank; kredit Uang Muka Pelanggan. | H36: 12 | I36: 46395 | J36: bank | K36: 44440000 | M36: =IF(Table3[[#This Row],[Akun Jawaban]]="","",IF(Table3[[#This Row],[Akun Jawaban]]=Table4[[#This Row],[Akun]],"Benar","salah")) -> Benar | N36: =IF(Table3[[#This Row],[Debit Jawaban]]="","",IF(Table3[[#This Row],[Debit Jawaban]]=Table4[[#This Row],[Debit (Rp)]],"Benar","salah")) -> Benar | O36: =IF(Table3[[#This Row],[Kredit Jawaban]]="","",IF(Table3[[#This Row],[Kredit Jawaban]]=Table4[[#This Row],[Kredit (Rp)]],"Benar","salah"))
G37: Debit Bank; kredit Uang Muka Pelanggan. | H37: 12 | I37: 46395 | J37: Uang Muka Pelanggan | L37: 44440000 | M37: =IF(Table3[[#This Row],[Akun Jawaban]]="","",IF(Table3[[#This Row],[Akun Jawaban]]=Table4[[#This Row],[Akun]],"Benar","salah")) -> Benar | N37: =IF(Table3[[#This Row],[Debit Jawaban]]="","",IF(Table3[[#This Row],[Debit Jawaban]]=Table4[[#This Row],[Debit (Rp)]],"Benar","salah")) | O37: =IF(Table3[[#This Row],[Kredit Jawaban]]="","",IF(Table3[[#This Row],[Kredit Jawaban]]=Table4[[#This Row],[Kredit (Rp)]],"Benar","salah")) -> Benar
A38: 13 | B38: 46396 | C38: Mudah / Retur pembelian | D38: Perusahaan mengembalikan barang kepada Supplier A senilai Rp15.000.000 sebelum PPN karena rusak. | E38: PPN 11% dibatalkan; retur mengurangi utang. | F38: 15000000 | G38: Debit Utang Usaha; kredit Persediaan dan PPN Masukan. | H38: 13 | I38: 46396 | J38: utang usaha | K38: =SUM(L39:L40) -> 16650000 | M38: =IF(Table3[[#This Row],[Akun Jawaban]]="","",IF(Table3[[#This Row],[Akun Jawaban]]=Table4[[#This Row],[Akun]],"Benar","salah")) -> Benar | N38: =IF(Table3[[#This Row],[Debit Jawaban]]="","",IF(Table3[[#This Row],[Debit Jawaban]]=Table4[[#This Row],[Debit (Rp)]],"Benar","salah")) -> Benar | O38: =IF(Table3[[#This Row],[Kredit Jawaban]]="","",IF(Table3[[#This Row],[Kredit Jawaban]]=Table4[[#This Row],[Kredit (Rp)]],"Benar","salah"))
G39: Debit Utang Usaha; kredit Persediaan dan PPN Masukan. | H39: 13 | I39: 46396 | J39: persediaan barang dagang | L39: 15000000 | M39: =IF(Table3[[#This Row],[Akun Jawaban]]="","",IF(Table3[[#This Row],[Akun Jawaban]]=Table4[[#This Row],[Akun]],"Benar","salah")) -> Benar | N39: =IF(Table3[[#This Row],[Debit Jawaban]]="","",IF(Table3[[#This Row],[Debit Jawaban]]=Table4[[#This Row],[Debit (Rp)]],"Benar","salah")) | O39: =IF(Table3[[#This Row],[Kredit Jawaban]]="","",IF(Table3[[#This Row],[Kredit Jawaban]]=Table4[[#This Row],[Kredit (Rp)]],"Benar","salah")) -> Benar
H40: 13 | I40: 46396 | J40: ppn masukan | L40: =11%*15000000 -> 1650000 | M40: =IF(Table3[[#This Row],[Akun Jawaban]]="","",IF(Table3[[#This Row],[Akun Jawaban]]=Table4[[#This Row],[Akun]],"Benar","salah")) -> Benar | N40: =IF(Table3[[#This Row],[Debit Jawaban]]="","",IF(Table3[[#This Row],[Debit Jawaban]]=Table4[[#This Row],[Debit (Rp)]],"Benar","salah")) | O40: =IF(Table3[[#This Row],[Kredit Jawaban]]="","",IF(Table3[[#This Row],[Kredit Jawaban]]=Table4[[#This Row],[Kredit (Rp)]],"Benar","salah")) -> Benar
A41: 14 | B41: 46397 | C41: Mudah / Retur penjualan | D41: Pelanggan B mengembalikan barang yang sebelumnya dijual seharga Rp10.000.000 sebelum PPN; nilai HPP barang yang kembali Rp6.000.000. | E41: PPN 11%; kembalinya barang memulihkan persediaan. | F41: 10000000 | G41: Catat retur + pembalikan PPN dan pemulihan persediaan/HPP. | H41: 14 | I41: 46397 | J41: Retur Penjualan | K41: 10000000 | M41: =IF(Table3[[#This Row],[Akun Jawaban]]="","",IF(Table3[[#This Row],[Akun Jawaban]]=Table4[[#This Row],[Akun]],"Benar","salah")) -> Benar | N41: =IF(Table3[[#This Row],[Debit Jawaban]]="","",IF(Table3[[#This Row],[Debit Jawaban]]=Table4[[#This Row],[Debit (Rp)]],"Benar","salah")) -> Benar | O41: =IF(Table3[[#This Row],[Kredit Jawaban]]="","",IF(Table3[[#This Row],[Kredit Jawaban]]=Table4[[#This Row],[Kredit (Rp)]],"Benar","salah"))
G42: Catat retur + pembalikan PPN dan pemulihan persediaan/HPP. | H42: 14 | I42: 46397 | J42: ppn keluaran | K42: =11%*K41 -> 1100000 | M42: =IF(Table3[[#This Row],[Akun Jawaban]]="","",IF(Table3[[#This Row],[Akun Jawaban]]=Table4[[#This Row],[Akun]],"Benar","salah")) -> Benar | N42: =IF(Table3[[#This Row],[Debit Jawaban]]="","",IF(Table3[[#This Row],[Debit Jawaban]]=Table4[[#This Row],[Debit (Rp)]],"Benar","salah")) -> Benar | O42: =IF(Table3[[#This Row],[Kredit Jawaban]]="","",IF(Table3[[#This Row],[Kredit Jawaban]]=Table4[[#This Row],[Kredit (Rp)]],"Benar","salah"))
H43: 14 | I43: 46397 | J43: piutang usaha | L43: =SUM(K41:K42) -> 11100000 | M43: =IF(Table3[[#This Row],[Akun Jawaban]]="","",IF(Table3[[#This Row],[Akun Jawaban]]=Table4[[#This Row],[Akun]],"Benar","salah")) -> Benar | N43: =IF(Table3[[#This Row],[Debit Jawaban]]="","",IF(Table3[[#This Row],[Debit Jawaban]]=Table4[[#This Row],[Debit (Rp)]],"Benar","salah")) | O43: =IF(Table3[[#This Row],[Kredit Jawaban]]="","",IF(Table3[[#This Row],[Kredit Jawaban]]=Table4[[#This Row],[Kredit (Rp)]],"Benar","salah")) -> Benar
H44: 14 | I44: 46397 | J44: persediaan barang dagang | K44: 6000000 | M44: =IF(Table3[[#This Row],[Akun Jawaban]]="","",IF(Table3[[#This Row],[Akun Jawaban]]=Table4[[#This Row],[Akun]],"Benar","salah")) -> Benar | N44: =IF(Table3[[#This Row],[Debit Jawaban]]="","",IF(Table3[[#This Row],[Debit Jawaban]]=Table4[[#This Row],[Debit (Rp)]],"Benar","salah")) -> Benar | O44: =IF(Table3[[#This Row],[Kredit Jawaban]]="","",IF(Table3[[#This Row],[Kredit Jawaban]]=Table4[[#This Row],[Kredit (Rp)]],"Benar","salah"))
H45: 14 | I45: 46397 | J45: hpp | L45: 6000000 | M45: =IF(Table3[[#This Row],[Akun Jawaban]]="","",IF(Table3[[#This Row],[Akun Jawaban]]=Table4[[#This Row],[Akun]],"Benar","salah")) -> Benar | N45: =IF(Table3[[#This Row],[Debit Jawaban]]="","",IF(Table3[[#This Row],[Debit Jawaban]]=Table4[[#This Row],[Debit (Rp)]],"Benar","salah")) | O45: =IF(Table3[[#This Row],[Kredit Jawaban]]="","",IF(Table3[[#This Row],[Kredit Jawaban]]=Table4[[#This Row],[Kredit (Rp)]],"Benar","salah")) -> Benar
A46: 15 | B46: 46397 | C46: Mudah / Freight-out | D46: Perusahaan membayar ongkos pengiriman penjualan Rp2.500.000 melalui bank. | E46: Freight-out adalah beban penjualan. | F46: 2500000 | G46: Debit Beban Pengiriman Penjualan; kredit Bank. | H46: 15 | I46: 46397 | J46: beban pengiriman penjualan | K46: 2500000 | M46: =IF(Table3[[#This Row],[Akun Jawaban]]="","",IF(Table3[[#This Row],[Akun Jawaban]]=Table4[[#This Row],[Akun]],"Benar","salah")) -> Benar | N46: =IF(Table3[[#This Row],[Debit Jawaban]]="","",IF(Table3[[#This Row],[Debit Jawaban]]=Table4[[#This Row],[Debit (Rp)]],"Benar","salah")) -> Benar | O46: =IF(Table3[[#This Row],[Kredit Jawaban]]="","",IF(Table3[[#This Row],[Kredit Jawaban]]=Table4[[#This Row],[Kredit (Rp)]],"Benar","salah"))
G47: Debit Beban Pengiriman Penjualan; kredit Bank. | H47: 15 | I47: 46397 | J47: bank | L47: 2500000 | M47: =IF(Table3[[#This Row],[Akun Jawaban]]="","",IF(Table3[[#This Row],[Akun Jawaban]]=Table4[[#This Row],[Akun]],"Benar","salah")) -> Benar | N47: =IF(Table3[[#This Row],[Debit Jawaban]]="","",IF(Table3[[#This Row],[Debit Jawaban]]=Table4[[#This Row],[Debit (Rp)]],"Benar","salah")) | O47: =IF(Table3[[#This Row],[Kredit Jawaban]]="","",IF(Table3[[#This Row],[Kredit Jawaban]]=Table4[[#This Row],[Kredit (Rp)]],"Benar","salah")) -> Benar
A48: 16 | B48: 46398 | C48: Mudah / Iklan dibayar di muka | D48: Perusahaan membayar kontrak iklan 12 bulan sebesar Rp12.000.000 melalui bank. | E48: Manfaat mulai Februari; seluruhnya masih prepaid pada 31 Januari. | F48: 12000000 | G48: Debit Iklan Dibayar di Muka; kredit Bank. | H48: 16 | I48: 46398 | J48: iklan dibayar di muka | K48: 12000000 | M48: =IF(Table3[[#This Row],[Akun Jawaban]]="","",IF(Table3[[#This Row],[Akun Jawaban]]=Table4[[#This Row],[Akun]],"Benar","salah")) -> Benar | N48: =IF(Table3[[#This Row],[Debit Jawaban]]="","",IF(Table3[[#This Row],[Debit Jawaban]]=Table4[[#This Row],[Debit (Rp)]],"Benar","salah")) -> Benar | O48: =IF(Table3[[#This Row],[Kredit Jawaban]]="","",IF(Table3[[#This Row],[Kredit Jawaban]]=Table4[[#This Row],[Kredit (Rp)]],"Benar","salah"))
G49: Debit Iklan Dibayar di Muka; kredit Bank. | H49: 16 | I49: 46398 | J49: bank | L49: 12000000 | M49: =IF(Table3[[#This Row],[Akun Jawaban]]="","",IF(Table3[[#This Row],[Akun Jawaban]]=Table4[[#This Row],[Akun]],"Benar","salah")) -> Benar | N49: =IF(Table3[[#This Row],[Debit Jawaban]]="","",IF(Table3[[#This Row],[Debit Jawaban]]=Table4[[#This Row],[Debit (Rp)]],"Benar","salah")) | O49: =IF(Table3[[#This Row],[Kredit Jawaban]]="","",IF(Table3[[#This Row],[Kredit Jawaban]]=Table4[[#This Row],[Kredit (Rp)]],"Benar","salah")) -> Benar
A50: 17 | B50: 46398 | C50: Mudah / Sewa dibayar di muka | D50: Perusahaan membayar sewa toko Rp18.000.000 untuk tiga bulan melalui bank. | E50: Manfaat sewa dimulai Januari; penyesuaian akan menghitung bagian yang terpakai. | F50: 18000000 | G50: Debit Sewa Dibayar di Muka; kredit Bank. | H50: 17 | I50: 46398 | J50: sewa dibayar di muka | K50: 18000000 | M50: =IF(Table3[[#This Row],[Akun Jawaban]]="","",IF(Table3[[#This Row],[Akun Jawaban]]=Table4[[#This Row],[Akun]],"Benar","salah")) -> Benar | N50: =IF(Table3[[#This Row],[Debit Jawaban]]="","",IF(Table3[[#This Row],[Debit Jawaban]]=Table4[[#This Row],[Debit (Rp)]],"Benar","salah")) -> Benar | O50: =IF(Table3[[#This Row],[Kredit Jawaban]]="","",IF(Table3[[#This Row],[Kredit Jawaban]]=Table4[[#This Row],[Kredit (Rp)]],"Benar","salah"))
G51: Debit Sewa Dibayar di Muka; kredit Bank. | H51: 17 | I51: 46398 | J51: bank | L51: 18000000 | M51: =IF(Table3[[#This Row],[Akun Jawaban]]="","",IF(Table3[[#This Row],[Akun Jawaban]]=Table4[[#This Row],[Akun]],"Benar","salah")) -> Benar | N51: =IF(Table3[[#This Row],[Debit Jawaban]]="","",IF(Table3[[#This Row],[Debit Jawaban]]=Table4[[#This Row],[Debit (Rp)]],"Benar","salah")) | O51: =IF(Table3[[#This Row],[Kredit Jawaban]]="","",IF(Table3[[#This Row],[Kredit Jawaban]]=Table4[[#This Row],[Kredit (Rp)]],"Benar","salah")) -> Benar
A52: 18 | B52: 46399 | C52: Mudah / Asuransi dibayar di muka | D52: Perusahaan membayar premi asuransi enam bulan Rp6.000.000 melalui bank. | E52: Manfaat mulai Januari; penyesuaian satu bulan akan dibuat. | F52: 6000000 | G52: Debit Asuransi Dibayar di Muka; kredit Bank. | H52: 18 | I52: 46399 | J52: asuransi dibayar di muka | K52: 6000000 | M52: =IF(Table3[[#This Row],[Akun Jawaban]]="","",IF(Table3[[#This Row],[Akun Jawaban]]=Table4[[#This Row],[Akun]],"Benar","salah")) -> Benar | N52: =IF(Table3[[#This Row],[Debit Jawaban]]="","",IF(Table3[[#This Row],[Debit Jawaban]]=Table4[[#This Row],[Debit (Rp)]],"Benar","salah")) -> Benar | O52: =IF(Table3[[#This Row],[Kredit Jawaban]]="","",IF(Table3[[#This Row],[Kredit Jawaban]]=Table4[[#This Row],[Kredit (Rp)]],"Benar","salah"))
G53: Debit Asuransi Dibayar di Muka; kredit Bank. | H53: 18 | I53: 46399 | J53: bank | L53: 6000000 | M53: =IF(Table3[[#This Row],[Akun Jawaban]]="","",IF(Table3[[#This Row],[Akun Jawaban]]=Table4[[#This Row],[Akun]],"Benar","salah")) -> Benar | N53: =IF(Table3[[#This Row],[Debit Jawaban]]="","",IF(Table3[[#This Row],[Debit Jawaban]]=Table4[[#This Row],[Debit (Rp)]],"Benar","salah")) | O53: =IF(Table3[[#This Row],[Kredit Jawaban]]="","",IF(Table3[[#This Row],[Kredit Jawaban]]=Table4[[#This Row],[Kredit (Rp)]],"Benar","salah")) -> Benar
A54: 19 | B54: 46399 | C54: Mudah / Top-up kas kecil | D54: Kas kecil diisi kembali Rp10.000.000 dari bank. | E54: Sistem imprest; perpindahan kas. | F54: 10000000 | G54: Debit Kas Kecil; kredit Bank. | H54: 19 | I54: 46399 | J54: kas kecil | K54: 10000000 | M54: =IF(Table3[[#This Row],[Akun Jawaban]]="","",IF(Table3[[#This Row],[Akun Jawaban]]=Table4[[#This Row],[Akun]],"Benar","salah")) -> Benar | N54: =IF(Table3[[#This Row],[Debit Jawaban]]="","",IF(Table3[[#This Row],[Debit Jawaban]]=Table4[[#This Row],[Debit (Rp)]],"Benar","salah")) -> Benar | O54: =IF(Table3[[#This Row],[Kredit Jawaban]]="","",IF(Table3[[#This Row],[Kredit Jawaban]]=Table4[[#This Row],[Kredit (Rp)]],"Benar","salah"))
G55: Debit Kas Kecil; kredit Bank. | H55: 19 | I55: 46399 | J55: bank | L55: 10000000 | M55: =IF(Table3[[#This Row],[Akun Jawaban]]="","",IF(Table3[[#This Row],[Akun Jawaban]]=Table4[[#This Row],[Akun]],"Benar","salah")) -> Benar | N55: =IF(Table3[[#This Row],[Debit Jawaban]]="","",IF(Table3[[#This Row],[Debit Jawaban]]=Table4[[#This Row],[Debit (Rp)]],"Benar","salah")) | O55: =IF(Table3[[#This Row],[Kredit Jawaban]]="","",IF(Table3[[#This Row],[Kredit Jawaban]]=Table4[[#This Row],[Kredit (Rp)]],"Benar","salah")) -> Benar
A56: 20 | B56: 46400 | C56: Mudah / Pembayaran utilitas | D56: Perusahaan membayar listrik dan air Rp3.200.000 melalui bank. | E56: Tidak ada PPN dalam soal. | F56: 3200000 | G56: Debit Beban Utilitas; kredit Bank. | H56: 20 | I56: 46400 | J56: beban utilitas | K56: 3200000 | M56: =IF(Table3[[#This Row],[Akun Jawaban]]="","",IF(Table3[[#This Row],[Akun Jawaban]]=Table4[[#This Row],[Akun]],"Benar","salah")) -> Benar | N56: =IF(Table3[[#This Row],[Debit Jawaban]]="","",IF(Table3[[#This Row],[Debit Jawaban]]=Table4[[#This Row],[Debit (Rp)]],"Benar","salah")) -> Benar | O56: =IF(Table3[[#This Row],[Kredit Jawaban]]="","",IF(Table3[[#This Row],[Kredit Jawaban]]=Table4[[#This Row],[Kredit (Rp)]],"Benar","salah"))
G57: Debit Beban Utilitas; kredit Bank. | H57: 20 | I57: 46400 | J57: bank | L57: 3200000 | M57: =IF(Table3[[#This Row],[Akun Jawaban]]="","",IF(Table3[[#This Row],[Akun Jawaban]]=Table4[[#This Row],[Akun]],"Benar","salah")) -> Benar | N57: =IF(Table3[[#This Row],[Debit Jawaban]]="","",IF(Table3[[#This Row],[Debit Jawaban]]=Table4[[#This Row],[Debit (Rp)]],"Benar","salah")) | O57: =IF(Table3[[#This Row],[Kredit Jawaban]]="","",IF(Table3[[#This Row],[Kredit Jawaban]]=Table4[[#This Row],[Kredit (Rp)]],"Benar","salah")) -> Benar
A58: 21 | B58: 46400 | C58: Mudah / Pembelian perlengkapan tunai | D58: Perusahaan membeli perlengkapan/ATK Rp2.000.000 dan membayar melalui kas kecil. | E58: Dicatat sebagai aset perlengkapan terlebih dahulu. | F58: 2000000 | G58: Debit Perlengkapan; kredit Kas Kecil. | H58: 21 | I58: 46400 | J58: perlengkapan | K58: 2000000 | M58: =IF(Table3[[#This Row],[Akun Jawaban]]="","",IF(Table3[[#This Row],[Akun Jawaban]]=Table4[[#This Row],[Akun]],"Benar","salah")) -> Benar | N58: =IF(Table3[[#This Row],[Debit Jawaban]]="","",IF(Table3[[#This Row],[Debit Jawaban]]=Table4[[#This Row],[Debit (Rp)]],"Benar","salah")) -> Benar | O58: =IF(Table3[[#This Row],[Kredit Jawaban]]="","",IF(Table3[[#This Row],[Kredit Jawaban]]=Table4[[#This Row],[Kredit (Rp)]],"Benar","salah"))
G59: Debit Perlengkapan; kredit Kas Kecil. | H59: 21 | I59: 46400 | J59: kas kecil | L59: 2000000 | M59: =IF(Table3[[#This Row],[Akun Jawaban]]="","",IF(Table3[[#This Row],[Akun Jawaban]]=Table4[[#This Row],[Akun]],"Benar","salah")) -> Benar | N59: =IF(Table3[[#This Row],[Debit Jawaban]]="","",IF(Table3[[#This Row],[Debit Jawaban]]=Table4[[#This Row],[Debit (Rp)]],"Benar","salah")) | O59: =IF(Table3[[#This Row],[Kredit Jawaban]]="","",IF(Table3[[#This Row],[Kredit Jawaban]]=Table4[[#This Row],[Kredit (Rp)]],"Benar","salah")) -> Benar
A60: 22 | B60: 46401 | C60: Menengah / Jasa profesional + PPh23 | D60: Perusahaan menerima tagihan jasa profesional Rp8.000.000 + PPN latihan 11%. PPh 23 2% dipotong dari imbalan jasa. | E60: PPh 23 = 2% x Rp8.000.000 = Rp160.000. Sisa dibayar melalui bank. | F60: 8000000 | G60: Debit Beban Jasa Profesional dan PPN; kredit Utang PPh23 dan Bank. | H60: 22 | I60: 46401 | J60: beban jasa profesional | K60: 8000000 | M60: =IF(Table3[[#This Row],[Akun Jawaban]]="","",IF(Table3[[#This Row],[Akun Jawaban]]=Table4[[#This Row],[Akun]],"Benar","salah")) -> Benar | N60: =IF(Table3[[#This Row],[Debit Jawaban]]="","",IF(Table3[[#This Row],[Debit Jawaban]]=Table4[[#This Row],[Debit (Rp)]],"Benar","salah")) -> Benar | O60: =IF(Table3[[#This Row],[Kredit Jawaban]]="","",IF(Table3[[#This Row],[Kredit Jawaban]]=Table4[[#This Row],[Kredit (Rp)]],"Benar","salah"))
G61: Debit Beban Jasa Profesional dan PPN; kredit Utang PPh23 dan Bank. | H61: 22 | I61: 46401 | J61: ppn masukan | K61: =11%*K60 -> 880000 | M61: =IF(Table3[[#This Row],[Akun Jawaban]]="","",IF(Table3[[#This Row],[Akun Jawaban]]=Table4[[#This Row],[Akun]],"Benar","salah")) -> Benar | N61: =IF(Table3[[#This Row],[Debit Jawaban]]="","",IF(Table3[[#This Row],[Debit Jawaban]]=Table4[[#This Row],[Debit (Rp)]],"Benar","salah")) -> Benar | O61: =IF(Table3[[#This Row],[Kredit Jawaban]]="","",IF(Table3[[#This Row],[Kredit Jawaban]]=Table4[[#This Row],[Kredit (Rp)]],"Benar","salah"))
H62: 22 | I62: 46401 | J62: utang pph 23 | L62: =2%*K60 -> 160000 | M62: =IF(Table3[[#This Row],[Akun Jawaban]]="","",IF(Table3[[#This Row],[Akun Jawaban]]=Table4[[#This Row],[Akun]],"Benar","salah")) -> Benar | N62: =IF(Table3[[#This Row],[Debit Jawaban]]="","",IF(Table3[[#This Row],[Debit Jawaban]]=Table4[[#This Row],[Debit (Rp)]],"Benar","salah")) | O62: =IF(Table3[[#This Row],[Kredit Jawaban]]="","",IF(Table3[[#This Row],[Kredit Jawaban]]=Table4[[#This Row],[Kredit (Rp)]],"Benar","salah")) -> Benar
H63: 22 | I63: 46401 | J63: bank | L63: =SUM(K60,K61-L62) -> 8720000 | M63: =IF(Table3[[#This Row],[Akun Jawaban]]="","",IF(Table3[[#This Row],[Akun Jawaban]]=Table4[[#This Row],[Akun]],"Benar","salah")) -> Benar | N63: =IF(Table3[[#This Row],[Debit Jawaban]]="","",IF(Table3[[#This Row],[Debit Jawaban]]=Table4[[#This Row],[Debit (Rp)]],"Benar","salah")) | O63: =IF(Table3[[#This Row],[Kredit Jawaban]]="","",IF(Table3[[#This Row],[Kredit Jawaban]]=Table4[[#This Row],[Kredit (Rp)]],"Benar","salah")) -> Benar
A64: 23 | B64: 46401 | C64: Menengah / Sewa tanah/bangunan + PPh Final | D64: Perusahaan membayar sewa gudang Rp20.000.000. Atas sewa tanah/bangunan, PPh Final 4(2) 10% dipotong dari jumlah bruto. | E64: Dalam soal latihan, PPN efektif 11% juga dikenakan; PPh Final = Rp2.000.000. | F64: 20000000 | G64: Debit Beban Sewa dan PPN; kredit Utang PPh Final dan Bank. | H64: 23 | I64: 46401 | J64: beban sewa | K64: 20000000 | M64: =IF(Table3[[#This Row],[Akun Jawaban]]="","",IF(Table3[[#This Row],[Akun Jawaban]]=Table4[[#This Row],[Akun]],"Benar","salah")) -> Benar | N64: =IF(Table3[[#This Row],[Debit Jawaban]]="","",IF(Table3[[#This Row],[Debit Jawaban]]=Table4[[#This Row],[Debit (Rp)]],"Benar","salah")) -> Benar | O64: =IF(Table3[[#This Row],[Kredit Jawaban]]="","",IF(Table3[[#This Row],[Kredit Jawaban]]=Table4[[#This Row],[Kredit (Rp)]],"Benar","salah"))
G65: Debit Beban Sewa dan PPN; kredit Utang PPh Final dan Bank. | H65: 23 | I65: 46401 | J65: ppn masukan | K65: =11%*K64 -> 2200000 | M65: =IF(Table3[[#This Row],[Akun Jawaban]]="","",IF(Table3[[#This Row],[Akun Jawaban]]=Table4[[#This Row],[Akun]],"Benar","salah")) -> Benar | N65: =IF(Table3[[#This Row],[Debit Jawaban]]="","",IF(Table3[[#This Row],[Debit Jawaban]]=Table4[[#This Row],[Debit (Rp)]],"Benar","salah")) -> Benar | O65: =IF(Table3[[#This Row],[Kredit Jawaban]]="","",IF(Table3[[#This Row],[Kredit Jawaban]]=Table4[[#This Row],[Kredit (Rp)]],"Benar","salah"))
H66: 23 | I66: 46401 | J66: Utang PPh Final 4(2) | L66: 2000000 | M66: =IF(Table3[[#This Row],[Akun Jawaban]]="","",IF(Table3[[#This Row],[Akun Jawaban]]=Table4[[#This Row],[Akun]],"Benar","salah")) -> Benar | N66: =IF(Table3[[#This Row],[Debit Jawaban]]="","",IF(Table3[[#This Row],[Debit Jawaban]]=Table4[[#This Row],[Debit (Rp)]],"Benar","salah")) | O66: =IF(Table3[[#This Row],[Kredit Jawaban]]="","",IF(Table3[[#This Row],[Kredit Jawaban]]=Table4[[#This Row],[Kredit (Rp)]],"Benar","salah")) -> Benar
H67: 23 | I67: 46401 | J67: Bank | L67: =SUM(K64,K65-L66) -> 20200000 | M67: =IF(Table3[[#This Row],[Akun Jawaban]]="","",IF(Table3[[#This Row],[Akun Jawaban]]=Table4[[#This Row],[Akun]],"Benar","salah")) -> Benar | N67: =IF(Table3[[#This Row],[Debit Jawaban]]="","",IF(Table3[[#This Row],[Debit Jawaban]]=Table4[[#This Row],[Debit (Rp)]],"Benar","salah")) | O67: =IF(Table3[[#This Row],[Kredit Jawaban]]="","",IF(Table3[[#This Row],[Kredit Jawaban]]=Table4[[#This Row],[Kredit (Rp)]],"Benar","salah")) -> Benar
A68: 24 | B68: 46402 | C68: Menengah / Payroll | D68: Payroll menetapkan gaji bruto Rp25.000.000. PPh 21 yang dipotong Rp1.000.000 dan BPJS karyawan Rp500.000. Gaji bersih dibayar melalui bank. | E68: Nominal pajak/iuran disederhanakan sebagai asumsi latihan. | F68: 25000000 | G68: Debit Beban Gaji; kredit Utang PPh21, Utang BPJS, dan Bank. | H68: 24 | I68: 46402 | J68: beban gaji | K68: 25000000 | M68: =IF(Table3[[#This Row],[Akun Jawaban]]="","",IF(Table3[[#This Row],[Akun Jawaban]]=Table4[[#This Row],[Akun]],"Benar","salah")) -> Benar | N68: =IF(Table3[[#This Row],[Debit Jawaban]]="","",IF(Table3[[#This Row],[Debit Jawaban]]=Table4[[#This Row],[Debit (Rp)]],"Benar","salah")) -> Benar | O68: =IF(Table3[[#This Row],[Kredit Jawaban]]="","",IF(Table3[[#This Row],[Kredit Jawaban]]=Table4[[#This Row],[Kredit (Rp)]],"Benar","salah"))
G69: Debit Beban Gaji; kredit Utang PPh21, Utang BPJS, dan Bank. | H69: 24 | I69: 46402 | J69: utang pph 21 | L69: 1000000 | M69: =IF(Table3[[#This Row],[Akun Jawaban]]="","",IF(Table3[[#This Row],[Akun Jawaban]]=Table4[[#This Row],[Akun]],"Benar","salah")) -> Benar | N69: =IF(Table3[[#This Row],[Debit Jawaban]]="","",IF(Table3[[#This Row],[Debit Jawaban]]=Table4[[#This Row],[Debit (Rp)]],"Benar","salah")) | O69: =IF(Table3[[#This Row],[Kredit Jawaban]]="","",IF(Table3[[#This Row],[Kredit Jawaban]]=Table4[[#This Row],[Kredit (Rp)]],"Benar","salah")) -> Benar
H70: 24 | I70: 46402 | J70: utang bpjs | L70: 500000 | M70: =IF(Table3[[#This Row],[Akun Jawaban]]="","",IF(Table3[[#This Row],[Akun Jawaban]]=Table4[[#This Row],[Akun]],"Benar","salah")) -> Benar | N70: =IF(Table3[[#This Row],[Debit Jawaban]]="","",IF(Table3[[#This Row],[Debit Jawaban]]=Table4[[#This Row],[Debit (Rp)]],"Benar","salah")) | O70: =IF(Table3[[#This Row],[Kredit Jawaban]]="","",IF(Table3[[#This Row],[Kredit Jawaban]]=Table4[[#This Row],[Kredit (Rp)]],"Benar","salah")) -> Benar
H71: 24 | I71: 46402 | J71: bank | L71: =K68-L69-L70 -> 23500000 | M71: =IF(Table3[[#This Row],[Akun Jawaban]]="","",IF(Table3[[#This Row],[Akun Jawaban]]=Table4[[#This Row],[Akun]],"Benar","salah")) -> Benar | N71: =IF(Table3[[#This Row],[Debit Jawaban]]="","",IF(Table3[[#This Row],[Debit Jawaban]]=Table4[[#This Row],[Debit (Rp)]],"Benar","salah")) | O71: =IF(Table3[[#This Row],[Kredit Jawaban]]="","",IF(Table3[[#This Row],[Kredit Jawaban]]=Table4[[#This Row],[Kredit (Rp)]],"Benar","salah")) -> Benar
A72: 25 | B72: 46402 | C72: Menengah / BPJS pemberi kerja | D72: Perusahaan mengakui iuran BPJS bagian pemberi kerja Rp2.000.000 untuk payroll bulan berjalan. | E72: Akan dibayar bulan berikutnya. | F72: 2000000 | G72: Debit Beban BPJS; kredit Utang BPJS. | H72: 25 | I72: 46402 | J72: beban bpjs | K72: 2000000 | M72: =IF(Table3[[#This Row],[Akun Jawaban]]="","",IF(Table3[[#This Row],[Akun Jawaban]]=Table4[[#This Row],[Akun]],"Benar","salah")) -> Benar | N72: =IF(Table3[[#This Row],[Debit Jawaban]]="","",IF(Table3[[#This Row],[Debit Jawaban]]=Table4[[#This Row],[Debit (Rp)]],"Benar","salah")) -> Benar | O72: =IF(Table3[[#This Row],[Kredit Jawaban]]="","",IF(Table3[[#This Row],[Kredit Jawaban]]=Table4[[#This Row],[Kredit (Rp)]],"Benar","salah"))
G73: Debit Beban BPJS; kredit Utang BPJS. | H73: 25 | I73: 46402 | J73: utang bpjs | L73: 2000000 | M73: =IF(Table3[[#This Row],[Akun Jawaban]]="","",IF(Table3[[#This Row],[Akun Jawaban]]=Table4[[#This Row],[Akun]],"Benar","salah")) -> Benar | N73: =IF(Table3[[#This Row],[Debit Jawaban]]="","",IF(Table3[[#This Row],[Debit Jawaban]]=Table4[[#This Row],[Debit (Rp)]],"Benar","salah")) | O73: =IF(Table3[[#This Row],[Kredit Jawaban]]="","",IF(Table3[[#This Row],[Kredit Jawaban]]=Table4[[#This Row],[Kredit (Rp)]],"Benar","salah")) -> Benar
A74: 26 | B74: 46403 | C74: Menengah / Penerimaan bunga bank | D74: Perusahaan menerima bunga deposito Rp1.500.000 melalui bank. | E74: Tidak ada potongan pajak dalam soal latihan ini. | F74: 1500000 | G74: Debit Bank; kredit Pendapatan Bunga. | H74: 26 | I74: 46403 | J74: bank | K74: 1500000 | M74: =IF(Table3[[#This Row],[Akun Jawaban]]="","",IF(Table3[[#This Row],[Akun Jawaban]]=Table4[[#This Row],[Akun]],"Benar","salah")) -> Benar | N74: =IF(Table3[[#This Row],[Debit Jawaban]]="","",IF(Table3[[#This Row],[Debit Jawaban]]=Table4[[#This Row],[Debit (Rp)]],"Benar","salah")) -> Benar | O74: =IF(Table3[[#This Row],[Kredit Jawaban]]="","",IF(Table3[[#This Row],[Kredit Jawaban]]=Table4[[#This Row],[Kredit (Rp)]],"Benar","salah"))
G75: Debit Bank; kredit Pendapatan Bunga. | H75: 26 | I75: 46403 | J75: pendapatan bunga | L75: 1500000 | M75: =IF(Table3[[#This Row],[Akun Jawaban]]="","",IF(Table3[[#This Row],[Akun Jawaban]]=Table4[[#This Row],[Akun]],"Benar","salah")) -> Benar | N75: =IF(Table3[[#This Row],[Debit Jawaban]]="","",IF(Table3[[#This Row],[Debit Jawaban]]=Table4[[#This Row],[Debit (Rp)]],"Benar","salah")) | O75: =IF(Table3[[#This Row],[Kredit Jawaban]]="","",IF(Table3[[#This Row],[Kredit Jawaban]]=Table4[[#This Row],[Kredit (Rp)]],"Benar","salah")) -> Benar
A76: 27 | B76: 46403 | C76: Menengah / Biaya administrasi bank | D76: Bank membebankan biaya administrasi Rp250.000 yang langsung mengurangi rekening bank. | E76: Belum ada jurnal sebelumnya. | F76: 250000 | G76: Debit Beban Administrasi Bank; kredit Bank. | H76: 27 | I76: 46403 | J76: beban administrasi bank | K76: 250000 | M76: =IF(Table3[[#This Row],[Akun Jawaban]]="","",IF(Table3[[#This Row],[Akun Jawaban]]=Table4[[#This Row],[Akun]],"Benar","salah")) -> Benar | N76: =IF(Table3[[#This Row],[Debit Jawaban]]="","",IF(Table3[[#This Row],[Debit Jawaban]]=Table4[[#This Row],[Debit (Rp)]],"Benar","salah")) -> Benar | O76: =IF(Table3[[#This Row],[Kredit Jawaban]]="","",IF(Table3[[#This Row],[Kredit Jawaban]]=Table4[[#This Row],[Kredit (Rp)]],"Benar","salah"))
G77: Debit Beban Administrasi Bank; kredit Bank. | H77: 27 | I77: 46403 | J77: bank | L77: 250000 | M77: =IF(Table3[[#This Row],[Akun Jawaban]]="","",IF(Table3[[#This Row],[Akun Jawaban]]=Table4[[#This Row],[Akun]],"Benar","salah")) -> Benar | N77: =IF(Table3[[#This Row],[Debit Jawaban]]="","",IF(Table3[[#This Row],[Debit Jawaban]]=Table4[[#This Row],[Debit (Rp)]],"Benar","salah")) | O77: =IF(Table3[[#This Row],[Kredit Jawaban]]="","",IF(Table3[[#This Row],[Kredit Jawaban]]=Table4[[#This Row],[Kredit (Rp)]],"Benar","salah")) -> Benar
A78: 28 | B78: 46404 | C78: Menengah / Pinjaman bank | D78: Perusahaan menerima pinjaman bank Rp200.000.000 dengan jangka waktu 3 tahun. Dana masuk ke bank perusahaan. | E78: Anggap seluruhnya pinjaman jangka panjang. | F78: 200000000 | G78: Debit Bank; kredit Utang Bank Jangka Panjang. | H78: 28 | I78: 46404 | J78: bank | K78: 200000000 | M78: =IF(Table3[[#This Row],[Akun Jawaban]]="","",IF(Table3[[#This Row],[Akun Jawaban]]=Table4[[#This Row],[Akun]],"Benar","salah")) -> Benar | N78: =IF(Table3[[#This Row],[Debit Jawaban]]="","",IF(Table3[[#This Row],[Debit Jawaban]]=Table4[[#This Row],[Debit (Rp)]],"Benar","salah")) -> Benar | O78: =IF(Table3[[#This Row],[Kredit Jawaban]]="","",IF(Table3[[#This Row],[Kredit Jawaban]]=Table4[[#This Row],[Kredit (Rp)]],"Benar","salah"))
G79: Debit Bank; kredit Utang Bank Jangka Panjang. | H79: 28 | I79: 46404 | J79: utang bank jangka panjang | L79: 200000000 | M79: =IF(Table3[[#This Row],[Akun Jawaban]]="","",IF(Table3[[#This Row],[Akun Jawaban]]=Table4[[#This Row],[Akun]],"Benar","salah")) -> Benar | N79: =IF(Table3[[#This Row],[Debit Jawaban]]="","",IF(Table3[[#This Row],[Debit Jawaban]]=Table4[[#This Row],[Debit (Rp)]],"Benar","salah")) | O79: =IF(Table3[[#This Row],[Kredit Jawaban]]="","",IF(Table3[[#This Row],[Kredit Jawaban]]=Table4[[#This Row],[Kredit (Rp)]],"Benar","salah")) -> Benar
A80: 29 | B80: 46405 | C80: Menengah / Pembelian kendaraan | D80: Perusahaan membeli kendaraan operasional Rp250.000.000 sebelum PPN; PPN latihan efektif 11%; dibayar melalui bank. | E80: Kendaraan siap digunakan. | F80: 250000000 | G80: Debit Kendaraan dan PPN Masukan; kredit Bank. | H80: 29 | I80: 46405 | J80: kendaraan | K80: 250000000 | M80: =IF(Table3[[#This Row],[Akun Jawaban]]="","",IF(Table3[[#This Row],[Akun Jawaban]]=Table4[[#This Row],[Akun]],"Benar","salah")) -> Benar | N80: =IF(Table3[[#This Row],[Debit Jawaban]]="","",IF(Table3[[#This Row],[Debit Jawaban]]=Table4[[#This Row],[Debit (Rp)]],"Benar","salah")) -> Benar | O80: =IF(Table3[[#This Row],[Kredit Jawaban]]="","",IF(Table3[[#This Row],[Kredit Jawaban]]=Table4[[#This Row],[Kredit (Rp)]],"Benar","salah"))
G81: Debit Kendaraan dan PPN Masukan; kredit Bank. | H81: 29 | I81: 46405 | J81: ppn masukan | K81: =11%*K80 -> 27500000 | M81: =IF(Table3[[#This Row],[Akun Jawaban]]="","",IF(Table3[[#This Row],[Akun Jawaban]]=Table4[[#This Row],[Akun]],"Benar","salah")) -> Benar | N81: =IF(Table3[[#This Row],[Debit Jawaban]]="","",IF(Table3[[#This Row],[Debit Jawaban]]=Table4[[#This Row],[Debit (Rp)]],"Benar","salah")) -> Benar | O81: =IF(Table3[[#This Row],[Kredit Jawaban]]="","",IF(Table3[[#This Row],[Kredit Jawaban]]=Table4[[#This Row],[Kredit (Rp)]],"Benar","salah"))
H82: 29 | I82: 46405 | J82: bank | L82: =SUM(K80:K81) -> 277500000 | M82: =IF(Table3[[#This Row],[Akun Jawaban]]="","",IF(Table3[[#This Row],[Akun Jawaban]]=Table4[[#This Row],[Akun]],"Benar","salah")) -> Benar | N82: =IF(Table3[[#This Row],[Debit Jawaban]]="","",IF(Table3[[#This Row],[Debit Jawaban]]=Table4[[#This Row],[Debit (Rp)]],"Benar","salah")) | O82: =IF(Table3[[#This Row],[Kredit Jawaban]]="","",IF(Table3[[#This Row],[Kredit Jawaban]]=Table4[[#This Row],[Kredit (Rp)]],"Benar","salah")) -> Benar
A83: 30 | B83: 46405 | C83: Menengah / Pelunasan utang dengan diskon pembelian | D83: Perusahaan melunasi invoice Supplier A sebesar Rp120.000.000 sebelum PPN. Diberikan diskon tunai 2% dari harga barang, dan PPN ikut disesuaikan. | E83: Diskon barang = Rp2.400.000; koreksi PPN = Rp264.000; kas dibayar Rp130.536.000. | F83: 120000000 | G83: Debit Utang Usaha; kredit Bank, Persediaan, dan PPN Masukan. | H83: 30 | I83: 46405 | J83: utang usaha | K83: =SUM(L84:L86) -> 133200000 | M83: =IF(Table3[[#This Row],[Akun Jawaban]]="","",IF(Table3[[#This Row],[Akun Jawaban]]=Table4[[#This Row],[Akun]],"Benar","salah")) -> Benar | N83: =IF(Table3[[#This Row],[Debit Jawaban]]="","",IF(Table3[[#This Row],[Debit Jawaban]]=Table4[[#This Row],[Debit (Rp)]],"Benar","salah")) -> Benar | O83: =IF(Table3[[#This Row],[Kredit Jawaban]]="","",IF(Table3[[#This Row],[Kredit Jawaban]]=Table4[[#This Row],[Kredit (Rp)]],"Benar","salah"))
G84: Debit Utang Usaha; kredit Bank, Persediaan, dan PPN Masukan. | H84: 30 | I84: 46405 | J84: bank | L84: 130536000 | M84: =IF(Table3[[#This Row],[Akun Jawaban]]="","",IF(Table3[[#This Row],[Akun Jawaban]]=Table4[[#This Row],[Akun]],"Benar","salah")) -> Benar | N84: =IF(Table3[[#This Row],[Debit Jawaban]]="","",IF(Table3[[#This Row],[Debit Jawaban]]=Table4[[#This Row],[Debit (Rp)]],"Benar","salah")) | O84: =IF(Table3[[#This Row],[Kredit Jawaban]]="","",IF(Table3[[#This Row],[Kredit Jawaban]]=Table4[[#This Row],[Kredit (Rp)]],"Benar","salah")) -> Benar
H85: 30 | I85: 46405 | J85: persediaan barang dagang | L85: 2400000 | M85: =IF(Table3[[#This Row],[Akun Jawaban]]="","",IF(Table3[[#This Row],[Akun Jawaban]]=Table4[[#This Row],[Akun]],"Benar","salah")) -> Benar | N85: =IF(Table3[[#This Row],[Debit Jawaban]]="","",IF(Table3[[#This Row],[Debit Jawaban]]=Table4[[#This Row],[Debit (Rp)]],"Benar","salah")) | O85: =IF(Table3[[#This Row],[Kredit Jawaban]]="","",IF(Table3[[#This Row],[Kredit Jawaban]]=Table4[[#This Row],[Kredit (Rp)]],"Benar","salah")) -> Benar
H86: 30 | I86: 46405 | J86: ppn masukan | L86: 264000 | M86: =IF(Table3[[#This Row],[Akun Jawaban]]="","",IF(Table3[[#This Row],[Akun Jawaban]]=Table4[[#This Row],[Akun]],"Benar","salah")) -> Benar | N86: =IF(Table3[[#This Row],[Debit Jawaban]]="","",IF(Table3[[#This Row],[Debit Jawaban]]=Table4[[#This Row],[Debit (Rp)]],"Benar","salah")) | O86: =IF(Table3[[#This Row],[Kredit Jawaban]]="","",IF(Table3[[#This Row],[Kredit Jawaban]]=Table4[[#This Row],[Kredit (Rp)]],"Benar","salah")) -> Benar
A87: 31 | B87: 46406 | C87: Menengah / Realisasi uang muka pelanggan | D87: Barang pesanan Pelanggan C dikirim dengan harga Rp30.000.000 sebelum PPN; PPN 11% dan HPP Rp16.000.000. Uang muka Rp33.300.000 digunakan sebagai pelunasan. | E87: Tidak ada kas baru. | F87: 30000000 | G87: Debit Uang Muka Pelanggan; kredit Penjualan dan PPN Keluaran; lalu HPP dan Persediaan. | H87: 31 | I87: 46406 | J87: Uang Muka Pelanggan | K87: 33300000 | M87: =IF(Table3[[#This Row],[Akun Jawaban]]="","",IF(Table3[[#This Row],[Akun Jawaban]]=Table4[[#This Row],[Akun]],"Benar","salah")) -> Benar | N87: =IF(Table3[[#This Row],[Debit Jawaban]]="","",IF(Table3[[#This Row],[Debit Jawaban]]=Table4[[#This Row],[Debit (Rp)]],"Benar","salah")) -> Benar | O87: =IF(Table3[[#This Row],[Kredit Jawaban]]="","",IF(Table3[[#This Row],[Kredit Jawaban]]=Table4[[#This Row],[Kredit (Rp)]],"Benar","salah"))
G88: Debit Uang Muka Pelanggan; kredit Penjualan dan PPN Keluaran; lalu HPP dan Persediaan. | H88: 31 | I88: 46406 | J88: penjualan | L88: 30000000 | M88: =IF(Table3[[#This Row],[Akun Jawaban]]="","",IF(Table3[[#This Row],[Akun Jawaban]]=Table4[[#This Row],[Akun]],"Benar","salah")) -> Benar | N88: =IF(Table3[[#This Row],[Debit Jawaban]]="","",IF(Table3[[#This Row],[Debit Jawaban]]=Table4[[#This Row],[Debit (Rp)]],"Benar","salah")) | O88: =IF(Table3[[#This Row],[Kredit Jawaban]]="","",IF(Table3[[#This Row],[Kredit Jawaban]]=Table4[[#This Row],[Kredit (Rp)]],"Benar","salah")) -> Benar
H89: 31 | I89: 46406 | J89: ppn keluaran | L89: =11%*L88 -> 3300000 | M89: =IF(Table3[[#This Row],[Akun Jawaban]]="","",IF(Table3[[#This Row],[Akun Jawaban]]=Table4[[#This Row],[Akun]],"Benar","salah")) -> Benar | N89: =IF(Table3[[#This Row],[Debit Jawaban]]="","",IF(Table3[[#This Row],[Debit Jawaban]]=Table4[[#This Row],[Debit (Rp)]],"Benar","salah")) | O89: =IF(Table3[[#This Row],[Kredit Jawaban]]="","",IF(Table3[[#This Row],[Kredit Jawaban]]=Table4[[#This Row],[Kredit (Rp)]],"Benar","salah")) -> Benar
H90: 31 | I90: 46406 | J90: hpp | K90: 16000000 | M90: =IF(Table3[[#This Row],[Akun Jawaban]]="","",IF(Table3[[#This Row],[Akun Jawaban]]=Table4[[#This Row],[Akun]],"Benar","salah")) -> Benar | N90: =IF(Table3[[#This Row],[Debit Jawaban]]="","",IF(Table3[[#This Row],[Debit Jawaban]]=Table4[[#This Row],[Debit (Rp)]],"Benar","salah")) -> Benar | O90: =IF(Table3[[#This Row],[Kredit Jawaban]]="","",IF(Table3[[#This Row],[Kredit Jawaban]]=Table4[[#This Row],[Kredit (Rp)]],"Benar","salah"))
H91: 31 | I91: 46406 | J91: persediaan barang dagang | L91: 16000000 | M91: =IF(Table3[[#This Row],[Akun Jawaban]]="","",IF(Table3[[#This Row],[Akun Jawaban]]=Table4[[#This Row],[Akun]],"Benar","salah")) -> Benar | N91: =IF(Table3[[#This Row],[Debit Jawaban]]="","",IF(Table3[[#This Row],[Debit Jawaban]]=Table4[[#This Row],[Debit (Rp)]],"Benar","salah")) | O91: =IF(Table3[[#This Row],[Kredit Jawaban]]="","",IF(Table3[[#This Row],[Kredit Jawaban]]=Table4[[#This Row],[Kredit (Rp)]],"Benar","salah")) -> Benar
A92: 32 | B92: 46406 | C92: Menengah / Penjualan tunai | D92: Penjualan tunai Rp85.000.000 sebelum PPN; PPN 11%; HPP Rp48.000.000. | E92: Pembayaran langsung melalui bank. | F92: 85000000 | G92: Debit Bank; kredit Penjualan/PPN; lalu HPP/Persediaan. | H92: 32 | I92: 46406 | J92: bank | K92: =SUM(L93:L94) -> 94350000 | M92: =IF(Table3[[#This Row],[Akun Jawaban]]="","",IF(Table3[[#This Row],[Akun Jawaban]]=Table4[[#This Row],[Akun]],"Benar","salah")) -> Benar | N92: =IF(Table3[[#This Row],[Debit Jawaban]]="","",IF(Table3[[#This Row],[Debit Jawaban]]=Table4[[#This Row],[Debit (Rp)]],"Benar","salah")) -> Benar | O92: =IF(Table3[[#This Row],[Kredit Jawaban]]="","",IF(Table3[[#This Row],[Kredit Jawaban]]=Table4[[#This Row],[Kredit (Rp)]],"Benar","salah"))
G93: Debit Bank; kredit Penjualan/PPN; lalu HPP/Persediaan. | H93: 32 | I93: 46406 | J93: penjualan | L93: 85000000 | M93: =IF(Table3[[#This Row],[Akun Jawaban]]="","",IF(Table3[[#This Row],[Akun Jawaban]]=Table4[[#This Row],[Akun]],"Benar","salah")) -> Benar | N93: =IF(Table3[[#This Row],[Debit Jawaban]]="","",IF(Table3[[#This Row],[Debit Jawaban]]=Table4[[#This Row],[Debit (Rp)]],"Benar","salah")) | O93: =IF(Table3[[#This Row],[Kredit Jawaban]]="","",IF(Table3[[#This Row],[Kredit Jawaban]]=Table4[[#This Row],[Kredit (Rp)]],"Benar","salah")) -> Benar
H94: 32 | I94: 46406 | J94: ppn keluaran | L94: =11%*L93 -> 9350000 | M94: =IF(Table3[[#This Row],[Akun Jawaban]]="","",IF(Table3[[#This Row],[Akun Jawaban]]=Table4[[#This Row],[Akun]],"Benar","salah")) -> Benar | N94: =IF(Table3[[#This Row],[Debit Jawaban]]="","",IF(Table3[[#This Row],[Debit Jawaban]]=Table4[[#This Row],[Debit (Rp)]],"Benar","salah")) | O94: =IF(Table3[[#This Row],[Kredit Jawaban]]="","",IF(Table3[[#This Row],[Kredit Jawaban]]=Table4[[#This Row],[Kredit (Rp)]],"Benar","salah")) -> Benar
H95: 32 | I95: 46406 | J95: hpp | K95: 48000000 | M95: =IF(Table3[[#This Row],[Akun Jawaban]]="","",IF(Table3[[#This Row],[Akun Jawaban]]=Table4[[#This Row],[Akun]],"Benar","salah")) -> Benar | N95: =IF(Table3[[#This Row],[Debit Jawaban]]="","",IF(Table3[[#This Row],[Debit Jawaban]]=Table4[[#This Row],[Debit (Rp)]],"Benar","salah")) -> Benar | O95: =IF(Table3[[#This Row],[Kredit Jawaban]]="","",IF(Table3[[#This Row],[Kredit Jawaban]]=Table4[[#This Row],[Kredit (Rp)]],"Benar","salah"))
H96: 32 | I96: 46406 | J96: persediaan barang dagang | L96: 48000000 | M96: =IF(Table3[[#This Row],[Akun Jawaban]]="","",IF(Table3[[#This Row],[Akun Jawaban]]=Table4[[#This Row],[Akun]],"Benar","salah")) -> Benar | N96: =IF(Table3[[#This Row],[Debit Jawaban]]="","",IF(Table3[[#This Row],[Debit Jawaban]]=Table4[[#This Row],[Debit (Rp)]],"Benar","salah")) | O96: =IF(Table3[[#This Row],[Kredit Jawaban]]="","",IF(Table3[[#This Row],[Kredit Jawaban]]=Table4[[#This Row],[Kredit (Rp)]],"Benar","salah")) -> Benar
A97: 33 | B97: 46407 | C97: Menengah / Penjualan kredit besar | D97: Perusahaan menjual barang kepada Pelanggan D secara kredit Rp210.000.000 sebelum PPN; HPP Rp125.000.000. | E97: PPN latihan 11%; termin 45 hari. | F97: 210000000 | G97: Debit Piutang; kredit Penjualan/PPN; lalu HPP/Persediaan. | H97: 33 | I97: 46407 | J97: piutang usaha | K97: =SUM(L98:L99) -> 233100000 | M97: =IF(Table3[[#This Row],[Akun Jawaban]]="","",IF(Table3[[#This Row],[Akun Jawaban]]=Table4[[#This Row],[Akun]],"Benar","salah")) -> Benar | N97: =IF(Table3[[#This Row],[Debit Jawaban]]="","",IF(Table3[[#This Row],[Debit Jawaban]]=Table4[[#This Row],[Debit (Rp)]],"Benar","salah")) -> Benar | O97: =IF(Table3[[#This Row],[Kredit Jawaban]]="","",IF(Table3[[#This Row],[Kredit Jawaban]]=Table4[[#This Row],[Kredit (Rp)]],"Benar","salah"))
G98: Debit Piutang; kredit Penjualan/PPN; lalu HPP/Persediaan. | H98: 33 | I98: 46407 | J98: penjualan | L98: 210000000 | M98: =IF(Table3[[#This Row],[Akun Jawaban]]="","",IF(Table3[[#This Row],[Akun Jawaban]]=Table4[[#This Row],[Akun]],"Benar","salah")) -> Benar | N98: =IF(Table3[[#This Row],[Debit Jawaban]]="","",IF(Table3[[#This Row],[Debit Jawaban]]=Table4[[#This Row],[Debit (Rp)]],"Benar","salah")) | O98: =IF(Table3[[#This Row],[Kredit Jawaban]]="","",IF(Table3[[#This Row],[Kredit Jawaban]]=Table4[[#This Row],[Kredit (Rp)]],"Benar","salah")) -> Benar
H99: 33 | I99: 46407 | J99: ppn keluaran | L99: =11%*L98 -> 23100000 | M99: =IF(Table3[[#This Row],[Akun Jawaban]]="","",IF(Table3[[#This Row],[Akun Jawaban]]=Table4[[#This Row],[Akun]],"Benar","salah")) -> Benar | N99: =IF(Table3[[#This Row],[Debit Jawaban]]="","",IF(Table3[[#This Row],[Debit Jawaban]]=Table4[[#This Row],[Debit (Rp)]],"Benar","salah")) | O99: =IF(Table3[[#This Row],[Kredit Jawaban]]="","",IF(Table3[[#This Row],[Kredit Jawaban]]=Table4[[#This Row],[Kredit (Rp)]],"Benar","salah")) -> Benar
H100: 33 | I100: 46407 | J100: hpp | K100: 125000000 | M100: =IF(Table3[[#This Row],[Akun Jawaban]]="","",IF(Table3[[#This Row],[Akun Jawaban]]=Table4[[#This Row],[Akun]],"Benar","salah")) -> Benar | N100: =IF(Table3[[#This Row],[Debit Jawaban]]="","",IF(Table3[[#This Row],[Debit Jawaban]]=Table4[[#This Row],[Debit (Rp)]],"Benar","salah")) -> Benar | O100: =IF(Table3[[#This Row],[Kredit Jawaban]]="","",IF(Table3[[#This Row],[Kredit Jawaban]]=Table4[[#This Row],[Kredit (Rp)]],"Benar","salah"))
...

Sheet Kunci_Jurnal_80
A1: KUNCI JURNAL UMUM – 80 SOAL | SUMBER UNTUK BUKU BESAR & REKAP
A2: Kunci ini adalah answer key pembanding. Kolom F:G adalah nominal jurnal; H = arus kas; I = tingkat; J = dokumen; K = catatan.
A3: No | B3: Tanggal | C3: Tingkat / Jenis | D3: Counterparty | E3: Akun | F3: Debit (Rp) | G3: Kredit (Rp) | H3: Arus Kas | I3: Tingkat | J3: Dokumen | K3: Catatan
A4: 1 | B4: 46388 | C4: Mudah / Setoran modal | D4: Pemegang Saham | E4: Bank | F4: 1500000000 | G4: 0 | H4: Pendanaan | I4: Mudah | J4: Bukti Setoran Saham
A5: 1 | B5: 46388 | C5: Mudah / Setoran modal | D5: Pemegang Saham | E5: Modal Saham | F5: 0 | G5: 1500000000 | I5: Mudah | J5: Bukti Setoran Saham
A6: 2 | B6: 46388 | C6: Mudah / Transfer kas kecil | D6: Internal | E6: Kas Kecil | F6: 20000000 | G6: 0 | H6: Investasi | I6: Mudah | J6: Bukti Transfer
A7: 2 | B7: 46388 | C7: Mudah / Transfer kas kecil | D7: Internal | E7: Bank | F7: 0 | G7: 20000000 | H7: Investasi | I7: Mudah | J7: Bukti Transfer
A8: 3 | B8: 46389 | C8: Mudah / Pembelian aset tunai | D8: PT Perkasa Office | E8: Peralatan Toko | F8: 60000000 | G8: 0 | H8: Investasi | I8: Mudah | J8: Invoice FA-001
A9: 3 | B9: 46389 | C9: Mudah / Pembelian aset tunai | D9: PT Perkasa Office | E9: PPN Masukan | F9: 6600000 | G9: 0 | H9: Operasi | I9: Mudah | J9: Faktur Pajak
A10: 3 | B10: 46389 | C10: Mudah / Pembelian aset tunai | D10: PT Perkasa Office | E10: Bank | F10: 0 | G10: 66600000 | H10: Investasi | I10: Mudah | J10: Bukti Bayar
A11: 4 | B11: 46390 | C11: Mudah / Pembelian aset kredit | D11: PT Kantor Jaya | E11: Peralatan Kantor | F11: 40000000 | G11: 0 | H11: Investasi | I11: Mudah | J11: Invoice FA-002
A12: 4 | B12: 46390 | C12: Mudah / Pembelian aset kredit | D12: PT Kantor Jaya | E12: PPN Masukan | F12: 4400000 | G12: 0 | H12: Operasi | I12: Mudah | J12: Faktur Pajak
A13: 4 | B13: 46390 | C13: Mudah / Pembelian aset kredit | D13: PT Kantor Jaya | E13: Utang Usaha | F13: 0 | G13: 44400000 | H13: Operasi | I13: Mudah | J13: Invoice FA-002
A14: 5 | B14: 46390 | C14: Mudah / Pembelian persediaan kredit | D14: Supplier A | E14: Persediaan Barang Dagang | F14: 250000000 | G14: 0 | H14: Operasi | I14: Mudah | J14: INV-A-001
A15: 5 | B15: 46390 | C15: Mudah / Pembelian persediaan kredit | D15: Supplier A | E15: PPN Masukan | F15: 27500000 | G15: 0 | H15: Operasi | I15: Mudah | J15: Faktur Pajak
A16: 5 | B16: 46390 | C16: Mudah / Pembelian persediaan kredit | D16: Supplier A | E16: Utang Usaha | F16: 0 | G16: 277500000 | H16: Operasi | I16: Mudah | J16: INV-A-001
A17: 6 | B17: 46391 | C17: Mudah / Pembelian persediaan tunai | D17: Supplier B | E17: Persediaan Barang Dagang | F17: 100000000 | G17: 0 | H17: Operasi | I17: Mudah | J17: INV-B-001
... A36: 12 | B36: 46395 | C36: Mudah / Uang muka pelanggan | D36: Pelanggan C | E36: Bank | F36: 44440000 | G36: 0 | H36: Operasi | I36: Mudah | J36: AR-DP-001
A37: 12 | B37: 46395 | C37: Mudah / Uang muka pelanggan | D37: Pelanggan C | E37: Uang Muka Pelanggan | F37: 0 | G37: 44440000 | I37: Mudah | J37: AR-DP-001
A38: 13 | B38: 46396 | C38: Mudah / Retur pembelian | D38: Supplier A | E38: Utang Usaha | F38: 16650000 | G38: 0 | H38: Operasi | I38: Mudah | J38: RT-AP-001
A39: 13 | B39: 46396 | C39: Mudah / Retur pembelian | D39: Supplier A | E39: Persediaan Barang Dagang | F39: 0 | G39: 15000000 | H39: Operasi | I39: Mudah | J39: Nota Retur
A40: 13 | B40: 46396 | C40: Mudah / Retur pembelian | D40: Supplier A | E40: PPN Masukan | F40: 0 | G40: 1650000 | H40: Operasi | I40: Mudah | J40: Nota Retur
A41: 14 | B41: 46397 | C41: Mudah / Retur penjualan | D41: Pelanggan B | E41: Retur Penjualan | F41: 10000000 | G41: 0 | H41: Operasi | I41: Mudah | J41: RT-AR-001
A42: 14 | B42: 46397 | C42: Mudah / Retur penjualan | D42: Pelanggan B | E42: PPN Keluaran | F42: 1100000 | G42: 0 | H42: Operasi | I42: Mudah | J42: Nota Retur
A43: 14 | B43: 46397 | C43: Mudah / Retur penjualan | D43: Pelanggan B | E43: Piutang Usaha | F43: 0 | G43: 11100000 | H43: Operasi | I43: Mudah | J43: Nota Retur
A44: 14 | B44: 46397 | C44: Mudah / Retur penjualan | D44: Pelanggan B | E44: Persediaan Barang Dagang | F44: 6000000 | G44: 0 | H44: Operasi | I44: Mudah | J44: Kartu Persediaan
A45: 14 | B45: 46397 | C45: Mudah / Retur penjualan | D45: Pelanggan B | E45: HPP | F45: 0 | G45: 6000000 | H45: Operasi | I45: Mudah | J45: Kartu Persediaan
A46: 15 | B46: 46397 | C46: Mudah / Freight-out | D46: Ekspedisi | E46: Beban Pengiriman Penjualan | F46: 2500000 | G46: 0 | H46: Operasi | I46: Mudah | J46: FO-001
A47: 15 | B47: 46397 | C47: Mudah / Freight-out | D47: Ekspedisi | E47: Bank | F47: 0 | G47: 2500000 | H47: Operasi | I47: Mudah | J47: Bukti Bayar
A48: 16 | B48: 46398 | C48: Mudah / Iklan dibayar di muka | D48: Media Nusantara | E48: Iklan Dibayar di Muka | F48: 12000000 | G48: 0 | H48: Operasi | I48: Mudah | J48: ADV-001
A49: 16 | B49: 46398 | C49: Mudah / Iklan dibayar di muka | D49: Media Nusantara | E49: Bank | F49: 0 | G49: 12000000 | H49: Operasi | I49: Mudah | J49: Bukti Bayar
... A111: 37 | B111: 46409 | C111: Menengah / Pengembalian dana pelanggan | D111: Pelanggan C | E111: Uang Muka Pelanggan | F111: 6700000 | G111: 0 | H111: Operasi | I111: Menengah | J111: CM-REF-001
A112: 37 | B112: 46409 | C112: Menengah / Pengembalian dana pelanggan | D112: Pelanggan C | E112: Bank | F112: 0 | G112: 6700000 | I112: Menengah | J112: CM-REF-001
A113: 38 | B113: 46410 | C113: Menengah / Cek pelanggan ditolak | D113: Pelanggan B | E113: Piutang Usaha | F113: 3000000 | G113: 0 | H113: Operasi | I113: Menengah | J113: NSF-001
A114: 38 | B114: 46410 | C114: Menengah / Cek pelanggan ditolak | D114: Pelanggan B | E114: Bank | F114: 0 | G114: 3000000 | H114: Operasi | I114: Menengah | J114: Bank Advice
A115: 39 | B115: 46410 | C115: Menengah / Penerimaan piutang | D115: Pelanggan B | E115: Bank | F115: 50000000 | G115: 0 | H115: Operasi | I115: Menengah | J115: BT-AR-003
A116: 39 | B116: 46410 | C116: Menengah / Penerimaan piutang | D116: Pelanggan B | E116: Piutang Usaha | F116: 0 | G116: 50000000 | H116: Operasi | I116: Menengah | J116: BT-AR-003
A117: 40 | B117: 46411 | C117: Sulit / Impor persediaan + bea + PPN + PPh22 | D117: Direktorat Bea Cukai | E117: Persediaan Barang Dagang | F117: 105000000 | G117: 0 | H117: Operasi | I117: Sulit | J117: IMP-001
A118: 40 | B118: 46411 | C118: Sulit / Impor persediaan + bea + PPN + PPh22 | D118: Direktorat Bea Cukai | E118: PPN Masukan | F118: 11550000 | G118: 0 | H118: Operasi | I118: Sulit | J118: IMP-001
A119: 40 | B119: 46411 | C119: Sulit / Impor persediaan + bea + PPN + PPh22 | D119: Direktorat Bea Cukai | E119: PPh 22 Dibayar di Muka | F119: 2625000 | G119: 0 | H119: Operasi | I119: Sulit | J119: IMP-001
A120: 40 | B120: 46411 | C120: Sulit / Impor persediaan + bea + PPN + PPh22 | D120: Direktorat Bea Cukai | E120: Bank | F120: 0 | G120: 119175000 | H120: Operasi | I120: Sulit | J120: IMP-001
A121: 41 | B121: 46411 | C121: Sulit / PPh22 pemungut | D121: Supplier Pemerintah | E121: Persediaan Barang Dagang | F121: 50000000 | G121: 0 | H121: Operasi | I121: Sulit | J121: PPH22-001
A122: 41 | B122: 46411 | C122: Sulit / PPh22 pemungut | D122: Supplier Pemerintah | E122: PPN Masukan | F122: 5500000 | G122: 0 | H122: Operasi | I122: Sulit | J122: Faktur Pajak
A123: 41 | B123: 46411 | C123: Sulit / PPh22 pemungut | D123: Supplier Pemerintah | E123: Utang PPh 22 | F123: 0 | G123: 750000 | H123: Operasi | I123: Sulit | J123: Bukti Pungut
A124: 41 | B124: 46411 | C124: Sulit / PPh22 pemungut | D124: Supplier Pemerintah | E124: Utang Usaha | F124: 0 | G124: 54750000 | H124: Operasi | I124: Sulit | J124: Invoice
... A227: 80 | B227: 46418 | C227: Paling Sulit / Transaksi gabungan | D227: Pelanggan F | E227: Bank | F227: 40000000 | G227: 0 | H227: Operasi | I227: Paling Sulit | J227: AR-REC-003
A228: 80 | B228: 46418 | C228: Paling Sulit / Transaksi gabungan | D228: Pelanggan F | E228: Piutang Usaha | F228: 0 | G228: 40000000 | I228: Paling Sulit | J228: AR-REC-003
A229: 80 | B229: 46418 | C229: Paling Sulit / Transaksi gabungan | D229: Ekspedisi | E229: Beban Pengiriman Penjualan | F229: 1000000 | G229: 0 | H229: Operasi | I229: Paling Sulit | J229: EXP-DEL-002
A230: 80 | B230: 46418 | C230: Paling Sulit / Transaksi gabungan | D230: Ekspedisi | E230: Bank | F230: 0 | G230: 1000000 | I230: Paling Sulit | J230: EXP-DEL-002

Sheet Buku_Besar
A1: BUKU BESAR RINGKAS – SALDO AWAL + JURNAL UMUM + PENYESUAIAN + PENUTUP
A2: Identitas | E2: Saldo Awal | G2: Jurnal Umum | I2: Penyesuaian | K2: Saldo Sebelum Penutup | M2: Jurnal Penutup | O2: Saldo Akhir
A3: Kode Akun | B3: Nama Akun | C3: Kategori | D3: Saldo Normal | E3: Debit Awal | F3: Kredit Awal | G3: Debit JU | H3: Kredit JU | I3: Debit Penyesuaian | J3: Kredit Penyesuaian | K3: Saldo Debit | L3: Saldo Kredit | M3: Debit Penutup | N3: Kredit Penutup | O3: Saldo Debit Akhir | P3: Saldo Kredit Akhir
A4: 1-001 | B4: Bank | C4: Aset | D4: Debit | E4: =SUMIF(Saldo_Awal!$B$4:$B$91,$B4,Saldo_Awal!$C$4:$C$91) -> 100000000 | F4: =SUMIF(Saldo_Awal!$B$4:$B$91,$B4,Saldo_Awal!$D$4:$D$91) -> 0 | G4: =SUMIF(Kunci_Jurnal_80!$E$4:$E$230,$B4,Kunci_Jurnal_80!$F$4:$F$230) -> 2468414000 | H4: =SUMIF(Kunci_Jurnal_80!$E$4:$E$230,$B4,Kunci_Jurnal_80!$G$4:$G$230) -> 1164987000 | I4: =SUMIF(Kunci_Penyesuaian!$D$4:$D$65,$B4,Kunci_Penyesuaian!$E$4:$E$65) -> 0 | J4: =SUMIF(Kunci_Penyesuaian!$D$4:$D$65,$B4,Kunci_Penyesuaian!$F$4:$F$65) -> 0 | K4: =IF(E4+G4+I4-F4-H4-J4>0,E4+G4+I4-F4-H4-J4,0) -> 1403427000 | L4: =IF(F4+H4+J4-E4-G4-I4>0,F4+H4+J4-E4-G4-I4,0) -> 0 | M4: =SUMIF(Jurnal_Penutup!$D$5:$D$82,$B4,Jurnal_Penutup!$E$5:$E$82) -> 0 | N4: =SUMIF(Jurnal_Penutup!$D$5:$D$82,$B4,Jurnal_Penutup!$F$5:$F$82) -> 0 | O4: =IF(K4+M4-L4-N4>0,K4+M4-L4-N4,0) -> 1403427000 | P4: =IF(L4+N4-K4-M4>0,L4+N4-K4-M4,0) -> 0
A5: 1-002 | B5: Kas Kecil | C5: Aset | D5: Debit | E5: =SUMIF(Saldo_Awal!$B$4:$B$91,$B5,Saldo_Awal!$C$4:$C$91) -> 10000000 | F5: =SUMIF(Saldo_Awal!$B$4:$B$91,$B5,Saldo_Awal!$D$4:$D$91) -> 0 | G5: =SUMIF(Kunci_Jurnal_80!$E$4:$E$230,$B5,Kunci_Jurnal_80!$F$4:$F$230) -> 30150000 | H5: =SUMIF(Kunci_Jurnal_80!$E$4:$E$230,$B5,Kunci_Jurnal_80!$G$4:$G$230) -> 2300000 | I5: =SUMIF(Kunci_Penyesuaian!$D$4:$D$65,$B5,Kunci_Penyesuaian!$E$4:$E$65) -> 0 | J5: =SUMIF(Kunci_Penyesuaian!$D$4:$D$65,$B5,Kunci_Penyesuaian!$F$4:$F$65) -> 0 | K5: =IF(E5+G5+I5-F5-H5-J5>0,E5+G5+I5-F5-H5-J5,0) -> 37850000 | L5: =IF(F5+H5+J5-E5-G5-I5>0,F5+H5+J5-E5-G5-I5,0) -> 0 | M5: =SUMIF(Jurnal_Penutup!$D$5:$D$82,$B5,Jurnal_Penutup!$E$5:$E$82) -> 0 | N5: =SUMIF(Jurnal_Penutup!$D$5:$D$82,$B5,Jurnal_Penutup!$F$5:$F$82) -> 0 | O5: =IF(K5+M5-L5-N5>0,K5+M5-L5-N5,0) -> 37850000 | P5: =IF(L5+N5-K5-M5>0,L5+N5-K5-M5,0) -> 0
A6: 1-003 | B6: Piutang Usaha | C6: Aset | D6: Debit | E6: =SUMIF(Saldo_Awal!$B$4:$B$91,$B6,Saldo_Awal!$C$4:$C$91) -> 60000000 | F6: =SUMIF(Saldo_Awal!$B$4:$B$91,$B6,Saldo_Awal!$D$4:$D$91) -> 0 | G6: =SUMIF(Kunci_Jurnal_80!$E$4:$E$230,$B6,Kunci_Jurnal_80!$F$4:$F$230) -> 483630000 | H6: =SUMIF(Kunci_Jurnal_80!$E$4:$E$230,$B6,Kunci_Jurnal_80!$G$4:$G$230) -> 425490000 | I6: =SUMIF(Kunci_Penyesuaian!$D$4:$D$65,$B6,Kunci_Penyesuaian!$E$4:$E$65) -> 0 | J6: =SUMIF(Kunci_Penyesuaian!$D$4:$D$65,$B6,Kunci_Penyesuaian!$F$4:$F$65) -> 2000000 | K6: =IF(E6+G6+I6-F6-H6-J6>0,E6+G6+I6-F6-H6-J6,0) -> 116140000 | L6: =IF(F6+H6+J6-E6-G6-I6>0,F6+H6+J6-E6-G6-I6,0) -> 0 | M6: =SUMIF(Jurnal_Penutup!$D$5:$D$82,$B6,Jurnal_Penutup!$E$5:$E$82) -> 0 | N6: =SUMIF(Jurnal_Penutup!$D$5:$D$82,$B6,Jurnal_Penutup!$F$5:$F$82) -> 0 | O6: =IF(K6+M6-L6-N6>0,K6+M6-L6-N6,0) -> 116140000 | P6: =IF(L6+N6-K6-M6>0,L6+N6-K6-M6,0) -> 0
A7: 1-004 | B7: Piutang Karyawan | C7: Aset | D7: Debit | E7: =SUMIF(Saldo_Awal!$B$4:$B$91,$B7,Saldo_Awal!$C$4:$C$91) -> 0 | F7: =SUMIF(Saldo_Awal!$B$4:$B$91,$B7,Saldo_Awal!$D$4:$D$91) -> 0 | G7: =SUMIF(Kunci_Jurnal_80!$E$4:$E$230,$B7,Kunci_Jurnal_80!$F$4:$F$230) -> 5000000 | H7: =SUMIF(Kunci_Jurnal_80!$E$4:$E$230,$B7,Kunci_Jurnal_80!$G$4:$G$230) -> 2000000 | I7: =SUMIF(Kunci_Penyesuaian!$D$4:$D$65,$B7,Kunci_Penyesuaian!$E$4:$E$65) -> 0 | J7: =SUMIF(Kunci_Penyesuaian!$D$4:$D$65,$B7,Kunci_Penyesuaian!$F$4:$F$65) -> 0 | K7: =IF(E7+G7+I7-F7-H7-J7>0,E7+G7+I7-F7-H7-J7,0) -> 3000000 | L7: =IF(F7+H7+J7-E7-G7-I7>0,F7+H7+J7-E7-G7-I7,0) -> 0 | M7: =SUMIF(Jurnal_Penutup!$D$5:$D$82,$B7,Jurnal_Penutup!$E$5:$E$82) -> 0 | N7: =SUMIF(Jurnal_Penutup!$D$5:$D$82,$B7,Jurnal_Penutup!$F$5:$F$82) -> 0 | O7: =IF(K7+M7-L7-N7>0,K7+M7-L7-N7,0) -> 3000000 | P7: =IF(L7+N7-K7-M7>0,L7+N7-K7-M7,0) -> 0
A8: 1-005 | B8: Piutang Bunga | C8: Aset | D8: Debit | E8: =SUMIF(Saldo_Awal!$B$4:$B$91,$B8,Saldo_Awal!$C$4:$C$91) -> 0 | F8: =SUMIF(Saldo_Awal!$B$4:$B$91,$B8,Saldo_Awal!$D$4:$D$91) -> 0 | G8: =SUMIF(Kunci_Jurnal_80!$E$4:$E$230,$B8,Kunci_Jurnal_80!$F$4:$F$230) -> 0 | H8: =SUMIF(Kunci_Jurnal_80!$E$4:$E$230,$B8,Kunci_Jurnal_80!$G$4:$G$230) -> 0 | I8: =SUMIF(Kunci_Penyesuaian!$D$4:$D$65,$B8,Kunci_Penyesuaian!$E$4:$E$65) -> 700000 | J8: =SUMIF(Kunci_Penyesuaian!$D$4:$D$65,$B8,Kunci_Penyesuaian!$F$4:$F$65) -> 0 | K8: =IF(E8+G8+I8-F8-H8-J8>0,E8+G8+I8-F8-H8-J8,0) -> 700000 | L8: =IF(F8+H8+J8-E8-G8-I8>0,F8+H8+J8-E8-G8-I8,0) -> 0 | M8: =SUMIF(Jurnal_Penutup!$D$5:$D$82,$B8,Jurnal_Penutup!$E$5:$E$82) -> 0 | N8: =SUMIF(Jurnal_Penutup!$D$5:$D$82,$B8,Jurnal_Penutup!$F$5:$F$82) -> 0 | O8: =IF(K8+M8-L8-N8>0,K8+M8-L8-N8,0) -> 700000 | P8: =IF(L8+N8-K8-M8>0,L8+N8-K8-M8,0) -> 0
A9: 1-006 | B9: Piutang Pendapatan | C9: Aset | D9: Debit | E9: =SUMIF(Saldo_Awal!$B$4:$B$91,$B9,Saldo_Awal!$C$4:$C$91) -> 0 | F9: =SUMIF(Saldo_Awal!$B$4:$B$91,$B9,Saldo_Awal!$D$4:$D$91) -> 0 | G9: =SUMIF(Kunci_Jurnal_80!$E$4:$E$230,$B9,Kunci_Jurnal_80!$F$4:$F$230) -> 0 | H9: =SUMIF(Kunci_Jurnal_80!$E$4:$E$230,$B9,Kunci_Jurnal_80!$G$4:$G$230) -> 0 | I9: =SUMIF(Kunci_Penyesuaian!$D$4:$D$65,$B9,Kunci_Penyesuaian!$E$4:$E$65) -> 0 | J9: =SUMIF(Kunci_Penyesuaian!$D$4:$D$65,$B9,Kunci_Penyesuaian!$F$4:$F$65) -> 0 | K9: =IF(E9+G9+I9-F9-H9-J9>0,E9+G9+I9-F9-H9-J9,0) -> 0 | L9: =IF(F9+H9+J9-E9-G9-I9>0,F9+H9+J9-E9-G9-I9,0) -> 0 | M9: =SUMIF(Jurnal_Penutup!$D$5:$D$82,$B9,Jurnal_Penutup!$E$5:$E$82) -> 0 | N9: =SUMIF(Jurnal_Penutup!$D$5:$D$82,$B9,Jurnal_Penutup!$F$5:$F$82) -> 0 | O9: =IF(K9+M9-L9-N9>0,K9+M9-L9-N9,0) -> 0 | P9: =IF(L9+N9-K9-M9>0,L9+N9-K9-M9,0) -> 0
A10: 1-007 | B10: Persediaan Barang Dagang | C10: Aset | D10: Debit | E10: =SUMIF(Saldo_Awal!$B$4:$B$91,$B10,Saldo_Awal!$C$4:$C$91) -> 120000000 | F10: =SUMIF(Saldo_Awal!$B$4:$B$91,$B10,Saldo_Awal!$D$4:$D$91) -> 0 | G10: =SUMIF(Kunci_Jurnal_80!$E$4:$E$230,$B10,Kunci_Jurnal_80!$F$4:$F$230) -> 574000000 | H10: =SUMIF(Kunci_Jurnal_80!$E$4:$E$230,$B10,Kunci_Jurnal_80!$G$4:$G$230) -> 436300000 | I10: =SUMIF(Kunci_Penyesuaian!$D$4:$D$65,$B10,Kunci_Penyesuaian!$E$4:$E$65) -> 0 | J10: =SUMIF(Kunci_Penyesuaian!$D$4:$D$65,$B10,Kunci_Penyesuaian!$F$4:$F$65) -> 5900000 | K10: =IF(E10+G10+I10-F10-H10-J10>0,E10+G10+I10-F10-H10-J10,0) -> 251800000 | L10: =IF(F10+H10+J10-E10-G10-I10>0,F10+H10+J10-E10-G10-I10,0) -> 0 | M10: =SUMIF(Jurnal_Penutup!$D$5:$D$82,$B10,Jurnal_Penutup!$E$5:$E$82) -> 0 | N10: =SUMIF(Jurnal_Penutup!$D$5:$D$82,$B10,Jurnal_Penutup!$F$5:$F$82) -> 0 | O10: =IF(K10+M10-L10-N10>0,K10+M10-L10-N10,0) -> 251800000 | P10: =IF(L10+N10-K10-M10>0,L10+N10-K10-M10,0) -> 0
A11: 1-008 | B11: PPN Masukan | C11: Aset | D11: Debit | E11: =SUMIF(Saldo_Awal!$B$4:$B$91,$B11,Saldo_Awal!$C$4:$C$91) -> 0 | F11: =SUMIF(Saldo_Awal!$B$4:$B$91,$B11,Saldo_Awal!$D$4:$D$91) -> 0 | G11: =SUMIF(Kunci_Jurnal_80!$E$4:$E$230,$B11,Kunci_Jurnal_80!$F$4:$F$230) -> 103125000 | H11: =SUMIF(Kunci_Jurnal_80!$E$4:$E$230,$B11,Kunci_Jurnal_80!$G$4:$G$230) -> 2013000 | I11: =SUMIF(Kunci_Penyesuaian!$D$4:$D$65,$B11,Kunci_Penyesuaian!$E$4:$E$65) -> 0 | J11: =SUMIF(Kunci_Penyesuaian!$D$4:$D$65,$B11,Kunci_Penyesuaian!$F$4:$F$65) -> 74954000 | K11: =IF(E11+G11+I11-F11-H11-J11>0,E11+G11+I11-F11-H11-J11,0) -> 26158000 | L11: =IF(F11+H11+J11-E11-G11-I11>0,F11+H11+J11-E11-G11-I11,0) -> 0 | M11: =SUMIF(Jurnal_Penutup!$D$5:$D$82,$B11,Jurnal_Penutup!$E$5:$E$82) -> 0 | N11: =SUMIF(Jurnal_Penutup!$D$5:$D$82,$B11,Jurnal_Penutup!$F$5:$F$82) -> 0 | O11: =IF(K11+M11-L11-N11>0,K11+M11-L11-N11,0) -> 26158000 | P11: =IF(L11+N11-K11-M11>0,L11+N11-K11-M11,0) -> 0
A12: 1-009 | B12: PPh 22 Dibayar di Muka | C12: Aset | D12: Debit | E12: =SUMIF(Saldo_Awal!$B$4:$B$91,$B12,Saldo_Awal!$C$4:$C$91) -> 0 | F12: =SUMIF(Saldo_Awal!$B$4:$B$91,$B12,Saldo_Awal!$D$4:$D$91) -> 0 | G12: =SUMIF(Kunci_Jurnal_80!$E$4:$E$230,$B12,Kunci_Jurnal_80!$F$4:$F$230) -> 2625000 | H12: =SUMIF(Kunci_Jurnal_80!$E$4:$E$230,$B12,Kunci_Jurnal_80!$G$4:$G$230) -> 0 | I12: =SUMIF(Kunci_Penyesuaian!$D$4:$D$65,$B12,Kunci_Penyesuaian!$E$4:$E$65) -> 0 | J12: =SUMIF(Kunci_Penyesuaian!$D$4:$D$65,$B12,Kunci_Penyesuaian!$F$4:$F$65) -> 0 | K12: =IF(E12+G12+I12-F12-H12-J12>0,E12+G12+I12-F12-H12-J12,0) -> 2625000 | L12: =IF(F12+H12+J12-E12-G12-I12>0,F12+H12+J12-E12-G12-I12,0) -> 0 | M12: =SUMIF(Jurnal_Penutup!$D$5:$D$82,$B12,Jurnal_Penutup!$E$5:$E$82) -> 0 | N12: =SUMIF(Jurnal_Penutup!$D$5:$D$82,$B12,Jurnal_Penutup!$F$5:$F$82) -> 0 | O12: =IF(K12+M12-L12-N12>0,K12+M12-L12-N12,0) -> 2625000 | P12: =IF(L12+N12-K12-M12>0,L12+N12-K12-M12,0) -> 0
A13: 1-010 | B13: PPh 23 Dibayar di Muka | C13: Aset | D13: Debit | E13: =SUMIF(Saldo_Awal!$B$4:$B$91,$B13,Saldo_Awal!$C$4:$C$91) -> 0 | F13: =SUMIF(Saldo_Awal!$B$4:$B$91,$B13,Saldo_Awal!$D$4:$D$91) -> 0 | G13: =SUMIF(Kunci_Jurnal_80!$E$4:$E$230,$B13,Kunci_Jurnal_80!$F$4:$F$230) -> 0 | H13: =SUMIF(Kunci_Jurnal_80!$E$4:$E$230,$B13,Kunci_Jurnal_80!$G$4:$G$230) -> 0 | I13: =SUMIF(Kunci_Penyesuaian!$D$4:$D$65,$B13,Kunci_Penyesuaian!$E$4:$E$65) -> 0 | J13: =SUMIF(Kunci_Penyesuaian!$D$4:$D$65,$B13,Kunci_Penyesuaian!$F$4:$F$65) -> 0 | K13: =IF(E13+G13+I13-F13-H13-J13>0,E13+G13+I13-F13-H13-J13,0) -> 0 | L13: =IF(F13+H13+J13-E13-G13-I13>0,F13+H13+J13-E13-G13-I13,0) -> 0 | M13: =SUMIF(Jurnal_Penutup!$D$5:$D$82,$B13,Jurnal_Penutup!$E$5:$E$82) -> 0 | N13: =SUMIF(Jurnal_Penutup!$D$5:$D$82,$B13,Jurnal_Penutup!$F$5:$F$82) -> 0 | O13: =IF(K13+M13-L13-N13>0,K13+M13-L13-N13,0) -> 0 | P13: =IF(L13+N13-K13-M13>0,L13+N13-K13-M13,0) -> 0
A14: 1-011 | B14: PPh Final Dibayar di Muka | C14: Aset | D14: Debit | E14: =SUMIF(Saldo_Awal!$B$4:$B$91,$B14,Saldo_Awal!$C$4:$C$91) -> 0 | F14: =SUMIF(Saldo_Awal!$B$4:$B$91,$B14,Saldo_Awal!$D$4:$D$91) -> 0 | G14: =SUMIF(Kunci_Jurnal_80!$E$4:$E$230,$B14,Kunci_Jurnal_80!$F$4:$F$230) -> 0 | H14: =SUMIF(Kunci_Jurnal_80!$E$4:$E$230,$B14,Kunci_Jurnal_80!$G$4:$G$230) -> 0 | I14: =SUMIF(Kunci_Penyesuaian!$D$4:$D$65,$B14,Kunci_Penyesuaian!$E$4:$E$65) -> 0 | J14: =SUMIF(Kunci_Penyesuaian!$D$4:$D$65,$B14,Kunci_Penyesuaian!$F$4:$F$65) -> 0 | K14: =IF(E14+G14+I14-F14-H14-J14>0,E14+G14+I14-F14-H14-J14,0) -> 0 | L14: =IF(F14+H14+J14-E14-G14-I14>0,F14+H14+J14-E14-G14-I14,0) -> 0 | M14: =SUMIF(Jurnal_Penutup!$D$5:$D$82,$B14,Jurnal_Penutup!$E$5:$E$82) -> 0 | N14: =SUMIF(Jurnal_Penutup!$D$5:$D$82,$B14,Jurnal_Penutup!$F$5:$F$82) -> 0 | O14: =IF(K14+M14-L14-N14>0,K14+M14-L14-N14,0) -> 0 | P14: =IF(L14+N14-K14-M14>0,L14+N14-K14-M14,0) -> 0
A15: 1-012 | B15: Sewa Dibayar di Muka | C15: Aset | D15: Debit | E15: =SUMIF(Saldo_Awal!$B$4:$B$91,$B15,Saldo_Awal!$C$4:$C$91) -> 6000000 | F15: =SUMIF(Saldo_Awal!$B$4:$B$91,$B15,Saldo_Awal!$D$4:$D$91) -> 0 | G15: =SUMIF(Kunci_Jurnal_80!$E$4:$E$230,$B15,Kunci_Jurnal_80!$F$4:$F$230) -> 18000000 | H15: =SUMIF(Kunci_Jurnal_80!$E$4:$E$230,$B15,Kunci_Jurnal_80!$G$4:$G$230) -> 0 | I15: =SUMIF(Kunci_Penyesuaian!$D$4:$D$65,$B15,Kunci_Penyesuaian!$E$4:$E$65) -> 0 | J15: =SUMIF(Kunci_Penyesuaian!$D$4:$D$65,$B15,Kunci_Penyesuaian!$F$4:$F$65) -> 6000000 | K15: =IF(E15+G15+I15-F15-H15-J15>0,E15+G15+I15-F15-H15-J15,0) -> 18000000 | L15: =IF(F15+H15+J15-E15-G15-I15>0,F15+H15+J15-E15-G15-I15,0) -> 0 | M15: =SUMIF(Jurnal_Penutup!$D$5:$D$82,$B15,Jurnal_Penutup!$E$5:$E$82) -> 0 | N15: =SUMIF(Jurnal_Penutup!$D$5:$D$82,$B15,Jurnal_Penutup!$F$5:$F$82) -> 0 | O15: =IF(K15+M15-L15-N15>0,K15+M15-L15-N15,0) -> 18000000 | P15: =IF(L15+N15-K15-M15>0,L15+N15-K15-M15,0) -> 0
... A91: 2-021 | B91: PPN Keluaran | C91: Liabilitas | D91: Kredit | E91: =SUMIF(Saldo_Awal!$B$4:$B$91,$B91,Saldo_Awal!$C$4:$C$91) -> 0 | F91: =SUMIF(Saldo_Awal!$B$4:$B$91,$B91,Saldo_Awal!$D$4:$D$91) -> 0 | G91: =SUMIF(Kunci_Jurnal_80!$E$4:$E$230,$B91,Kunci_Jurnal_80!$F$4:$F$230) -> 3256000 | H91: =SUMIF(Kunci_Jurnal_80!$E$4:$E$230,$B91,Kunci_Jurnal_80!$G$4:$G$230) -> 77770000 | I91: =SUMIF(Kunci_Penyesuaian!$D$4:$D$65,$B91,Kunci_Penyesuaian!$E$4:$E$65) -> 74954000 | J91: =SUMIF(Kunci_Penyesuaian!$D$4:$D$65,$B91,Kunci_Penyesuaian!$F$4:$F$65) -> 440000 | K91: =IF(E91+G91+I91-F91-H91-J91>0,E91+G91+I91-F91-H91-J91,0) -> 0 | L91: =IF(F91+H91+J91-E91-G91-I91>0,F91+H91+J91-E91-G91-I91,0) -> 0 | M91: =SUMIF(Jurnal_Penutup!$D$5:$D$82,$B91,Jurnal_Penutup!$E$5:$E$82) -> 0 | N91: =SUMIF(Jurnal_Penutup!$D$5:$D$82,$B91,Jurnal_Penutup!$F$5:$F$82) -> 0 | O91: =IF(K91+M91-L91-N91>0,K91+M91-L91-N91,0) -> 0 | P91: =IF(L91+N91-K91-M91>0,L91+N91-K91-M91,0) -> 0
A92: TOTAL | E92: =SUM(E4:E91) -> 569000000 | F92: =SUM(F4:F91) -> 569000000 | G92: =SUM(G4:G91) -> 5183570000 | H92: =SUM(H4:H91) -> 5183570000 | I92: =SUM(I4:I91) -> 147294000 | J92: =SUM(J4:J91) -> 147294000 | K92: =SUM(K4:K91) -> 3097950000 | L92: =SUM(L4:L91) -> 3097950000 | ... P92: =SUM(P4:P91) -> 2514400000

Sheet Rekap_AP
A1: REKAP ACCOUNTS PAYABLE (AP) – SUBLEDGER & AGING
A3: Supplier | B3: Opening | C3: Invoice / Pembelian Kredit | D3: Retur | E3: Pembayaran | F3: Diskon | G3: Saldo Akhir | H3: Current 0-30 | I3: 31-60 | J3: Dokumen Utama
A4: Supplier A | B4: 0 | C4: 277500000 | D4: 16650000 | E4: 255800000 | F4: 2400000 | G4: =B4+C4-D4-E4-F4 -> 2650000 | H4: 2650000 | I4: 0 | J4: INV-A-001 / RT-AP-001 / PAY-A-001/003
A5: Supplier B | B5: 0 | C5: 111000000 | D5: 0 | E5: 90000000 | F5: 0 | G5: =B5+C5-D5-E5-F5 -> 21000000 | H5: 21000000 | I5: 0 | J5: INV-B-001 / PAY-B-001 / REB-001
A6: Supplier G | B6: 70000000 | C6: 0 | D6: 0 | E6: 0 | F6: 0 | G6: =B6+C6-D6-E6-F6 -> 70000000 | H6: 0 | I6: 70000000 | J6: Opening AP 31-Dec-2026
A7: Supplier Pemerintah | B7: 0 | C7: 54750000 | D7: 0 | E7: 0 | F7: 0 | G7: =B7+C7-D7-E7-F7 -> 54750000 | H7: 54750000 | I7: 0 | J7: PPH22-001
A8: PT Kantor Jaya | B8: 0 | C8: 44400000 | D8: 0 | E8: 44400000 | F8: 0 | G8: =B8+C8-D8-E8-F8 -> 0 | H8: 0 | I8: 0 | J8: FA-002 / PAY-FA-001
A9: Toko ATK Nusantara | B9: 0 | C9: 3330000 | D9: 0 | E9: 3330000 | F9: 0 | G9: =B9+C9-D9-E9-F9 -> 0 | H9: 0 | I9: 0 | J9: ATK-002 / PAY-ATK-001
A11: TOTAL SUBLEDGER | G11: =SUM(G4:G9) -> 148400000 | H11: =SUM(H4:H9) -> 78400000 | I11: =SUM(I4:I9) -> 70000000

Sheet Rekap_AR
A1: REKAP ACCOUNTS RECEIVABLE (AR) – SUBLEDGER & AGING
A3: Customer | B3: Opening | C3: Invoice Penjualan Kredit | D3: Retur / Rebate | E3: NSF / Pembalikan | F3: Penerimaan | G3: Diskon | H3: Penghapusan | I3: Saldo Akhir | J3: Current 0-30 | K3: 31-60 | L3: Dokumen Utama
A4: Pelanggan B | B4: 0 | C4: 177600000 | D4: 11100000 | E4: 3000000 | F4: 163300000 | G4: 0 | H4: 0 | I4: =B4+C4-D4+E4-F4-G4-H4 -> 6200000 | J4: 6200000 | K4: 0 | L4: INV-C-001 / RT-AR-001 / NSF-001 / AR-DSC-001
A5: Pelanggan D | B5: 0 | C5: 233100000 | D5: 21090000 | E5: 0 | F5: 190000000 | G5: 0 | H5: 0 | I5: =B5+C5-D5+E5-F5-G5-H5 -> 22010000 | J5: 22010000 | K5: 0 | L5: INV-D-001 / RT-AR-002 / REB-AR-001
A6: Pelanggan F | B6: 0 | C6: 99900000 | D6: 0 | E6: 0 | F6: 69970000 | G6: 0 | H6: 0 | I6: =B6+C6-D6+E6-F6-G6-H6 -> 29930000 | J6: 29930000 | K6: 0 | L6: INV-F-001 / AR-REC-003
A7: Pelanggan H | B7: 60000000 | C7: 0 | D7: 0 | E7: 0 | F7: 0 | G7: 0 | H7: 2000000 | I7: =B7+C7-D7+E7-F7-G7-H7 -> 58000000 | J7: 0 | K7: 58000000 | L7: Opening AR / Write-off adjustment
A8: TOTAL SUBLEDGER | I8: =SUM(I4:I7) -> 116140000 | J8: =SUM(J4:J7) -> 58140000 | K8: =SUM(K4:K7) -> 58000000

Sheet Inventory_Kartu
A1: KARTU PERSEDIAAN – PERPETUAL FIFO (MODUL LATIHAN)
A2: Gunakan master SKU pada Data_Master. Contoh di bawah memakai unit & harga pokok yang eksplisit agar FIFO dapat dipelajari langkah demi langkah.
A3: Tanggal | B3: SKU | C3: Dokumen | D3: Masuk Qty | E3: Harga Satuan | F3: Masuk Nilai | G3: Keluar Qty | H3: HPP Keluar | I3: Saldo Qty | J3: Saldo Nilai
A4: 46389 | B4: SKU-01 | C4: PUR-001 | D4: 20 | E4: 2500000 | F4: =IF(D4="","",D4*E4) -> 50000000 | I4: =IF(D4="",0,D4)-IF(G4="",0,G4) -> 20 | J4: =IF(F4="",0,F4)-IF(H4="",0,H4) -> 50000000
A5: 46392 | B5: SKU-01 | C5: SAL-001 | F5: =IF(D5="","",D5*E5) | G5: 8 | H5: =8*2500000 -> 20000000 | I5: =I4+IF(D5="",0,D5)-IF(G5="",0,G5) -> 12 | J5: =J4+IF(F5="",0,F5)-IF(H5="",0,H5) -> 30000000
A6: 46395 | B6: SKU-01 | C6: PUR-002 | D6: 10 | E6: 2600000 | F6: =IF(D6="","",D6*E6) -> 26000000 | I6: =I5+IF(D6="",0,D6)-IF(G6="",0,G6) -> 22 | J6: =J5+IF(F6="",0,F6)-IF(H6="",0,H6) -> 56000000
A7: 46399 | B7: SKU-01 | C7: SAL-002 | F7: =IF(D7="","",D7*E7) | G7: 12 | I7: =I6+IF(D7="",0,D7)-IF(G7="",0,G7) -> 10 | J7: =J6+IF(F7="",0,F7)-IF(H7="",0,H7) -> 56000000
A8: 46402 | B8: SKU-01 | C8: SAL-003 | F8: =IF(D8="","",D8*E8) | G8: 5 | H8: =10*2500000+2*2600000 -> 30200000 | I8: =I7+IF(D8="",0,D8)-IF(G8="",0,G8) -> 5 | J8: =J7+IF(F8="",0,F8)-IF(H8="",0,H8) -> 25800000
A9: 46390 | B9: SKU-03 | C9: PUR-003 | D9: 100 | E9: 45000 | F9: =IF(D9="","",D9*E9) -> 4500000 | H9: =5*2600000 -> 13000000 | I9: =I8+IF(D9="",0,D9)-IF(G9="",0,G9) -> 105 | J9: =J8+IF(F9="",0,F9)-IF(H9="",0,H9) -> 17300000
A10: 46397 | B10: SKU-03 | C10: PUR-004 | D10: 50 | E10: 47000 | F10: =IF(D10="","",D10*E10) -> 2350000 | I10: =I9+IF(D10="",0,D10)-IF(G10="",0,G10) -> 155 | J10: =J9+IF(F10="",0,F10)-IF(H10="",0,H10) -> 19650000
A11: 46403 | B11: SKU-03 | C11: SAL-004 | F11: =IF(D11="","",D11*E11) | G11: 120 | H11: =100*45000+20*47000 -> 5440000 | I11: =I10+IF(D11="",0,D11)-IF(G11="",0,G11) -> 35 | J11: =J10+IF(F11="",0,F11)-IF(H11="",0,H11) -> 14210000
A12: 46407 | B12: SKU-03 | C12: PUR-005 | D12: 80 | E12: 48000 | F12: =IF(D12="","",D12*E12) -> 3840000 | I12: =I11+IF(D12="",0,D12)-IF(G12="",0,G12) -> 115 | J12: =J11+IF(F12="",0,F12)-IF(H12="",0,H12) -> 18050000
A13: 46412 | B13: SKU-03 | C13: SAL-005 | F13: =IF(D13="","",D13*E13) | G13: 50 | H13: =50*47000 -> 2350000 | I13: =I12+IF(D13="",0,D13)-IF(G13="",0,G13) -> 65 | J13: =J12+IF(F13="",0,F13)-IF(H13="",0,H13) -> 15700000

Sheet Payroll
A1: PAYROLL JANUARI 2027 – SIMULASI GAJI, PPh 21, BPJS & JURNAL
A3: NIK | B3: Nama | C3: Gaji Pokok | D3: Tunjangan/OT | E3: Bruto | F3: PPh21 (Latihan) | G3: BPJS Pegawai | H3: Take Home Pay | I3: BPJS Pemberi Kerja | J3: Beban Perusahaan | K3: Jurnal Ringkas
A4: E001 | B4: Andi | C4: 5000000 | D4: 0 | E4: =C4+D4 -> 5000000 | F4: =F4 -> 0 | G4: =G4 -> 0 | H4: =E4-F4-G4 -> 5000000 | I4: =E4*8% -> 400000 | J4: =E4+I4 -> 5400000 | K4: =IF(ROW()=4,"Dr Beban Gaji / Cr PPh21, BPJS, Bank","") -> Dr Beban Gaji / Cr PPh21, BPJS, Bank
A5: E002 | B5: Budi | C5: 4500000 | D5: 0 | E5: =C5+D5 -> 4500000 | F5: =F5 -> 0 | G5: =G5 -> 0 | H5: =E5-F5-G5 -> 4500000 | I5: =E5*8% -> 360000 | J5: =E5+I5 -> 4860000 | K5: =IF(ROW()=4,"Dr Beban Gaji / Cr PPh21, BPJS, Bank","")
A6: E003 | B6: Citra | C6: 4000000 | D6: 0 | E6: =C6+D6 -> 4000000 | F6: =F6 -> 0 | G6: =G6 -> 0 | H6: =E6-F6-G6 -> 4000000 | I6: =E6*8% -> 320000 | J6: =E6+I6 -> 4320000 | K6: =IF(ROW()=4,"Dr Beban Gaji / Cr PPh21, BPJS, Bank","")
A7: E004 | B7: Deni | C7: 3500000 | D7: 0 | E7: =C7+D7 -> 3500000 | F7: =F7 -> 0 | G7: =G7 -> 0 | H7: =E7-F7-G7 -> 3500000 | I7: =E7*8% -> 280000 | J7: =E7+I7 -> 3780000 | K7: =IF(ROW()=4,"Dr Beban Gaji / Cr PPh21, BPJS, Bank","")
A8: E005 | B8: Eka | C8: 4000000 | D8: 0 | E8: =C8+D8 -> 4000000 | F8: =F8 -> 0 | G8: =G8 -> 0 | H8: =E8-F8-G8 -> 4000000 | I8: =E8*8% -> 320000 | J8: =E8+I8 -> 4320000 | K8: =IF(ROW()=4,"Dr Beban Gaji / Cr PPh21, BPJS, Bank","")
A9: E006 | B9: Fina | C9: 4000000 | D9: 2000000 | E9: =C9+D9 -> 6000000 | F9: =F9 -> 0 | G9: =G9 -> 0 | H9: =E9-F9-G9 -> 6000000 | I9: =E9*8% -> 480000 | J9: =E9+I9 -> 6480000 | K9: =IF(ROW()=4,"Dr Beban Gaji / Cr PPh21, BPJS, Bank","")
A11: TOTAL | C11: =SUM(C4:C9) -> 25000000 | E11: =SUM(E4:E9) -> 27000000 | F11: =SUM(F4:F9) -> 0 | G11: =SUM(G4:G9) -> 0 | H11: =SUM(H4:H9) -> 27000000 | I11: =SUM(I4:I9) -> 2160000 | J11: =SUM(J4:J9) -> 29160000
A13: Jurnal payroll | B13: Debit Beban Gaji = Bruto | C13: Kredit Utang PPh21 = PPh21 | D13: Kredit Utang BPJS = BPJS pegawai | E13: Kredit Bank = Take Home Pay | F13: Jurnal pemberi kerja | G13: Debit Beban BPJS = BPJS employer | H13: Kredit Utang BPJS = BPJS employer

Sheet Rekonsiliasi_Bank
A1: REKONSILIASI BANK – LATIHAN & KUNCI
A3: Item Rekonsiliasi | B3: Nilai (Rp) | C3: Tanda | D3: Penyesuaian ke saldo | E3: Sisi | F3: Keterangan
A4: Saldo menurut buku | B4: 1403427000 | D4: 0 | E4: Buku | F4: Saldo GL Bank sebelum item bank-only
A5: Saldo menurut rekening koran | B5: 1407177000 | D5: 0 | E5: Bank | F5: Saldo akhir rekening koran sebelum rekonsiliasi
A6: Setoran dalam perjalanan | B6: 8000000 | C6: + | D6: 8000000 | E6: Bank | F6: Belum masuk mutasi bank
A7: Cek/giro beredar | B7: 6000000 | C7: - | D7: -6000000 | E7: Bank | F7: Belum dicairkan bank
A8: Transfer pelanggan langsung ke bank | B8: 2000000 | C8: + | D8: 2000000 | E8: Buku | F8: Harus ditambahkan ke buku
A9: Bunga bank belum dibukukan | B9: 5000000 | C9: + | D9: 5000000 | E9: Buku | F9: Harus ditambahkan ke buku
A10: Biaya administrasi bank belum dibukukan | B10: 1250000 | C10: - | D10: -1250000 | E10: Buku | F10: Harus mengurangi saldo buku
A11: Saldo bank disesuaikan | B11: =B5+B6+D7 -> 1409177000 | D11: =B4+D8+D9+D10 -> 1409177000
A13: CHECK | B13: =IF(ABS(B11-D11)<0.01,"BALANCE","PERIKSA") -> BALANCE
A16: Versi siswa | B16: Isi kolom nilai item berikut dari dokumen bank yang diberikan mentor, lalu hitung saldo disesuaikan.

Sheet Rekonsiliasi_Akun
A1: REKONSILIASI AKUN – AP, AR, INVENTORY, TAX, PAYROLL
A3: Akun | B3: Saldo Subledger | C3: Saldo GL | D3: Selisih | E3: Status | F3: Reconciling Item | G3: Action | H3: PIC
A4: Utang Usaha | B4: =Rekap_AP!G11 -> 148400000 | C4: =Buku_Besar!$P$30 -> 148400000 | D4: =C4-B4 -> 0 | E4: =IF(ABS(D4)<0.01,"TIED","PERIKSA") -> TIED | F4: AP invoice subledger excludes accrued liabilities | G4: Map only vendor invoices here; accruals go to Utang Beban / Akrual | H4: AP Accountant
A5: Piutang Usaha | B5: =Rekap_AR!I8 -> 116140000 | C5: =Buku_Besar!$O$6 -> 116140000 | D5: =C5-B5 -> 0 | E5: =IF(ABS(D5)<0.01,"TIED","PERIKSA") -> TIED | F5: AR subledger includes NSF and write-off controls | G5: Tie customer-by-customer balances to GL | H5: AR Accountant
A6: Persediaan | B6: =Inventory_Kartu!J13 -> 15700000 | C6: =Buku_Besar!$O$10 -> 251800000 | D6: =C6-B6 -> 236100000 | E6: ="CONTROL ONLY" -> CONTROL ONLY | F6: Illustrative FIFO card is only for selected SKUs | G6: Use full warehouse listing for GL tie-out | H6: Inventory Accountant
A7: PPN | B7: =Buku_Besar!$O$11 -> 26158000 | C7: =Buku_Besar!$O$11 -> 26158000 | D7: =C7-B7 -> 0 | E7: =IF(ABS(D7)<0.01,"TIED","PERIKSA") -> TIED | F7: PPN control: PPN Keluaran diklarifikasi terhadap PPN Masukan; sisa PPN Masukan menjadi posisi kredit pajak/lebih bayar latihan | G7: Tie VAT return to GL before filing | H7: Tax Accountant
A8: Payroll | B8: =Payroll!E11 -> 27000000 | C8: =Buku_Besar!$O$61 -> 0 | D8: =C8-B8 -> -27000000 | E8: ="CONTROL ONLY" -> CONTROL ONLY | F8: Register payroll adalah contoh proses; perbedaan dengan GL berasal dari accrual/bonus/beban pemberi kerja di modul lain. | G8: Tie register, bank payment and payroll liabilities | H8: Payroll Accountant

Sheet Neraca_Saldo
A1: NERACA SALDO – SEBELUM PENYESUAIAN
A2: Sumber: Saldo awal + 80 Jurnal Umum.
A3: Kode Akun | B3: Nama Akun | C3: Kategori | D3: Saldo Normal | E3: Debit (Rp) | F3: Kredit (Rp)
A4: 1-001 | B4: Bank | C4: Aset | D4: Debit | E4: =Buku_Besar!E4+Buku_Besar!G4 -> 2568414000 | F4: =Buku_Besar!F4+Buku_Besar!H4 -> 1164987000
A5: 1-002 | B5: Kas Kecil | C5: Aset | D5: Debit | E5: =Buku_Besar!E5+Buku_Besar!G5 -> 40150000 | F5: =Buku_Besar!F5+Buku_Besar!H5 -> 2300000
A6: 1-003 | B6: Piutang Usaha | C6: Aset | D6: Debit | E6: =Buku_Besar!E6+Buku_Besar!G6 -> 543630000 | F6: =Buku_Besar!F6+Buku_Besar!H6 -> 425490000
A7: 1-004 | B7: Piutang Karyawan | C7: Aset | D7: Debit | E7: =Buku_Besar!E7+Buku_Besar!G7 -> 5000000 | F7: =Buku_Besar!F7+Buku_Besar!H7 -> 2000000
A8: 1-005 | B8: Piutang Bunga | C8: Aset | D8: Debit | E8: =Buku_Besar!E8+Buku_Besar!G8 -> 0 | F8: =Buku_Besar!F8+Buku_Besar!H8 -> 0
A9: 1-006 | B9: Piutang Pendapatan | C9: Aset | D9: Debit | E9: =Buku_Besar!E9+Buku_Besar!G9 -> 0 | F9: =Buku_Besar!F9+Buku_Besar!H9 -> 0
A10: 1-007 | B10: Persediaan Barang Dagang | C10: Aset | D10: Debit | E10: =Buku_Besar!E10+Buku_Besar!G10 -> 694000000 | F10: =Buku_Besar!F10+Buku_Besar!H10 -> 436300000
A11: 1-008 | B11: PPN Masukan | C11: Aset | D11: Debit | E11: =Buku_Besar!E11+Buku_Besar!G11 -> 103125000 | F11: =Buku_Besar!F11+Buku_Besar!H11 -> 2013000
A12: 1-009 | B12: PPh 22 Dibayar di Muka | C12: Aset | D12: Debit | E12: =Buku_Besar!E12+Buku_Besar!G12 -> 2625000 | F12: =Buku_Besar!F12+Buku_Besar!H12 -> 0
A13: 1-010 | B13: PPh 23 Dibayar di Muka | C13: Aset | D13: Debit | E13: =Buku_Besar!E13+Buku_Besar!G13 -> 0 | F13: =Buku_Besar!F13+Buku_Besar!H13 -> 0
A14: 1-011 | B14: PPh Final Dibayar di Muka | C14: Aset | D14: Debit | E14: =Buku_Besar!E14+Buku_Besar!G14 -> 0 | F14: =Buku_Besar!F14+Buku_Besar!H14 -> 0
A15: 1-012 | B15: Sewa Dibayar di Muka | C15: Aset | D15: Debit | E15: =Buku_Besar!E15+Buku_Besar!G15 -> 24000000 | F15: =Buku_Besar!F15+Buku_Besar!H15 -> 0
... A91: 2-021 | B91: PPN Keluaran | C91: Liabilitas | D91: Kredit | E91: =Buku_Besar!E91+Buku_Besar!G91 -> 3256000 | F91: =Buku_Besar!F91+Buku_Besar!H91 -> 77770000
A92: TOTAL | E92: =SUM(E4:E91) -> 5752570000 | F92: =SUM(F4:F91) -> 5752570000

Sheet Jurnal_Penyesuaian
A1: LATIHAN 30 SOAL – JURNAL PENYESUAIAN | BASIC → PALING SULIT
A2: Isi kolom J:L. H:I adalah identitas baris. M:O memeriksa terhadap Kunci_Penyesuaian. Kasus 26 sengaja menguji apakah penyesuaian memang diperlukan.
A3: No | B3: Tanggal | C3: Tingkat / Jenis | D3: Soal | E3: Tambahan / Fakta Penting | F3: Nominal (Rp) | G3: Petunjuk | H3: No2 | I3: Tanggal2 | J3: Akun Jawaban | K3: Debit Jawaban | L3: Kredit Jawaban | M3: Cek Akun | N3: Cek Debit | O3: Cek Kredit | P3: Status
A4: 1 | B4: 46418 | C4: Basic – Perlengkapan terpakai | D4: Saldo Perlengkapan sebelum penyesuaian Rp5.000.000. Hasil pemeriksaan fisik menunjukkan sisa Rp3.800.000. | F4: 1200000 | G4: Debit Beban Perlengkapan; kredit Perlengkapan. | H4: 1 | I4: 46418 | M4: =IF(J4="","",IF(J4=Kunci_Penyesuaian!$D$4,"OK","SALAH")) | N4: =IF(J4="","",IF(ABS(K4-Kunci_Penyesuaian!$E$4)<0.01,"OK","SALAH")) | O4: =IF(J4="","",IF(ABS(L4-Kunci_Penyesuaian!$F$4)<0.01,"OK","SALAH")) | P4: =IF(COUNTA(J4:L4)=0,"Belum diisi",IF(COUNTIF(M4:O4,"OK")=3,"BENAR","PERIKSA")) -> Belum diisi
H5: 1 | I5: 46418 | M5: =IF(J5="","",IF(J5=Kunci_Penyesuaian!$D$5,"OK","SALAH")) | N5: =IF(J5="","",IF(ABS(K5-Kunci_Penyesuaian!$E$5)<0.01,"OK","SALAH")) | O5: =IF(J5="","",IF(ABS(L5-Kunci_Penyesuaian!$F$5)<0.01,"OK","SALAH")) | P5: =IF(COUNTA(J5:L5)=0,"Belum diisi",IF(COUNTIF(M5:O5,"OK")=3,"BENAR","PERIKSA")) -> Belum diisi
A7: 2 | B7: 46418 | C7: Basic – Sewa terpakai | D7: Sewa dibayar di muka yang manfaatnya sudah terpakai selama Januari sebesar Rp6.000.000. | F7: 6000000 | G7: Debit Beban Sewa; kredit Sewa Dibayar di Muka. | H7: 2 | I7: 46418 | M7: =IF(J7="","",IF(J7=Kunci_Penyesuaian!$D$6,"OK","SALAH")) | N7: =IF(J7="","",IF(ABS(K7-Kunci_Penyesuaian!$E$6)<0.01,"OK","SALAH")) | O7: =IF(J7="","",IF(ABS(L7-Kunci_Penyesuaian!$F$6)<0.01,"OK","SALAH")) | P7: =IF(COUNTA(J7:L7)=0,"Belum diisi",IF(COUNTIF(M7:O7,"OK")=3,"BENAR","PERIKSA")) -> Belum diisi
H8: 2 | I8: 46418 | M8: =IF(J8="","",IF(J8=Kunci_Penyesuaian!$D$7,"OK","SALAH")) | N8: =IF(J8="","",IF(ABS(K8-Kunci_Penyesuaian!$E$7)<0.01,"OK","SALAH")) | O8: =IF(J8="","",IF(ABS(L8-Kunci_Penyesuaian!$F$7)<0.01,"OK","SALAH")) | P8: =IF(COUNTA(J8:L8)=0,"Belum diisi",IF(COUNTIF(M8:O8,"OK")=3,"BENAR","PERIKSA")) -> Belum diisi
A10: 3 | B10: 46418 | C10: Basic – Asuransi terpakai | D10: Premi asuransi Rp18.000.000 untuk 12 bulan. Satu bulan telah terpakai. | E10: Rp18.000.000 ÷ 12 = Rp1.500.000 | F10: 1500000 | G10: Debit Beban Asuransi; kredit Asuransi Dibayar di Muka. | H10: 3 | I10: 46418 | M10: =IF(J10="","",IF(J10=Kunci_Penyesuaian!$D$8,"OK","SALAH")) | N10: =IF(J10="","",IF(ABS(K10-Kunci_Penyesuaian!$E$8)<0.01,"OK","SALAH")) | O10: =IF(J10="","",IF(ABS(L10-Kunci_Penyesuaian!$F$8)<0.01,"OK","SALAH")) | P10: =IF(COUNTA(J10:L10)=0,"Belum diisi",IF(COUNTIF(M10:O10,"OK")=3,"BENAR","PERIKSA")) -> Belum diisi
H11: 3 | I11: 46418 | M11: =IF(J11="","",IF(J11=Kunci_Penyesuaian!$D$9,"OK","SALAH")) | N11: =IF(J11="","",IF(ABS(K11-Kunci_Penyesuaian!$E$9)<0.01,"OK","SALAH")) | O11: =IF(J11="","",IF(ABS(L11-Kunci_Penyesuaian!$F$9)<0.01,"OK","SALAH")) | P11: =IF(COUNTA(J11:L11)=0,"Belum diisi",IF(COUNTIF(M11:O11,"OK")=3,"BENAR","PERIKSA")) -> Belum diisi
A13: 4 | B13: 46418 | C13: Basic – Iklan terpakai | D13: Dari iklan dibayar di muka, manfaat bulan Januari yang telah diterima adalah Rp1.000.000. | F13: 1000000 | G13: Debit Beban Iklan; kredit Iklan Dibayar di Muka. | H13: 4 | I13: 46418 | M13: =IF(J13="","",IF(J13=Kunci_Penyesuaian!$D$10,"OK","SALAH")) | N13: =IF(J13="","",IF(ABS(K13-Kunci_Penyesuaian!$E$10)<0.01,"OK","SALAH")) | O13: =IF(J13="","",IF(ABS(L13-Kunci_Penyesuaian!$F$10)<0.01,"OK","SALAH")) | P13: =IF(COUNTA(J13:L13)=0,"Belum diisi",IF(COUNTIF(M13:O13,"OK")=3,"BENAR","PERIKSA")) -> Belum diisi
H14: 4 | I14: 46418 | M14: =IF(J14="","",IF(J14=Kunci_Penyesuaian!$D$11,"OK","SALAH")) | N14: =IF(J14="","",IF(ABS(K14-Kunci_Penyesuaian!$E$11)<0.01,"OK","SALAH")) | O14: =IF(J14="","",IF(ABS(L14-Kunci_Penyesuaian!$F$11)<0.01,"OK","SALAH")) | P14: =IF(COUNTA(J14:L14)=0,"Belum diisi",IF(COUNTIF(M14:O14,"OK")=3,"BENAR","PERIKSA")) -> Belum diisi
A16: 5 | B16: 46418 | C16: Basic – Software terpakai | D16: Lisensi software Rp4.800.000 digunakan untuk 12 bulan. Akui satu bulan. | E16: 4.800.000 ÷ 12 = 400.000 | F16: 400000 | G16: Debit Beban Lisensi/Software; kredit Software Dibayar di Muka. | H16: 5 | I16: 46418 | M16: =IF(J16="","",IF(J16=Kunci_Penyesuaian!$D$12,"OK","SALAH")) | N16: =IF(J16="","",IF(ABS(K16-Kunci_Penyesuaian!$E$12)<0.01,"OK","SALAH")) | O16: =IF(J16="","",IF(ABS(L16-Kunci_Penyesuaian!$F$12)<0.01,"OK","SALAH")) | P16: =IF(COUNTA(J16:L16)=0,"Belum diisi",IF(COUNTIF(M16:O16,"OK")=3,"BENAR","PERIKSA")) -> Belum diisi
H17: 5 | I17: 46418 | M17: =IF(J17="","",IF(J17=Kunci_Penyesuaian!$D$13,"OK","SALAH")) | N17: =IF(J17="","",IF(ABS(K17-Kunci_Penyesuaian!$E$13)<0.01,"OK","SALAH")) | O17: =IF(J17="","",IF(ABS(L17-Kunci_Penyesuaian!$F$13)<0.01,"OK","SALAH")) | P17: =IF(COUNTA(J17:L17)=0,"Belum diisi",IF(COUNTIF(M17:O17,"OK")=3,"BENAR","PERIKSA")) -> Belum diisi
A19: 6 | B19: 46418 | C19: Basic – Penyusutan peralatan toko | D19: Saldo peralatan toko yang disusutkan Rp75.000.000. Umur manfaat 5 tahun, residu nol, garis lurus. | E19: 75.000.000 ÷ 5 ÷ 12 | F19: 1250000 | G19: Debit Beban Penyusutan Peralatan Toko; kredit Akumulasi Penyusutan Peralatan Toko. | H19: 6 | I19: 46418 | M19: =IF(J19="","",IF(J19=Kunci_Penyesuaian!$D$14,"OK","SALAH")) | N19: =IF(J19="","",IF(ABS(K19-Kunci_Penyesuaian!$E$14)<0.01,"OK","SALAH")) | O19: =IF(J19="","",IF(ABS(L19-Kunci_Penyesuaian!$F$14)<0.01,"OK","SALAH")) | P19: =IF(COUNTA(J19:L19)=0,"Belum diisi",IF(COUNTIF(M19:O19,"OK")=3,"BENAR","PERIKSA")) -> Belum diisi
H20: 6 | I20: 46418 | M20: =IF(J20="","",IF(J20=Kunci_Penyesuaian!$D$15,"OK","SALAH")) | N20: =IF(J20="","",IF(ABS(K20-Kunci_Penyesuaian!$E$15)<0.01,"OK","SALAH")) | O20: =IF(J20="","",IF(ABS(L20-Kunci_Penyesuaian!$F$15)<0.01,"OK","SALAH")) | P20: =IF(COUNTA(J20:L20)=0,"Belum diisi",IF(COUNTIF(M20:O20,"OK")=3,"BENAR","PERIKSA")) -> Belum diisi
A22: 7 | B22: 46418 | C22: Basic – Penyusutan peralatan kantor | D22: Peralatan kantor tersisa yang disusutkan Rp20.000.000. Umur manfaat 5 tahun, residu nol, garis lurus. | E22: 20.000.000 ÷ 5 ÷ 12 | F22: 333333.33 | G22: Debit Beban Penyusutan Peralatan Kantor; kredit Akumulasi Penyusutan Peralatan Kantor. | H22: 7 | I22: 46418 | M22: =IF(J22="","",IF(J22=Kunci_Penyesuaian!$D$16,"OK","SALAH")) | N22: =IF(J22="","",IF(ABS(K22-Kunci_Penyesuaian!$E$16)<0.01,"OK","SALAH")) | O22: =IF(J22="","",IF(ABS(L22-Kunci_Penyesuaian!$F$16)<0.01,"OK","SALAH")) | P22: =IF(COUNTA(J22:L22)=0,"Belum diisi",IF(COUNTIF(M22:O22,"OK")=3,"BENAR","PERIKSA")) -> Belum diisi
H23: 7 | I23: 46418 | M23: =IF(J23="","",IF(J23=Kunci_Penyesuaian!$D$17,"OK","SALAH")) | N23: =IF(J23="","",IF(ABS(K23-Kunci_Penyesuaian!$E$17)<0.01,"OK","SALAH")) | O23: =IF(J23="","",IF(ABS(L23-Kunci_Penyesuaian!$F$17)<0.01,"OK","SALAH")) | P23: =IF(COUNTA(J23:L23)=0,"Belum diisi",IF(COUNTIF(M23:O23,"OK")=3,"BENAR","PERIKSA")) -> Belum diisi
A25: 8 | B25: 46418 | C25: Basic – Penyusutan kendaraan | D25: Kendaraan operasional Rp250.000.000. Umur manfaat 5 tahun, residu nol, garis lurus. | E25: 250.000.000 ÷ 5 ÷ 12 | F25: 4166666.7 | G25: Debit Beban Penyusutan Kendaraan; kredit Akumulasi Penyusutan Kendaraan. | H25: 8 | I25: 46418 | M25: =IF(J25="","",IF(J25=Kunci_Penyesuaian!$D$18,"OK","SALAH")) | N25: =IF(J25="","",IF(ABS(K25-Kunci_Penyesuaian!$E$18)<0.01,"OK","SALAH")) | O25: =IF(J25="","",IF(ABS(L25-Kunci_Penyesuaian!$F$18)<0.01,"OK","SALAH")) | P25: =IF(COUNTA(J25:L25)=0,"Belum diisi",IF(COUNTIF(M25:O25,"OK")=3,"BENAR","PERIKSA")) -> Belum diisi
H26: 8 | I26: 46418 | M26: =IF(J26="","",IF(J26=Kunci_Penyesuaian!$D$19,"OK","SALAH")) | N26: =IF(J26="","",IF(ABS(K26-Kunci_Penyesuaian!$E$19)<0.01,"OK","SALAH")) | O26: =IF(J26="","",IF(ABS(L26-Kunci_Penyesuaian!$F$19)<0.01,"OK","SALAH")) | P26: =IF(COUNTA(J26:L26)=0,"Belum diisi",IF(COUNTIF(M26:O26,"OK")=3,"BENAR","PERIKSA")) -> Belum diisi
A28: 9 | B28: 46418 | C28: Basic – Gaji masih harus dibayar | D28: Gaji karyawan yang telah menjadi beban tetapi belum dibayar sebesar Rp5.000.000. | F28: 5000000 | G28: Debit Beban Gaji; kredit Utang Gaji. | H28: 9 | I28: 46418 | M28: =IF(J28="","",IF(J28=Kunci_Penyesuaian!$D$20,"OK","SALAH")) | N28: =IF(J28="","",IF(ABS(K28-Kunci_Penyesuaian!$E$20)<0.01,"OK","SALAH")) | O28: =IF(J28="","",IF(ABS(L28-Kunci_Penyesuaian!$F$20)<0.01,"OK","SALAH")) | P28: =IF(COUNTA(J28:L28)=0,"Belum diisi",IF(COUNTIF(M28:O28,"OK")=3,"BENAR","PERIKSA")) -> Belum diisi
H29: 9 | I29: 46418 | M29: =IF(J29="","",IF(J29=Kunci_Penyesuaian!$D$21,"OK","SALAH")) | N29: =IF(J29="","",IF(ABS(K29-Kunci_Penyesuaian!$E$21)<0.01,"OK","SALAH")) | O29: =IF(J29="","",IF(ABS(L29-Kunci_Penyesuaian!$F$21)<0.01,"OK","SALAH")) | P29: =IF(COUNTA(J29:L29)=0,"Belum diisi",IF(COUNTIF(M29:O29,"OK")=3,"BENAR","PERIKSA")) -> Belum diisi
A31: 10 | B31: 46418 | C31: Basic – Bonus masih harus dibayar | D31: Bonus karyawan yang telah diperoleh untuk Januari tetapi baru dibayar Februari sebesar Rp3.000.000. | F31: 3000000 | G31: Debit Beban Bonus; kredit Utang Bonus. | H31: 10 | I31: 46418 | M31: =IF(J31="","",IF(J31=Kunci_Penyesuaian!$D$22,"OK","SALAH")) | N31: =IF(J31="","",IF(ABS(K31-Kunci_Penyesuaian!$E$22)<0.01,"OK","SALAH")) | O31: =IF(J31="","",IF(ABS(L31-Kunci_Penyesuaian!$F$22)<0.01,"OK","SALAH")) | P31: =IF(COUNTA(J31:L31)=0,"Belum diisi",IF(COUNTIF(M31:O31,"OK")=3,"BENAR","PERIKSA")) -> Belum diisi
H32: 10 | I32: 46418 | M32: =IF(J32="","",IF(J32=Kunci_Penyesuaian!$D$23,"OK","SALAH")) | N32: =IF(J32="","",IF(ABS(K32-Kunci_Penyesuaian!$E$23)<0.01,"OK","SALAH")) | O32: =IF(J32="","",IF(ABS(L32-Kunci_Penyesuaian!$F$23)<0.01,"OK","SALAH")) | P32: =IF(COUNTA(J32:L32)=0,"Belum diisi",IF(COUNTIF(M32:O32,"OK")=3,"BENAR","PERIKSA")) -> Belum diisi
A34: 11 | B34: 46418 | C34: Basic – Bunga terutang | D34: Bunga pinjaman Januari yang belum dibayar sebesar Rp1.200.000. | F34: 1200000 | G34: Debit Beban Bunga; kredit Utang Bunga. | H34: 11 | I34: 46418 | M34: =IF(J34="","",IF(J34=Kunci_Penyesuaian!$D$24,"OK","SALAH")) | N34: =IF(J34="","",IF(ABS(K34-Kunci_Penyesuaian!$E$24)<0.01,"OK","SALAH")) | O34: =IF(J34="","",IF(ABS(L34-Kunci_Penyesuaian!$F$24)<0.01,"OK","SALAH")) | P34: =IF(COUNTA(J34:L34)=0,"Belum diisi",IF(COUNTIF(M34:O34,"OK")=3,"BENAR","PERIKSA")) -> Belum diisi
H35: 11 | I35: 46418 | M35: =IF(J35="","",IF(J35=Kunci_Penyesuaian!$D$25,"OK","SALAH")) | N35: =IF(J35="","",IF(ABS(K35-Kunci_Penyesuaian!$E$25)<0.01,"OK","SALAH")) | O35: =IF(J35="","",IF(ABS(L35-Kunci_Penyesuaian!$F$25)<0.01,"OK","SALAH")) | P35: =IF(COUNTA(J35:L35)=0,"Belum diisi",IF(COUNTIF(M35:O35,"OK")=3,"BENAR","PERIKSA")) -> Belum diisi
A37: 12 | B37: 46418 | C37: Basic – Utilitas terutang | D37: Listrik, air, dan telekomunikasi yang telah digunakan tetapi tagihan belum dibayar sebesar Rp1.800.000. | F37: 1800000 | G37: Debit Beban Utilitas; kredit Utang Utilitas. | H37: 12 | I37: 46418 | M37: =IF(J37="","",IF(J37=Kunci_Penyesuaian!$D$26,"OK","SALAH")) | N37: =IF(J37="","",IF(ABS(K37-Kunci_Penyesuaian!$E$26)<0.01,"OK","SALAH")) | O37: =IF(J37="","",IF(ABS(L37-Kunci_Penyesuaian!$F$26)<0.01,"OK","SALAH")) | P37: =IF(COUNTA(J37:L37)=0,"Belum diisi",IF(COUNTIF(M37:O37,"OK")=3,"BENAR","PERIKSA")) -> Belum diisi
H38: 12 | I38: 46418 | M38: =IF(J38="","",IF(J38=Kunci_Penyesuaian!$D$27,"OK","SALAH")) | N38: =IF(J38="","",IF(ABS(K38-Kunci_Penyesuaian!$E$27)<0.01,"OK","SALAH")) | O38: =IF(J38="","",IF(ABS(L38-Kunci_Penyesuaian!$F$27)<0.01,"OK","SALAH")) | P38: =IF(COUNTA(J38:L38)=0,"Belum diisi",IF(COUNTIF(M38:O38,"OK")=3,"BENAR","PERIKSA")) -> Belum diisi
A40: 13 | B40: 46418 | C40: Intermediate – Jasa profesional terutang + PPh23 | D40: Jasa profesional Januari Rp2.500.000 sudah diterima tetapi invoice belum dibayar. PPh23 latihan 2% dipotong saat pengakuan kewajiban. | E40: PPh23 = 2% × 2.500.000 = 50.000 | F40: 2500000 | G40: Debit Beban Jasa Profesional; kredit Utang PPh23 dan Utang Usaha. | H40: 13 | I40: 46418 | M40: =IF(J40="","",IF(J40=Kunci_Penyesuaian!$D$28,"OK","SALAH")) | N40: =IF(J40="","",IF(ABS(K40-Kunci_Penyesuaian!$E$28)<0.01,"OK","SALAH")) | O40: =IF(J40="","",IF(ABS(L40-Kunci_Penyesuaian!$F$28)<0.01,"OK","SALAH")) | P40: =IF(COUNTA(J40:L40)=0,"Belum diisi",IF(COUNTIF(M40:O40,"OK")=3,"BENAR","PERIKSA")) -> Belum diisi
H41: 13 | I41: 46418 | M41: =IF(J41="","",IF(J41=Kunci_Penyesuaian!$D$29,"OK","SALAH")) | N41: =IF(J41="","",IF(ABS(K41-Kunci_Penyesuaian!$E$29)<0.01,"OK","SALAH")) | O41: =IF(J41="","",IF(ABS(L41-Kunci_Penyesuaian!$F$29)<0.01,"OK","SALAH")) | P41: =IF(COUNTA(J41:L41)=0,"Belum diisi",IF(COUNTIF(M41:O41,"OK")=3,"BENAR","PERIKSA")) -> Belum diisi
H42: 13 | I42: 46418 | M42: =IF(J42="","",IF(J42=Kunci_Penyesuaian!$D$30,"OK","SALAH")) | N42: =IF(J42="","",IF(ABS(K42-Kunci_Penyesuaian!$E$30)<0.01,"OK","SALAH")) | O42: =IF(J42="","",IF(ABS(L42-Kunci_Penyesuaian!$F$30)<0.01,"OK","SALAH")) | P42: =IF(COUNTA(J42:L42)=0,"Belum diisi",IF(COUNTIF(M42:O42,"OK")=3,"BENAR","PERIKSA")) -> Belum diisi
A44: 14 | B44: 46418 | C44: Intermediate – BPJS pemberi kerja terutang | D44: Bagian BPJS pemberi kerja yang menjadi beban Januari tetapi belum dibayar sebesar Rp1.500.000. | F44: 1500000 | G44: Debit Beban BPJS; kredit Utang BPJS. | H44: 14 | I44: 46418 | M44: =IF(J44="","",IF(J44=Kunci_Penyesuaian!$D$31,"OK","SALAH")) | N44: =IF(J44="","",IF(ABS(K44-Kunci_Penyesuaian!$E$31)<0.01,"OK","SALAH")) | O44: =IF(J44="","",IF(ABS(L44-Kunci_Penyesuaian!$F$31)<0.01,"OK","SALAH")) | P44: =IF(COUNTA(J44:L44)=0,"Belum diisi",IF(COUNTIF(M44:O44,"OK")=3,"BENAR","PERIKSA")) -> Belum diisi
H45: 14 | I45: 46418 | M45: =IF(J45="","",IF(J45=Kunci_Penyesuaian!$D$32,"OK","SALAH")) | N45: =IF(J45="","",IF(ABS(K45-Kunci_Penyesuaian!$E$32)<0.01,"OK","SALAH")) | O45: =IF(J45="","",IF(ABS(L45-Kunci_Penyesuaian!$F$32)<0.01,"OK","SALAH")) | P45: =IF(COUNTA(J45:L45)=0,"Belum diisi",IF(COUNTIF(M45:O45,"OK")=3,"BENAR","PERIKSA")) -> Belum diisi
A47: 15 | B47: 46418 | C47: Intermediate – Cadangan piutang tak tertagih | D47: Berdasarkan aging schedule, penyisihan piutang yang seharusnya tersedia pada 31 Januari adalah Rp6.000.000. Saldo penyisihan sebelum penyesuaian Rp1.500.000. | E47: 6.000.000 - 1.500.000 | F47: 4500000 | G47: Tambahkan penyisihan sebesar selisih target dan saldo yang ada. | H47: 15 | I47: 46418 | M47: =IF(J47="","",IF(J47=Kunci_Penyesuaian!$D$33,"OK","SALAH")) | N47: =IF(J47="","",IF(ABS(K47-Kunci_Penyesuaian!$E$33)<0.01,"OK","SALAH")) | O47: =IF(J47="","",IF(ABS(L47-Kunci_Penyesuaian!$F$33)<0.01,"OK","SALAH")) | P47: =IF(COUNTA(J47:L47)=0,"Belum diisi",IF(COUNTIF(M47:O47,"OK")=3,"BENAR","PERIKSA")) -> Belum diisi
H48: 15 | I48: 46418 | M48: =IF(J48="","",IF(J48=Kunci_Penyesuaian!$D$34,"OK","SALAH")) | N48: =IF(J48="","",IF(ABS(K48-Kunci_Penyesuaian!$E$34)<0.01,"OK","SALAH")) | O48: =IF(J48="","",IF(ABS(L48-Kunci_Penyesuaian!$F$34)<0.01,"OK","SALAH")) | P48: =IF(COUNTA(J48:L48)=0,"Belum diisi",IF(COUNTIF(M48:O48,"OK")=3,"BENAR","PERIKSA")) -> Belum diisi
A50: 16 | B50: 46418 | C50: Intermediate – Penghapusan piutang yang disisihkan | D50: Piutang pelanggan tertentu Rp2.000.000 diputuskan tidak tertagih dan telah termasuk dalam saldo yang disisihkan. | F50: 2000000 | G50: Debit Penyisihan Piutang Tak Tertagih; kredit Piutang Usaha. | H50: 16 | I50: 46418 | M50: =IF(J50="","",IF(J50=Kunci_Penyesuaian!$D$35,"OK","SALAH")) | N50: =IF(J50="","",IF(ABS(K50-Kunci_Penyesuaian!$E$35)<0.01,"OK","SALAH")) | O50: =IF(J50="","",IF(ABS(L50-Kunci_Penyesuaian!$F$35)<0.01,"OK","SALAH")) | P50: =IF(COUNTA(J50:L50)=0,"Belum diisi",IF(COUNTIF(M50:O50,"OK")=3,"BENAR","PERIKSA")) -> Belum diisi
H51: 16 | I51: 46418 | M51: =IF(J51="","",IF(J51=Kunci_Penyesuaian!$D$36,"OK","SALAH")) | N51: =IF(J51="","",IF(ABS(K51-Kunci_Penyesuaian!$E$36)<0.01,"OK","SALAH")) | O51: =IF(J51="","",IF(ABS(L51-Kunci_Penyesuaian!$F$36)<0.01,"OK","SALAH")) | P51: =IF(COUNTA(J51:L51)=0,"Belum diisi",IF(COUNTIF(M51:O51,"OK")=3,"BENAR","PERIKSA")) -> Belum diisi
A53: 17 | B53: 46418 | C53: Intermediate – Selisih persediaan | D53: Stock opname menghasilkan kekurangan persediaan sebesar Rp2.000.000 yang belum dicatat. | F53: 2000000 | G53: Debit Beban Kerugian Persediaan; kredit Persediaan. | H53: 17 | I53: 46418 | M53: =IF(J53="","",IF(J53=Kunci_Penyesuaian!$D$37,"OK","SALAH")) | N53: =IF(J53="","",IF(ABS(K53-Kunci_Penyesuaian!$E$37)<0.01,"OK","SALAH")) | O53: =IF(J53="","",IF(ABS(L53-Kunci_Penyesuaian!$F$37)<0.01,"OK","SALAH")) | P53: =IF(COUNTA(J53:L53)=0,"Belum diisi",IF(COUNTIF(M53:O53,"OK")=3,"BENAR","PERIKSA")) -> Belum diisi
H54: 17 | I54: 46418 | M54: =IF(J54="","",IF(J54=Kunci_Penyesuaian!$D$38,"OK","SALAH")) | N54: =IF(J54="","",IF(ABS(K54-Kunci_Penyesuaian!$E$38)<0.01,"OK","SALAH")) | O54: =IF(J54="","",IF(ABS(L54-Kunci_Penyesuaian!$F$38)<0.01,"OK","SALAH")) | P54: =IF(COUNTA(J54:L54)=0,"Belum diisi",IF(COUNTIF(M54:O54,"OK")=3,"BENAR","PERIKSA")) -> Belum diisi
A56: 18 | B56: 46418 | C56: Intermediate – Penurunan nilai persediaan | D56: Nilai realisasi bersih beberapa barang lebih rendah dari nilai tercatat sebesar Rp1.500.000. | F56: 1500000 | G56: Debit Beban Kerugian Persediaan; kredit Persediaan. | H56: 18 | I56: 46418 | M56: =IF(J56="","",IF(J56=Kunci_Penyesuaian!$D$39,"OK","SALAH")) | N56: =IF(J56="","",IF(ABS(K56-Kunci_Penyesuaian!$E$39)<0.01,"OK","SALAH")) | O56: =IF(J56="","",IF(ABS(L56-Kunci_Penyesuaian!$F$39)<0.01,"OK","SALAH")) | P56: =IF(COUNTA(J56:L56)=0,"Belum diisi",IF(COUNTIF(M56:O56,"OK")=3,"BENAR","PERIKSA")) -> Belum diisi
H57: 18 | I57: 46418 | M57: =IF(J57="","",IF(J57=Kunci_Penyesuaian!$D$40,"OK","SALAH")) | N57: =IF(J57="","",IF(ABS(K57-Kunci_Penyesuaian!$E$40)<0.01,"OK","SALAH")) | O57: =IF(J57="","",IF(ABS(L57-Kunci_Penyesuaian!$F$40)<0.01,"OK","SALAH")) | P57: =IF(COUNTA(J57:L57)=0,"Belum diisi",IF(COUNTIF(M57:O57,"OK")=3,"BENAR","PERIKSA")) -> Belum diisi
A59: 19 | B59: 46418 | C59: Intermediate – Uang muka pelanggan menjadi pendapatan | D59: Dari uang muka pelanggan, barang senilai Rp4.000.000 sebelum PPN telah diserahkan dan PPN terkait Rp440.000 menjadi terutang. | E59: 4.000.000 + 440.000 | F59: 4440000 | G59: Debit Uang Muka Pelanggan; kredit Penjualan dan PPN Keluaran. | H59: 19 | I59: 46418 | M59: =IF(J59="","",IF(J59=Kunci_Penyesuaian!$D$41,"OK","SALAH")) | N59: =IF(J59="","",IF(ABS(K59-Kunci_Penyesuaian!$E$41)<0.01,"OK","SALAH")) | O59: =IF(J59="","",IF(ABS(L59-Kunci_Penyesuaian!$F$41)<0.01,"OK","SALAH")) | P59: =IF(COUNTA(J59:L59)=0,"Belum diisi",IF(COUNTIF(M59:O59,"OK")=3,"BENAR","PERIKSA")) -> Belum diisi
H60: 19 | I60: 46418 | M60: =IF(J60="","",IF(J60=Kunci_Penyesuaian!$D$42,"OK","SALAH")) | N60: =IF(J60="","",IF(ABS(K60-Kunci_Penyesuaian!$E$42)<0.01,"OK","SALAH")) | O60: =IF(J60="","",IF(ABS(L60-Kunci_Penyesuaian!$F$42)<0.01,"OK","SALAH")) | P60: =IF(COUNTA(J60:L60)=0,"Belum diisi",IF(COUNTIF(M60:O60,"OK")=3,"BENAR","PERIKSA")) -> Belum diisi
H61: 19 | I61: 46418 | M61: =IF(J61="","",IF(J61=Kunci_Penyesuaian!$D$43,"OK","SALAH")) | N61: =IF(J61="","",IF(ABS(K61-Kunci_Penyesuaian!$E$43)<0.01,"OK","SALAH")) | O61: =IF(J61="","",IF(ABS(L61-Kunci_Penyesuaian!$F$43)<0.01,"OK","SALAH")) | P61: =IF(COUNTA(J61:L61)=0,"Belum diisi",IF(COUNTIF(M61:O61,"OK")=3,"BENAR","PERIKSA")) -> Belum diisi
A63: 20 | B63: 46418 | C63: Intermediate – HPP atas penyerahan dari uang muka | D63: HPP barang yang telah diserahkan pada kasus penyesuaian sebelumnya adalah Rp2.400.000. | F63: 2400000 | G63: Debit HPP; kredit Persediaan. | H63: 20 | I63: 46418 | M63: =IF(J63="","",IF(J63=Kunci_Penyesuaian!$D$44,"OK","SALAH")) | N63: =IF(J63="","",IF(ABS(K63-Kunci_Penyesuaian!$E$44)<0.01,"OK","SALAH")) | O63: =IF(J63="","",IF(ABS(L63-Kunci_Penyesuaian!$F$44)<0.01,"OK","SALAH")) | P63: =IF(COUNTA(J63:L63)=0,"Belum diisi",IF(COUNTIF(M63:O63,"OK")=3,"BENAR","PERIKSA")) -> Belum diisi
H64: 20 | I64: 46418 | M64: =IF(J64="","",IF(J64=Kunci_Penyesuaian!$D$45,"OK","SALAH")) | N64: =IF(J64="","",IF(ABS(K64-Kunci_Penyesuaian!$E$45)<0.01,"OK","SALAH")) | O64: =IF(J64="","",IF(ABS(L64-Kunci_Penyesuaian!$F$45)<0.01,"OK","SALAH")) | P64: =IF(COUNTA(J64:L64)=0,"Belum diisi",IF(COUNTIF(M64:O64,"OK")=3,"BENAR","PERIKSA")) -> Belum diisi
A66: 21 | B66: 46418 | C66: Intermediate – Komisi masih harus dibayar | D66: Komisi penjualan yang menjadi beban Januari tetapi belum dibayar sebesar Rp2.000.000. | F66: 2000000 | G66: Debit Beban Komisi; kredit Utang Usaha. | H66: 21 | I66: 46418 | M66: =IF(J66="","",IF(J66=Kunci_Penyesuaian!$D$46,"OK","SALAH")) | N66: =IF(J66="","",IF(ABS(K66-Kunci_Penyesuaian!$E$46)<0.01,"OK","SALAH")) | O66: =IF(J66="","",IF(ABS(L66-Kunci_Penyesuaian!$F$46)<0.01,"OK","SALAH")) | P66: =IF(COUNTA(J66:L66)=0,"Belum diisi",IF(COUNTIF(M66:O66,"OK")=3,"BENAR","PERIKSA")) -> Belum diisi
H67: 21 | I67: 46418 | M67: =IF(J67="","",IF(J67=Kunci_Penyesuaian!$D$47,"OK","SALAH")) | N67: =IF(J67="","",IF(ABS(K67-Kunci_Penyesuaian!$E$47)<0.01,"OK","SALAH")) | O67: =IF(J67="","",IF(ABS(L67-Kunci_Penyesuaian!$F$47)<0.01,"OK","SALAH")) | P67: =IF(COUNTA(J67:L67)=0,"Belum diisi",IF(COUNTIF(M67:O67,"OK")=3,"BENAR","PERIKSA")) -> Belum diisi
A69: 22 | B69: 46418 | C69: Intermediate – Pajak daerah terutang | D69: Pajak daerah terkait kegiatan toko untuk Januari sebesar Rp800.000 belum dibayar. | F69: 800000 | G69: Debit Beban Pajak Daerah; kredit Utang Pajak Daerah. | H69: 22 | I69: 46418 | M69: =IF(J69="","",IF(J69=Kunci_Penyesuaian!$D$48,"OK","SALAH")) | N69: =IF(J69="","",IF(ABS(K69-Kunci_Penyesuaian!$E$48)<0.01,"OK","SALAH")) | O69: =IF(J69="","",IF(ABS(L69-Kunci_Penyesuaian!$F$48)<0.01,"OK","SALAH")) | P69: =IF(COUNTA(J69:L69)=0,"Belum diisi",IF(COUNTIF(M69:O69,"OK")=3,"BENAR","PERIKSA")) -> Belum diisi
H70: 22 | I70: 46418 | M70: =IF(J70="","",IF(J70=Kunci_Penyesuaian!$D$49,"OK","SALAH")) | N70: =IF(J70="","",IF(ABS(K70-Kunci_Penyesuaian!$E$49)<0.01,"OK","SALAH")) | O70: =IF(J70="","",IF(ABS(L70-Kunci_Penyesuaian!$F$49)<0.01,"OK","SALAH")) | P70: =IF(COUNTA(J70:L70)=0,"Belum diisi",IF(COUNTIF(M70:O70,"OK")=3,"BENAR","PERIKSA")) -> Belum diisi
A72: 23 | B72: 46418 | C72: Advanced – Bunga bank masih harus diterima | D72: Bunga deposito yang telah menjadi hak perusahaan tetapi baru akan diterima Februari sebesar Rp700.000. | F72: 700000 | G72: Debit Piutang Bunga; kredit Pendapatan Bunga. | H72: 23 | I72: 46418 | M72: =IF(J72="","",IF(J72=Kunci_Penyesuaian!$D$50,"OK","SALAH")) | N72: =IF(J72="","",IF(ABS(K72-Kunci_Penyesuaian!$E$50)<0.01,"OK","SALAH")) | O72: =IF(J72="","",IF(ABS(L72-Kunci_Penyesuaian!$F$50)<0.01,"OK","SALAH")) | P72: =IF(COUNTA(J72:L72)=0,"Belum diisi",IF(COUNTIF(M72:O72,"OK")=3,"BENAR","PERIKSA")) -> Belum diisi
H73: 23 | I73: 46418 | M73: =IF(J73="","",IF(J73=Kunci_Penyesuaian!$D$51,"OK","SALAH")) | N73: =IF(J73="","",IF(ABS(K73-Kunci_Penyesuaian!$E$51)<0.01,"OK","SALAH")) | O73: =IF(J73="","",IF(ABS(L73-Kunci_Penyesuaian!$F$51)<0.01,"OK","SALAH")) | P73: =IF(COUNTA(J73:L73)=0,"Belum diisi",IF(COUNTIF(M73:O73,"OK")=3,"BENAR","PERIKSA")) -> Belum diisi
A75: 24 | B75: 46418 | C75: Advanced – Beban administrasi bank terutang | D75: Biaya administrasi bank Rp150.000 telah dibebankan bank tetapi belum masuk rekening koran/buku perusahaan. | F75: 150000 | G75: Debit Beban Administrasi Bank; kredit Utang/akun bank. Dalam latihan, anggap menjadi kewajiban sementara. | H75: 24 | I75: 46418 | M75: =IF(J75="","",IF(J75=Kunci_Penyesuaian!$D$52,"OK","SALAH")) | N75: =IF(J75="","",IF(ABS(K75-Kunci_Penyesuaian!$E$52)<0.01,"OK","SALAH")) | O75: =IF(J75="","",IF(ABS(L75-Kunci_Penyesuaian!$F$52)<0.01,"OK","SALAH")) | P75: =IF(COUNTA(J75:L75)=0,"Belum diisi",IF(COUNTIF(M75:O75,"OK")=3,"BENAR","PERIKSA")) -> Belum diisi
H76: 24 | I76: 46418 | M76: =IF(J76="","",IF(J76=Kunci_Penyesuaian!$D$53,"OK","SALAH")) | N76: =IF(J76="","",IF(ABS(K76-Kunci_Penyesuaian!$E$53)<0.01,"OK","SALAH")) | O76: =IF(J76="","",IF(ABS(L76-Kunci_Penyesuaian!$F$53)<0.01,"OK","SALAH")) | P76: =IF(COUNTA(J76:L76)=0,"Belum diisi",IF(COUNTIF(M76:O76,"OK")=3,"BENAR","PERIKSA")) -> Belum diisi
A78: 25 | B78: 46418 | C78: Advanced – Perlengkapan dengan pemeriksaan ulang | D78: Saldo perlengkapan setelah penyesuaian sementara masih menyisakan Rp1.000.000 yang ternyata terpakai saat stock opname. | F78: 1000000 | G78: Debit Beban Perlengkapan; kredit Perlengkapan. | H78: 25 | I78: 46418 | M78: =IF(J78="","",IF(J78=Kunci_Penyesuaian!$D$54,"OK","SALAH")) | N78: =IF(J78="","",IF(ABS(K78-Kunci_Penyesuaian!$E$54)<0.01,"OK","SALAH")) | O78: =IF(J78="","",IF(ABS(L78-Kunci_Penyesuaian!$F$54)<0.01,"OK","SALAH")) | P78: =IF(COUNTA(J78:L78)=0,"Belum diisi",IF(COUNTIF(M78:O78,"OK")=3,"BENAR","PERIKSA")) -> Belum diisi
H79: 25 | I79: 46418 | M79: =IF(J79="","",IF(J79=Kunci_Penyesuaian!$D$55,"OK","SALAH")) | N79: =IF(J79="","",IF(ABS(K79-Kunci_Penyesuaian!$E$55)<0.01,"OK","SALAH")) | O79: =IF(J79="","",IF(ABS(L79-Kunci_Penyesuaian!$F$55)<0.01,"OK","SALAH")) | P79: =IF(COUNTA(J79:L79)=0,"Belum diisi",IF(COUNTIF(M79:O79,"OK")=3,"BENAR","PERIKSA")) -> Belum diisi
A81: 26 | B81: 46418 | C81: Advanced – Lisensi tahunan terpakai | D81: Lisensi usaha Rp12.000.000 dibayar 31 Januari. Untuk keperluan latihan, manfaat hari pertama tidak diamortisasi; bagian yang terpakai belum ada. | E81: 0 | F81: 0 | G81: Tidak ada jurnal penyesuaian; siswa harus memahami kapan aset mulai diamortisasi. | H81: 26 | I81: 46418 | M81: =IF(J81="","",IF(J81=Kunci_Penyesuaian!$D$56,"OK","SALAH")) | N81: =IF(J81="","",IF(ABS(K81-Kunci_Penyesuaian!$E$56)<0.01,"OK","SALAH")) | O81: =IF(J81="","",IF(ABS(L81-Kunci_Penyesuaian!$F$56)<0.01,"OK","SALAH")) | P81: =IF(COUNTA(J81:L81)=0,"Belum diisi",IF(COUNTIF(M81:O81,"OK")=3,"BENAR","PERIKSA")) -> Belum diisi
A83: 27 | B83: 46418 | C83: Advanced – Akru bonus manajemen | D83: Bonus manajemen Rp4.500.000 telah menjadi beban Januari dan dibayar setelah laporan diterbitkan. | F83: 4500000 | G83: Debit Beban Bonus; kredit Utang Bonus. | H83: 27 | I83: 46418 | M83: =IF(J83="","",IF(J83=Kunci_Penyesuaian!$D$57,"OK","SALAH")) | N83: =IF(J83="","",IF(ABS(K83-Kunci_Penyesuaian!$E$57)<0.01,"OK","SALAH")) | O83: =IF(J83="","",IF(ABS(L83-Kunci_Penyesuaian!$F$57)<0.01,"OK","SALAH")) | P83: =IF(COUNTA(J83:L83)=0,"Belum diisi",IF(COUNTIF(M83:O83,"OK")=3,"BENAR","PERIKSA")) -> Belum diisi
H84: 27 | I84: 46418 | M84: =IF(J84="","",IF(J84=Kunci_Penyesuaian!$D$58,"OK","SALAH")) | N84: =IF(J84="","",IF(ABS(K84-Kunci_Penyesuaian!$E$58)<0.01,"OK","SALAH")) | O84: =IF(J84="","",IF(ABS(L84-Kunci_Penyesuaian!$F$58)<0.01,"OK","SALAH")) | P84: =IF(COUNTA(J84:L84)=0,"Belum diisi",IF(COUNTIF(M84:O84,"OK")=3,"BENAR","PERIKSA")) -> Belum diisi
A86: 28 | B86: 46418 | C86: Advanced – Estimasi biaya audit | D86: Jasa audit Rp7.500.000 telah diterima sampai 31 Januari tetapi belum ditagih. | F86: 7500000 | G86: Debit Beban Jasa Profesional; kredit Utang Usaha. | H86: 28 | I86: 46418 | M86: =IF(J86="","",IF(J86=Kunci_Penyesuaian!$D$59,"OK","SALAH")) | N86: =IF(J86="","",IF(ABS(K86-Kunci_Penyesuaian!$E$59)<0.01,"OK","SALAH")) | O86: =IF(J86="","",IF(ABS(L86-Kunci_Penyesuaian!$F$59)<0.01,"OK","SALAH")) | P86: =IF(COUNTA(J86:L86)=0,"Belum diisi",IF(COUNTIF(M86:O86,"OK")=3,"BENAR","PERIKSA")) -> Belum diisi
H87: 28 | I87: 46418 | M87: =IF(J87="","",IF(J87=Kunci_Penyesuaian!$D$60,"OK","SALAH")) | N87: =IF(J87="","",IF(ABS(K87-Kunci_Penyesuaian!$E$60)<0.01,"OK","SALAH")) | O87: =IF(J87="","",IF(ABS(L87-Kunci_Penyesuaian!$F$60)<0.01,"OK","SALAH")) | P87: =IF(COUNTA(J87:L87)=0,"Belum diisi",IF(COUNTIF(M87:O87,"OK")=3,"BENAR","PERIKSA")) -> Belum diisi
A89: 29 | B89: 46418 | C89: Advanced – PPN keluaran dan masukan ditentukan untuk rekonsiliasi | D89: Hasil rekonsiliasi PPN menunjukkan PPN Keluaran yang masih harus dilaporkan Rp12.000.000 dan PPN Masukan yang dapat dikreditkan Rp8.500.000. Reklasifikasi neto untuk latihan diminta. | E89: Keluaran 12.000.000 - Masukan 8.500.000 = utang 3.500.000 | F89: 3500000 | G89: Debit PPN Keluaran; kredit PPN Masukan dan Utang PPN. | H89: 29 | I89: 46418 | M89: =IF(J89="","",IF(J89=Kunci_Penyesuaian!$D$61,"OK","SALAH")) | N89: =IF(J89="","",IF(ABS(K89-Kunci_Penyesuaian!$E$61)<0.01,"OK","SALAH")) | O89: =IF(J89="","",IF(ABS(L89-Kunci_Penyesuaian!$F$61)<0.01,"OK","SALAH")) | P89: =IF(COUNTA(J89:L89)=0,"Belum diisi",IF(COUNTIF(M89:O89,"OK")=3,"BENAR","PERIKSA")) -> Belum diisi
H90: 29 | I90: 46418 | M90: =IF(J90="","",IF(J90=Kunci_Penyesuaian!$D$62,"OK","SALAH")) | N90: =IF(J90="","",IF(ABS(K90-Kunci_Penyesuaian!$E$62)<0.01,"OK","SALAH")) | O90: =IF(J90="","",IF(ABS(L90-Kunci_Penyesuaian!$F$62)<0.01,"OK","SALAH")) | P90: =IF(COUNTA(J90:L90)=0,"Belum diisi",IF(COUNTIF(M90:O90,"OK")=3,"BENAR","PERIKSA")) -> Belum diisi
H91: 29 | I91: 46418 | M91: =IF(J91="","",IF(J91=Kunci_Penyesuaian!$D$63,"OK","SALAH")) | N91: =IF(J91="","",IF(ABS(K91-Kunci_Penyesuaian!$E$63)<0.01,"OK","SALAH")) | O91: =IF(J91="","",IF(ABS(L91-Kunci_Penyesuaian!$F$63)<0.01,"OK","SALAH")) | P91: =IF(COUNTA(J91:L91)=0,"Belum diisi",IF(COUNTIF(M91:O91,"OK")=3,"BENAR","PERIKSA")) -> Belum diisi
A93: 30 | B93: 46418 | C93: Paling Sulit – Provision pajak penghasilan | D93: Berdasarkan rekonsiliasi fiskal internal, beban pajak penghasilan periode Januari ditetapkan Rp8.000.000 untuk latihan. | E93: Nominal ditetapkan untuk latihan. | F93: 8000000 | G93: Debit Beban Pajak Penghasilan; kredit Utang Pajak Penghasilan. | H93: 30 | I93: 46418 | M93: =IF(J93="","",IF(J93=Kunci_Penyesuaian!$D$64,"OK","SALAH")) | N93: =IF(J93="","",IF(ABS(K93-Kunci_Penyesuaian!$E$64)<0.01,"OK","SALAH")) | O93: =IF(J93="","",IF(ABS(L93-Kunci_Penyesuaian!$F$64)<0.01,"OK","SALAH")) | P93: =IF(COUNTA(J93:L93)=0,"Belum diisi",IF(COUNTIF(M93:O93,"OK")=3,"BENAR","PERIKSA")) -> Belum diisi
H94: 30 | I94: 46418 | M94: =IF(J94="","",IF(J94=Kunci_Penyesuaian!$D$65,"OK","SALAH")) | N94: =IF(J94="","",IF(ABS(K94-Kunci_Penyesuaian!$E$65)<0.01,"OK","SALAH")) | O94: =IF(J94="","",IF(ABS(L94-Kunci_Penyesuaian!$F$65)<0.01,"OK","SALAH")) | P94: =IF(COUNTA(J94:L94)=0,"Belum diisi",IF(COUNTIF(M94:O94,"OK")=3,"BENAR","PERIKSA")) -> Belum diisi

Sheet Kunci_Penyesuaian
A1: KUNCI JURNAL PENYESUAIAN – 30 SOAL
A2: Kunci pembanding. Kasus tanpa jurnal dicatat sebagai TIDAK ADA JURNAL dengan nilai 0/0.
A3: No | B3: Tanggal | C3: Tingkat / Jenis | D3: Akun | E3: Debit (Rp) | F3: Kredit (Rp) | G3: Dasar / Formula | H3: Tingkat | I3: Catatan
A4: 1 | B4: 46418 | C4: Basic / Perlengkapan terpakai | D4: Beban Perlengkapan | E4: 1200000 | F4: 0 | H4: Basic | I4: Saldo terpakai = 5.000.000 - 3.800.000
A5: 1 | B5: 46418 | C5: Basic / Perlengkapan terpakai | D5: Perlengkapan | E5: 0 | F5: 1200000 | H5: Basic | I5: Saldo terpakai = 5.000.000 - 3.800.000
A6: 2 | B6: 46418 | C6: Basic / Sewa terpakai | D6: Beban Sewa | E6: 6000000 | F6: 0 | H6: Basic | I6: Diberikan langsung
A7: 2 | B7: 46418 | C7: Basic / Sewa terpakai | D7: Sewa Dibayar di Muka | E7: 0 | F7: 6000000 | H7: Basic | I7: Diberikan langsung
A8: 3 | B8: 46418 | C8: Basic / Asuransi terpakai | D8: Beban Asuransi | E8: 1500000 | F8: 0 | G8: Rp18.000.000 ÷ 12 = Rp1.500.000 | H8: Basic
A9: 3 | B9: 46418 | C9: Basic / Asuransi terpakai | D9: Asuransi Dibayar di Muka | E9: 0 | F9: 1500000 | G9: Rp18.000.000 ÷ 12 = Rp1.500.000 | H9: Basic
A10: 4 | B10: 46418 | C10: Basic / Iklan terpakai | D10: Beban Iklan | E10: 1000000 | F10: 0 | H10: Basic
A11: 4 | B11: 46418 | C11: Basic / Iklan terpakai | D11: Iklan Dibayar di Muka | E11: 0 | F11: 1000000 | H11: Basic
A12: 5 | B12: 46418 | C12: Basic / Software terpakai | D12: Beban Lisensi/Software | E12: 400000 | F12: 0 | G12: 4.800.000 ÷ 12 = 400.000 | H12: Basic
A13: 5 | B13: 46418 | C13: Basic / Software terpakai | D13: Software Dibayar di Muka | E13: 0 | F13: 400000 | G13: 4.800.000 ÷ 12 = 400.000 | H13: Basic
A14: 6 | B14: 46418 | C14: Basic / Penyusutan peralatan toko | D14: Beban Penyusutan Peralatan Toko | E14: 1250000 | F14: 0 | G14: 75.000.000 ÷ 5 ÷ 12 | H14: Basic
A15: 6 | B15: 46418 | C15: Basic / Penyusutan peralatan toko | D15: Akumulasi Penyusutan Peralatan Toko | E15: 0 | F15: 1250000 | G15: 75.000.000 ÷ 5 ÷ 12 | H15: Basic
A16: 7 | B16: 46418 | C16: Basic / Penyusutan peralatan kantor | D16: Beban Penyusutan Peralatan Kantor | E16: 333333.33 | F16: 0 | G16: 20.000.000 ÷ 5 ÷ 12 | H16: Basic
A17: 7 | B17: 46418 | C17: Basic / Penyusutan peralatan kantor | D17: Akumulasi Penyusutan Peralatan Kantor | E17: 0 | F17: 333333.33 | G17: 20.000.000 ÷ 5 ÷ 12 | H17: Basic
A18: 8 | B18: 46418 | C18: Basic / Penyusutan kendaraan | D18: Beban Penyusutan Kendaraan | E18: 4166666.7 | F18: 0 | G18: 250.000.000 ÷ 5 ÷ 12 | H18: Basic
A19: 8 | B19: 46418 | C19: Basic / Penyusutan kendaraan | D19: Akumulasi Penyusutan Kendaraan | E19: 0 | F19: 4166666.7 | G19: 250.000.000 ÷ 5 ÷ 12 | H19: Basic
A20: 9 | B20: 46418 | C20: Basic / Gaji masih harus dibayar | D20: Beban Gaji | E20: 5000000 | F20: 0 | H20: Basic
A21: 9 | B21: 46418 | C21: Basic / Gaji masih harus dibayar | D21: Utang Gaji | E21: 0 | F21: 5000000 | H21: Basic
A22: 10 | B22: 46418 | C22: Basic / Bonus masih harus dibayar | D22: Beban Bonus | E22: 3000000 | F22: 0 | H22: Basic
A23: 10 | B23: 46418 | C23: Basic / Bonus masih harus dibayar | D23: Utang Bonus | E23: 0 | F23: 3000000 | H23: Basic
A24: 11 | B24: 46418 | C24: Basic / Bunga terutang | D24: Beban Bunga | E24: 1200000 | F24: 0 | H24: Basic
A25: 11 | B25: 46418 | C25: Basic / Bunga terutang | D25: Utang Bunga | E25: 0 | F25: 1200000 | H25: Basic
A26: 12 | B26: 46418 | C26: Basic / Utilitas terutang | D26: Beban Utilitas | E26: 1800000 | F26: 0 | H26: Basic
A27: 12 | B27: 46418 | C27: Basic / Utilitas terutang | D27: Utang Utilitas | E27: 0 | F27: 1800000 | H27: Basic
A28: 13 | B28: 46418 | C28: Intermediate / Jasa profesional terutang + PPh23 | D28: Beban Jasa Profesional | E28: 2500000 | F28: 0 | G28: PPh23 = 2% × 2.500.000 = 50.000 | H28: Intermediate
A29: 13 | B29: 46418 | C29: Intermediate / Jasa profesional terutang + PPh23 | D29: Utang PPh 23 | E29: 0 | F29: 50000 | G29: PPh23 = 2% × 2.500.000 = 50.000 | H29: Intermediate
A30: 13 | B30: 46418 | C30: Intermediate / Jasa profesional terutang + PPh23 | D30: Utang Beban / Akrual | E30: 0 | F30: 2450000 | G30: PPh23 = 2% × 2.500.000 = 50.000 | H30: Intermediate
A31: 14 | B31: 46418 | C31: Intermediate / BPJS pemberi kerja terutang | D31: Beban BPJS | E31: 1500000 | F31: 0 | H31: Intermediate
A32: 14 | B32: 46418 | C32: Intermediate / BPJS pemberi kerja terutang | D32: Utang BPJS | E32: 0 | F32: 1500000 | H32: Intermediate
A33: 15 | B33: 46418 | C33: Intermediate / Cadangan piutang tak tertagih | D33: Beban Kerugian Piutang | E33: 4500000 | F33: 0 | G33: 6.000.000 - 1.500.000 | H33: Intermediate
A34: 15 | B34: 46418 | C34: Intermediate / Cadangan piutang tak tertagih | D34: Penyisihan Piutang Tak Tertagih | E34: 0 | F34: 4500000 | G34: 6.000.000 - 1.500.000 | H34: Intermediate
A35: 16 | B35: 46418 | C35: Intermediate / Penghapusan piutang yang disisihkan | D35: Penyisihan Piutang Tak Tertagih | E35: 2000000 | F35: 0 | H35: Intermediate
A36: 16 | B36: 46418 | C36: Intermediate / Penghapusan piutang yang disisihkan | D36: Piutang Usaha | E36: 0 | F36: 2000000 | H36: Intermediate
A37: 17 | B37: 46418 | C37: Intermediate / Selisih persediaan | D37: Beban Kerugian Persediaan | E37: 2000000 | F37: 0 | H37: Intermediate
A38: 17 | B38: 46418 | C38: Intermediate / Selisih persediaan | D38: Persediaan Barang Dagang | E38: 0 | F38: 2000000 | H38: Intermediate
A39: 18 | B39: 46418 | C39: Intermediate / Penurunan nilai persediaan | D39: Beban Kerugian Persediaan | E39: 1500000 | F39: 0 | H39: Intermediate
A40: 18 | B40: 46418 | C40: Intermediate / Penurunan nilai persediaan | D40: Persediaan Barang Dagang | E40: 0 | F40: 1500000 | H40: Intermediate
A41: 19 | B41: 46418 | C41: Intermediate / Uang muka pelanggan menjadi pendapatan | D41: Uang Muka Pelanggan | E41: 4440000 | F41: 0 | G41: 4.000.000 + 440.000 | H41: Intermediate
A42: 19 | B42: 46418 | C42: Intermediate / Uang muka pelanggan menjadi pendapatan | D42: Penjualan | E42: 0 | F42: 4000000 | G42: 4.000.000 + 440.000 | H42: Intermediate
A43: 19 | B43: 46418 | C43: Intermediate / Uang muka pelanggan menjadi pendapatan | D43: PPN Keluaran | E43: 0 | F43: 440000 | G43: 4.000.000 + 440.000 | H43: Intermediate
A44: 20 | B44: 46418 | C44: Intermediate / HPP atas penyerahan dari uang muka | D44: HPP | E44: 2400000 | F44: 0 | H44: Intermediate
A45: 20 | B45: 46418 | C45: Intermediate / HPP atas penyerahan dari uang muka | D45: Persediaan Barang Dagang | E45: 0 | F45: 2400000 | H45: Intermediate
A46: 21 | B46: 46418 | C46: Intermediate / Komisi masih harus dibayar | D46: Beban Komisi | E46: 2000000 | F46: 0 | H46: Intermediate
A47: 21 | B47: 46418 | C47: Intermediate / Komisi masih harus dibayar | D47: Utang Beban / Akrual | E47: 0 | F47: 2000000 | H47: Intermediate
A48: 22 | B48: 46418 | C48: Intermediate / Pajak daerah terutang | D48: Beban Pajak Daerah | E48: 800000 | F48: 0 | H48: Intermediate
A49: 22 | B49: 46418 | C49: Intermediate / Pajak daerah terutang | D49: Utang Pajak Daerah | E49: 0 | F49: 800000 | H49: Intermediate
A50: 23 | B50: 46418 | C50: Advanced / Bunga bank masih harus diterima | D50: Piutang Bunga | E50: 700000 | F50: 0 | H50: Advanced
A51: 23 | B51: 46418 | C51: Advanced / Bunga bank masih harus diterima | D51: Pendapatan Bunga | E51: 0 | F51: 700000 | H51: Advanced
A52: 24 | B52: 46418 | C52: Advanced / Beban administrasi bank terutang | D52: Beban Administrasi Bank | E52: 150000 | F52: 0 | H52: Advanced | I52: Kasus edukatif untuk membedakan bank reconciliation vs accrual.
A53: 24 | B53: 46418 | C53: Advanced / Beban administrasi bank terutang | D53: Utang Beban / Akrual | E53: 0 | F53: 150000 | H53: Advanced | I53: Kasus edukatif untuk membedakan bank reconciliation vs accrual.
A54: 25 | B54: 46418 | C54: Advanced / Perlengkapan dengan pemeriksaan ulang | D54: Beban Perlengkapan | E54: 1000000 | F54: 0 | H54: Advanced
A55: 25 | B55: 46418 | C55: Advanced / Perlengkapan dengan pemeriksaan ulang | D55: Perlengkapan | E55: 0 | F55: 1000000 | H55: Advanced
A56: 26 | B56: 46418 | C56: Advanced / Lisensi tahunan terpakai | D56: (Tidak ada jurnal) | E56: 0 | F56: 0 | G56: 0 | H56: Advanced
A57: 27 | B57: 46418 | C57: Advanced / Akru bonus manajemen | D57: Beban Bonus | E57: 4500000 | F57: 0 | H57: Advanced
A58: 27 | B58: 46418 | C58: Advanced / Akru bonus manajemen | D58: Utang Bonus | E58: 0 | F58: 4500000 | H58: Advanced
A59: 28 | B59: 46418 | C59: Advanced / Estimasi biaya audit | D59: Beban Jasa Profesional | E59: 7500000 | F59: 0 | H59: Advanced
A60: 28 | B60: 46418 | C60: Advanced / Estimasi biaya audit | D60: Utang Beban / Akrual | E60: 0 | F60: 7500000 | H60: Advanced
A61: 29 | B61: 46418 | C61: Advanced / PPN keluaran dan masukan ditentukan untuk rekonsiliasi | D61: PPN Keluaran | E61: 74954000 | F61: 0 | G61: PPN Keluaran sebelum clearing Rp74.954.000; PPN Masukan Rp101.112.000 → clear output against input; remaining PPN Masukan Rp26.158.000. | H61: Advanced | I61: Setelah clearing, PPN Keluaran nol dan PPN Masukan bersih Rp26.158.000.
A62: 29 | B62: 46418 | C62: Advanced / PPN keluaran dan masukan ditentukan untuk rekonsiliasi | D62: PPN Masukan | E62: 0 | F62: 74954000 | G62: PPN Keluaran sebelum clearing Rp74.954.000; PPN Masukan Rp101.112.000 → clear output against input; remaining PPN Masukan Rp26.158.000. | H62: Advanced | I62: Setelah clearing, PPN Keluaran nol dan PPN Masukan bersih Rp26.158.000.
A63: 30 | B63: 46418 | C63: Paling Sulit / Provision pajak penghasilan | D63: Beban Pajak Penghasilan | E63: 8000000 | F63: 0 | G63: Nominal ditetapkan untuk latihan. | H63: Paling Sulit
A64: 30 | B64: 46418 | C64: Paling Sulit / Provision pajak penghasilan | D64: Utang Pajak Penghasilan | E64: 0 | F64: 8000000 | G64: Nominal ditetapkan untuk latihan. | H64: Paling Sulit

Sheet NS_Setelah_Penyesuaian
A1: NERACA SALDO – SETELAH PENYESUAIAN
A2: Sumber: Saldo awal + 80 Jurnal Umum + 30 Penyesuaian.
A3: Kode Akun | B3: Nama Akun | C3: Kategori | D3: Saldo Normal | E3: Debit (Rp) | F3: Kredit (Rp)
A4: 1-001 | B4: Bank | C4: Aset | D4: Debit | E4: =Buku_Besar!E4+Buku_Besar!G4+Buku_Besar!I4 -> 2568414000 | F4: =Buku_Besar!F4+Buku_Besar!H4+Buku_Besar!J4 -> 1164987000
A5: 1-002 | B5: Kas Kecil | C5: Aset | D5: Debit | E5: =Buku_Besar!E5+Buku_Besar!G5+Buku_Besar!I5 -> 40150000 | F5: =Buku_Besar!F5+Buku_Besar!H5+Buku_Besar!J5 -> 2300000
A6: 1-003 | B6: Piutang Usaha | C6: Aset | D6: Debit | E6: =Buku_Besar!E6+Buku_Besar!G6+Buku_Besar!I6 -> 543630000 | F6: =Buku_Besar!F6+Buku_Besar!H6+Buku_Besar!J6 -> 427490000
A7: 1-004 | B7: Piutang Karyawan | C7: Aset | D7: Debit | E7: =Buku_Besar!E7+Buku_Besar!G7+Buku_Besar!I7 -> 5000000 | F7: =Buku_Besar!F7+Buku_Besar!H7+Buku_Besar!J7 -> 2000000
A8: 1-005 | B8: Piutang Bunga | C8: Aset | D8: Debit | E8: =Buku_Besar!E8+Buku_Besar!G8+Buku_Besar!I8 -> 700000 | F8: =Buku_Besar!F8+Buku_Besar!H8+Buku_Besar!J8 -> 0
A9: 1-006 | B9: Piutang Pendapatan | C9: Aset | D9: Debit | E9: =Buku_Besar!E9+Buku_Besar!G9+Buku_Besar!I9 -> 0 | F9: =Buku_Besar!F9+Buku_Besar!H9+Buku_Besar!J9 -> 0
A10: 1-007 | B10: Persediaan Barang Dagang | C10: Aset | D10: Debit | E10: =Buku_Besar!E10+Buku_Besar!G10+Buku_Besar!I10 -> 694000000 | F10: =Buku_Besar!F10+Buku_Besar!H10+Buku_Besar!J10 -> 442200000
A11: 1-008 | B11: PPN Masukan | C11: Aset | D11: Debit | E11: =Buku_Besar!E11+Buku_Besar!G11+Buku_Besar!I11 -> 103125000 | F11: =Buku_Besar!F11+Buku_Besar!H11+Buku_Besar!J11 -> 76967000
A12: 1-009 | B12: PPh 22 Dibayar di Muka | C12: Aset | D12: Debit | E12: =Buku_Besar!E12+Buku_Besar!G12+Buku_Besar!I12 -> 2625000 | F12: =Buku_Besar!F12+Buku_Besar!H12+Buku_Besar!J12 -> 0
A13: 1-010 | B13: PPh 23 Dibayar di Muka | C13: Aset | D13: Debit | E13: =Buku_Besar!E13+Buku_Besar!G13+Buku_Besar!I13 -> 0 | F13: =Buku_Besar!F13+Buku_Besar!H13+Buku_Besar!J13 -> 0
A14: 1-011 | B14: PPh Final Dibayar di Muka | C14: Aset | D14: Debit | E14: =Buku_Besar!E14+Buku_Besar!G14+Buku_Besar!I14 -> 0 | F14: =Buku_Besar!F14+Buku_Besar!H14+Buku_Besar!J14 -> 0
A15: 1-012 | B15: Sewa Dibayar di Muka | C15: Aset | D15: Debit | E15: =Buku_Besar!E15+Buku_Besar!G15+Buku_Besar!I15 -> 24000000 | F15: =Buku_Besar!F15+Buku_Besar!H15+Buku_Besar!J15 -> 6000000
... A91: 2-021 | B91: PPN Keluaran | C91: Liabilitas | D91: Kredit | E91: =Buku_Besar!E91+Buku_Besar!G91+Buku_Besar!I91 -> 78210000 | F91: =Buku_Besar!F91+Buku_Besar!H91+Buku_Besar!J91 -> 78210000
A92: TOTAL | E92: =SUM(E4:E91) -> 5899864000 | F92: =SUM(F4:F91) -> 5899864000

Sheet Jurnal_Penutup
A1: JURNAL PENUTUP – PT SINAR NIAGA INDONESIA
A2: Column1 | B2: Column2 | C2: Column3 | D2: Column4 | E2: Column5 | F2: Column6 | G2: Column7
A3: Tanggal | B3: No | C3: Jenis | D3: Akun | E3: Debit (Rp) | F3: Kredit (Rp) | G3: Keterangan
A5: 46418 | B5: 1 | C5: Penutup | D5: Penjualan | E5: =Buku_Besar!$L$53 -> 699000000 | F5: 0 | G5: Menutup pendapatan Penjualan
A6: 46418 | B6: 2 | C6: Penutup | D6: Ikhtisar Laba Rugi | E6: 0 | F6: =Buku_Besar!$L$53 -> 699000000 | G6: Mengkredit Ikhtisar – Penjualan
A7: 46418 | B7: 3 | C7: Penutup | D7: Ikhtisar Laba Rugi | E7: =Buku_Besar!$K$54 -> 25000000 | F7: 0 | G7: Menutup Retur Penjualan
A8: 46418 | B8: 4 | C8: Penutup | D8: Retur Penjualan | E8: 0 | F8: =Buku_Besar!$K$54 -> 25000000 | G8: Menutup Retur Penjualan
A9: 46418 | B9: 5 | C9: Penutup | D9: Ikhtisar Laba Rugi | E9: =Buku_Besar!$K$55 -> 4600000 | F9: 0 | G9: Menutup Potongan Penjualan
A10: 46418 | B10: 6 | C10: Penutup | D10: Potongan Penjualan | E10: 0 | F10: =Buku_Besar!$K$55 -> 4600000 | G10: Menutup Potongan Penjualan
A11: 46418 | B11: 7 | C11: Penutup | D11: Pendapatan Jasa | E11: =Buku_Besar!$L$56 -> 0 | F11: 0 | G11: Menutup pendapatan Pendapatan Jasa
A12: 46418 | B12: 8 | C12: Penutup | D12: Ikhtisar Laba Rugi | E12: 0 | F12: =Buku_Besar!$L$56 -> 0 | G12: Mengkredit Ikhtisar – Pendapatan Jasa
A13: 46418 | B13: 9 | C13: Penutup | D13: Pendapatan Bunga | E13: =Buku_Besar!$L$57 -> 2200000 | F13: 0 | G13: Menutup pendapatan Pendapatan Bunga
A14: 46418 | B14: 10 | C14: Penutup | D14: Ikhtisar Laba Rugi | E14: 0 | F14: =Buku_Besar!$L$57 -> 2200000 | G14: Mengkredit Ikhtisar – Pendapatan Bunga
A15: 46418 | B15: 11 | C15: Penutup | D15: Keuntungan Penjualan Aset | E15: =Buku_Besar!$L$58 -> 2000000 | F15: 0 | G15: Menutup pendapatan Keuntungan Penjualan Aset
A16: 46418 | B16: 12 | C16: Penutup | D16: Ikhtisar Laba Rugi | E16: 0 | F16: =Buku_Besar!$L$58 -> 2000000 | G16: Mengkredit Ikhtisar – Keuntungan Penjualan Aset
A17: 46418 | B17: 13 | C17: Penutup | D17: Pendapatan Lain-lain | E17: =Buku_Besar!$L$59 -> 150000 | F17: 0 | G17: Menutup pendapatan Pendapatan Lain-lain
A18: 46418 | B18: 14 | C18: Penutup | D18: Ikhtisar Laba Rugi | E18: 0 | F18: =Buku_Besar!$L$59 -> 150000 | G18: Mengkredit Ikhtisar – Pendapatan Lain-lain
A19: 46418 | B19: 15 | C19: Penutup | D19: Ikhtisar Laba Rugi | E19: =Buku_Besar!$K$60 -> 391400000 | F19: 0 | G19: Menutup beban HPP
A20: 46418 | B20: 16 | C20: Penutup | D20: HPP | E20: 0 | F20: =Buku_Besar!$K$60 -> 391400000 | G20: Menutup HPP
A21: 46418 | B21: 17 | C21: Penutup | D21: Ikhtisar Laba Rugi | E21: =Buku_Besar!$K$61 -> 30000000 | F21: 0 | G21: Menutup beban Beban Gaji
A22: 46418 | B22: 18 | C22: Penutup | D22: Beban Gaji | E22: 0 | F22: =Buku_Besar!$K$61 -> 30000000 | G22: Menutup Beban Gaji
A23: 46418 | B23: 19 | C23: Penutup | D23: Ikhtisar Laba Rugi | E23: =Buku_Besar!$K$62 -> 3500000 | F23: 0 | G23: Menutup beban Beban BPJS
A24: 46418 | B24: 20 | C24: Penutup | D24: Beban BPJS | E24: 0 | F24: =Buku_Besar!$K$62 -> 3500000 | G24: Menutup Beban BPJS
A25: 46418 | B25: 21 | C25: Penutup | D25: Ikhtisar Laba Rugi | E25: =Buku_Besar!$K$63 -> 26000000 | F25: 0 | G25: Menutup beban Beban Sewa
A26: 46418 | B26: 22 | C26: Penutup | D26: Beban Sewa | E26: 0 | F26: =Buku_Besar!$K$63 -> 26000000 | G26: Menutup Beban Sewa
A27: 46418 | B27: 23 | C27: Penutup | D27: Ikhtisar Laba Rugi | E27: =Buku_Besar!$K$64 -> 1500000 | F27: 0 | G27: Menutup beban Beban Asuransi
A28: 46418 | B28: 24 | C28: Penutup | D28: Beban Asuransi | E28: 0 | F28: =Buku_Besar!$K$64 -> 1500000 | G28: Menutup Beban Asuransi
A29: 46418 | B29: 25 | C29: Penutup | D29: Ikhtisar Laba Rugi | E29: =Buku_Besar!$K$65 -> 2200000 | F29: 0 | G29: Menutup beban Beban Perlengkapan
A30: 46418 | B30: 26 | C30: Penutup | D30: Beban Perlengkapan | E30: 0 | F30: =Buku_Besar!$K$65 -> 2200000 | G30: Menutup Beban Perlengkapan
A31: 46418 | B31: 27 | C31: Penutup | D31: Ikhtisar Laba Rugi | E31: =Buku_Besar!$K$66 -> 1000000 | F31: 0 | G31: Menutup beban Beban Iklan
A32: 46418 | B32: 28 | C32: Penutup | D32: Beban Iklan | E32: 0 | F32: =Buku_Besar!$K$66 -> 1000000 | G32: Menutup Beban Iklan
A33: 46418 | B33: 29 | C33: Penutup | D33: Ikhtisar Laba Rugi | E33: =Buku_Besar!$K$67 -> 400000 | F33: 0 | G33: Menutup beban Beban Lisensi/Software
A34: 46418 | B34: 30 | C34: Penutup | D34: Beban Lisensi/Software | E34: 0 | F34: =Buku_Besar!$K$67 -> 400000 | G34: Menutup Beban Lisensi/Software
A35: 46418 | B35: 31 | C35: Penutup | D35: Ikhtisar Laba Rugi | E35: =Buku_Besar!$K$68 -> 1250000 | F35: 0 | G35: Menutup beban Beban Penyusutan Peralatan Toko
A36: 46418 | B36: 32 | C36: Penutup | D36: Beban Penyusutan Peralatan Toko | E36: 0 | F36: =Buku_Besar!$K$68 -> 1250000 | G36: Menutup Beban Penyusutan Peralatan Toko
A37: 46418 | B37: 33 | C37: Penutup | D37: Ikhtisar Laba Rugi | E37: =Buku_Besar!$K$69 -> 333333.33 | F37: 0 | G37: Menutup beban Beban Penyusutan Peralatan Kantor
A38: 46418 | B38: 34 | C38: Penutup | D38: Beban Penyusutan Peralatan Kantor | E38: 0 | F38: =Buku_Besar!$K$69 -> 333333.33 | G38: Menutup Beban Penyusutan Peralatan Kantor
A39: 46418 | B39: 35 | C39: Penutup | D39: Ikhtisar Laba Rugi | E39: =Buku_Besar!$K$70 -> 4166666.7 | F39: 0 | G39: Menutup beban Beban Penyusutan Kendaraan
A40: 46418 | B40: 36 | C40: Penutup | D40: Beban Penyusutan Kendaraan | E40: 0 | F40: =Buku_Besar!$K$70 -> 4166666.7 | G40: Menutup Beban Penyusutan Kendaraan
A41: 46418 | B41: 37 | C41: Penutup | D41: Ikhtisar Laba Rugi | E41: =Buku_Besar!$K$71 -> 7400000 | F41: 0 | G41: Menutup beban Beban Utilitas
A42: 46418 | B42: 38 | C42: Penutup | D42: Beban Utilitas | E42: 0 | F42: =Buku_Besar!$K$71 -> 7400000 | G42: Menutup Beban Utilitas
A43: 46418 | B43: 39 | C43: Penutup | D43: Ikhtisar Laba Rugi | E43: =Buku_Besar!$K$72 -> 3500000 | F43: 0 | G43: Menutup beban Beban Pengiriman Penjualan
A44: 46418 | B44: 40 | C44: Penutup | D44: Beban Pengiriman Penjualan | E44: 0 | F44: =Buku_Besar!$K$72 -> 3500000 | G44: Menutup Beban Pengiriman Penjualan
A45: 46418 | B45: 41 | C45: Penutup | D45: Ikhtisar Laba Rugi | E45: =Buku_Besar!$K$73 -> 18000000 | F45: 0 | G45: Menutup beban Beban Jasa Profesional
A46: 46418 | B46: 42 | C46: Penutup | D46: Beban Jasa Profesional | E46: 0 | F46: =Buku_Besar!$K$73 -> 18000000 | G46: Menutup Beban Jasa Profesional
A47: 46418 | B47: 43 | C47: Penutup | D47: Ikhtisar Laba Rugi | E47: =Buku_Besar!$K$74 -> 3000000 | F47: 0 | G47: Menutup beban Beban Pemeliharaan
A48: 46418 | B48: 44 | C48: Penutup | D48: Beban Pemeliharaan | E48: 0 | F48: =Buku_Besar!$K$74 -> 3000000 | G48: Menutup Beban Pemeliharaan
A49: 46418 | B49: 45 | C49: Penutup | D49: Ikhtisar Laba Rugi | E49: =Buku_Besar!$K$75 -> 0 | F49: 0 | G49: Menutup beban Beban ATK
A50: 46418 | B50: 46 | C50: Penutup | D50: Beban ATK | E50: 0 | F50: =Buku_Besar!$K$75 -> 0 | G50: Menutup Beban ATK
A51: 46418 | B51: 47 | C51: Penutup | D51: Ikhtisar Laba Rugi | E51: =Buku_Besar!$K$76 -> 4200000 | F51: 0 | G51: Menutup beban Beban Bunga
A52: 46418 | B52: 48 | C52: Penutup | D52: Beban Bunga | E52: 0 | F52: =Buku_Besar!$K$76 -> 4200000 | G52: Menutup Beban Bunga
A53: 46418 | B53: 49 | C53: Penutup | D53: Ikhtisar Laba Rugi | E53: =Buku_Besar!$K$77 -> 3800000 | F53: 0 | G53: Menutup beban Beban Komisi
A54: 46418 | B54: 50 | C54: Penutup | D54: Beban Komisi | E54: 0 | F54: =Buku_Besar!$K$77 -> 3800000 | G54: Menutup Beban Komisi
A55: 46418 | B55: 51 | C55: Penutup | D55: Ikhtisar Laba Rugi | E55: =Buku_Besar!$K$78 -> 7500000 | F55: 0 | G55: Menutup beban Beban Bonus
A56: 46418 | B56: 52 | C56: Penutup | D56: Beban Bonus | E56: 0 | F56: =Buku_Besar!$K$78 -> 7500000 | G56: Menutup Beban Bonus
A57: 46418 | B57: 53 | C57: Penutup | D57: Ikhtisar Laba Rugi | E57: =Buku_Besar!$K$79 -> 4500000 | F57: 0 | G57: Menutup beban Beban Kerugian Piutang
A58: 46418 | B58: 54 | C58: Penutup | D58: Beban Kerugian Piutang | E58: 0 | F58: =Buku_Besar!$K$79 -> 4500000 | G58: Menutup Beban Kerugian Piutang
A59: 46418 | B59: 55 | C59: Penutup | D59: Ikhtisar Laba Rugi | E59: =Buku_Besar!$K$80 -> 10500000 | F59: 0 | G59: Menutup beban Beban Kerugian Persediaan
A60: 46418 | B60: 56 | C60: Penutup | D60: Beban Kerugian Persediaan | E60: 0 | F60: =Buku_Besar!$K$80 -> 10500000 | G60: Menutup Beban Kerugian Persediaan
A61: 46418 | B61: 57 | C61: Penutup | D61: Ikhtisar Laba Rugi | E61: =Buku_Besar!$K$81 -> 800000 | F61: 0 | G61: Menutup beban Beban Pajak Daerah
A62: 46418 | B62: 58 | C62: Penutup | D62: Beban Pajak Daerah | E62: 0 | F62: =Buku_Besar!$K$81 -> 800000 | G62: Menutup Beban Pajak Daerah
A63: 46418 | B63: 59 | C63: Penutup | D63: Ikhtisar Laba Rugi | E63: =Buku_Besar!$K$82 -> 400000 | F63: 0 | G63: Menutup beban Beban Administrasi Bank
A64: 46418 | B64: 60 | C64: Penutup | D64: Beban Administrasi Bank | E64: 0 | F64: =Buku_Besar!$K$82 -> 400000 | G64: Menutup Beban Administrasi Bank
A65: 46418 | B65: 61 | C65: Penutup | D65: Ikhtisar Laba Rugi | E65: =Buku_Besar!$K$83 -> 8000000 | F65: 0 | G65: Menutup beban Beban Pajak Penghasilan
A66: 46418 | B66: 62 | C66: Penutup | D66: Beban Pajak Penghasilan | E66: 0 | F66: =Buku_Besar!$K$83 -> 8000000 | G66: Menutup Beban Pajak Penghasilan
A67: 46418 | B67: 63 | C67: Penutup | D67: Ikhtisar Laba Rugi | E67: =Buku_Besar!$K$84 -> 2000000 | F67: 0 | G67: Menutup beban Beban Training
A68: 46418 | B68: 64 | C68: Penutup | D68: Beban Training | E68: 0 | F68: =Buku_Besar!$K$84 -> 2000000 | G68: Menutup Beban Training
A69: 46418 | B69: 65 | C69: Penutup | D69: Ikhtisar Laba Rugi | E69: =Buku_Besar!$K$85 -> 1500000 | F69: 0 | G69: Menutup beban Beban Keamanan
A70: 46418 | B70: 66 | C70: Penutup | D70: Beban Keamanan | E70: 0 | F70: =Buku_Besar!$K$85 -> 1500000 | G70: Menutup Beban Keamanan
A71: 46418 | B71: 67 | C71: Penutup | D71: Ikhtisar Laba Rugi | E71: =Buku_Besar!$K$86 -> 800000 | F71: 0 | G71: Menutup beban Beban Kurir
A72: 46418 | B72: 68 | C72: Penutup | D72: Beban Kurir | E72: 0 | F72: =Buku_Besar!$K$86 -> 800000 | G72: Menutup Beban Kurir
A73: 46418 | B73: 69 | C73: Penutup | D73: Ikhtisar Laba Rugi | E73: =Buku_Besar!$K$87 -> 300000 | F73: 0 | G73: Menutup beban Beban Selisih Kas
A74: 46418 | B74: 70 | C74: Penutup | D74: Beban Selisih Kas | E74: 0 | F74: =Buku_Besar!$K$87 -> 300000 | G74: Menutup Beban Selisih Kas
A75: 46418 | B75: 71 | C75: Penutup | D75: Ikhtisar Laba Rugi | E75: =Buku_Besar!$K$88 -> 1000000 | F75: 0 | G75: Menutup beban Kerugian Penjualan Aset
A76: 46418 | B76: 72 | C76: Penutup | D76: Kerugian Penjualan Aset | E76: 0 | F76: =Buku_Besar!$K$88 -> 1000000 | G76: Menutup Kerugian Penjualan Aset
A77: 46418 | B77: 73 | C77: Penutup | D77: Ikhtisar Laba Rugi | E77: =Buku_Besar!$K$89 -> 0 | F77: 0 | G77: Menutup beban Beban Denda Pajak
A78: 46418 | B78: 74 | C78: Penutup | D78: Beban Denda Pajak | E78: 0 | F78: =Buku_Besar!$K$89 -> 0 | G78: Menutup Beban Denda Pajak
A79: 46418 | B79: 75 | C79: Penutup | D79: Ikhtisar Laba Rugi | E79: =MAX(0,Laba_Rugi!$B$45) -> 134800000 | F79: =MAX(0,-Laba_Rugi!$B$45) -> 0 | G79: Menutup Ikhtisar Laba Rugi
A80: 46418 | B80: 76 | C80: Penutup | D80: Saldo Laba | E80: =MAX(0,-Laba_Rugi!$B$45) -> 0 | F80: =MAX(0,Laba_Rugi!$B$45) -> 134800000 | G80: Mentransfer laba/rugi ke Saldo Laba
A81: 46418 | B81: 77 | C81: Penutup | D81: Dividen | E81: 0 | F81: =Buku_Besar!$K$50 -> 15000000 | G81: Menutup Dividen
A82: 46418 | B82: 78 | C82: Penutup | D82: Saldo Laba | E82: =Buku_Besar!$K$50 -> 15000000 | F82: 0 | G82: Menutup Dividen ke Saldo Laba

Sheet NS_Setelah_Penutupan
A1: NERACA SALDO – SETELAH PENUTUPAN
A2: Sumber: Saldo akhir Buku Besar setelah Jurnal Penutup. Akun nominal harus nol.
A3: Kode Akun | B3: Nama Akun | C3: Kategori | D3: Saldo Normal | E3: Debit (Rp) | F3: Kredit (Rp)
A4: 1-001 | B4: Bank | C4: Aset | D4: Debit | E4: =Buku_Besar!O4 -> 1403427000 | F4: =Buku_Besar!P4 -> 0
A5: 1-002 | B5: Kas Kecil | C5: Aset | D5: Debit | E5: =Buku_Besar!O5 -> 37850000 | F5: =Buku_Besar!P5 -> 0
A6: 1-003 | B6: Piutang Usaha | C6: Aset | D6: Debit | E6: =Buku_Besar!O6 -> 116140000 | F6: =Buku_Besar!P6 -> 0
A7: 1-004 | B7: Piutang Karyawan | C7: Aset | D7: Debit | E7: =Buku_Besar!O7 -> 3000000 | F7: =Buku_Besar!P7 -> 0
A8: 1-005 | B8: Piutang Bunga | C8: Aset | D8: Debit | E8: =Buku_Besar!O8 -> 700000 | F8: =Buku_Besar!P8 -> 0
A9: 1-006 | B9: Piutang Pendapatan | C9: Aset | D9: Debit | E9: =Buku_Besar!O9 -> 0 | F9: =Buku_Besar!P9 -> 0
A10: 1-007 | B10: Persediaan Barang Dagang | C10: Aset | D10: Debit | E10: =Buku_Besar!O10 -> 251800000 | F10: =Buku_Besar!P10 -> 0
A11: 1-008 | B11: PPN Masukan | C11: Aset | D11: Debit | E11: =Buku_Besar!O11 -> 26158000 | F11: =Buku_Besar!P11 -> 0
A12: 1-009 | B12: PPh 22 Dibayar di Muka | C12: Aset | D12: Debit | E12: =Buku_Besar!O12 -> 2625000 | F12: =Buku_Besar!P12 -> 0
A13: 1-010 | B13: PPh 23 Dibayar di Muka | C13: Aset | D13: Debit | E13: =Buku_Besar!O13 -> 0 | F13: =Buku_Besar!P13 -> 0
A14: 1-011 | B14: PPh Final Dibayar di Muka | C14: Aset | D14: Debit | E14: =Buku_Besar!O14 -> 0 | F14: =Buku_Besar!P14 -> 0
A15: 1-012 | B15: Sewa Dibayar di Muka | C15: Aset | D15: Debit | E15: =Buku_Besar!O15 -> 18000000 | F15: =Buku_Besar!P15 -> 0
... A91: 2-021 | B91: PPN Keluaran | C91: Liabilitas | D91: Kredit | E91: =Buku_Besar!O91 -> 0 | F91: =Buku_Besar!P91 -> 0
A92: TOTAL | E92: =SUM(E4:E91) -> 2514400000 | F92: =SUM(F4:F91) -> 2514400000

Sheet Laba_Rugi
A1: LAPORAN LABA RUGI – PT SINAR NIAGA INDONESIA
A2: Untuk periode yang berakhir 31 Januari 2027 | Perpetual | Accrual basis
A4: Keterangan | B4: Jumlah (Rp)
A5: Penjualan | B5: =Buku_Besar!$L$53 -> 699000000
A6: (-) Retur Penjualan | B6: =Buku_Besar!$K$54 -> 25000000
A7: (-) Potongan Penjualan | B7: =Buku_Besar!$K$55 -> 4600000
A8: Penjualan Bersih | B8: =B5-B6-B7 -> 669400000
A9: (-) HPP | B9: =Buku_Besar!$K$60 -> 391400000
A10: Laba Kotor | B10: =B8-B9 -> 278000000
A11: Beban Gaji | B11: =Buku_Besar!$K$61 -> 30000000
A12: Beban BPJS | B12: =Buku_Besar!$K$62 -> 3500000
A13: Beban Sewa | B13: =Buku_Besar!$K$63 -> 26000000
A14: Beban Asuransi | B14: =Buku_Besar!$K$64 -> 1500000
A15: Beban Perlengkapan | B15: =Buku_Besar!$K$65 -> 2200000
A16: Beban Iklan | B16: =Buku_Besar!$K$66 -> 1000000
A17: Beban Lisensi/Software | B17: =Buku_Besar!$K$67 -> 400000
A18: Beban Penyusutan Peralatan Toko | B18: =Buku_Besar!$K$68 -> 1250000
A19: Beban Penyusutan Peralatan Kantor | B19: =Buku_Besar!$K$69 -> 333333.33
A20: Beban Penyusutan Kendaraan | B20: =Buku_Besar!$K$70 -> 4166666.7
A21: Beban Utilitas | B21: =Buku_Besar!$K$71 -> 7400000
A22: Beban Pengiriman Penjualan | B22: =Buku_Besar!$K$72 -> 3500000
A23: Beban Jasa Profesional | B23: =Buku_Besar!$K$73 -> 18000000
A24: Beban Pemeliharaan | B24: =Buku_Besar!$K$74 -> 3000000
A25: Beban ATK | B25: =Buku_Besar!$K$75 -> 0
A26: Beban Bunga | B26: =Buku_Besar!$K$76 -> 4200000
A27: Beban Komisi | B27: =Buku_Besar!$K$77 -> 3800000
A28: Beban Bonus | B28: =Buku_Besar!$K$78 -> 7500000
A29: Beban Kerugian Piutang | B29: =Buku_Besar!$K$79 -> 4500000
A30: Beban Kerugian Persediaan | B30: =Buku_Besar!$K$80 -> 10500000
A31: Beban Pajak Daerah | B31: =Buku_Besar!$K$81 -> 800000
A32: Beban Administrasi Bank | B32: =Buku_Besar!$K$82 -> 400000
A33: Beban Training | B33: =Buku_Besar!$K$84 -> 2000000
A34: Beban Keamanan | B34: =Buku_Besar!$K$85 -> 1500000
A35: Beban Kurir | B35: =Buku_Besar!$K$86 -> 800000
A36: Beban Selisih Kas | B36: =Buku_Besar!$K$87 -> 300000
A37: Total Beban Operasi | B37: =SUM(B11:B36) -> 138550000
A38: Laba Operasi | B38: =B10-B37 -> 139450000
A39: Pendapatan Bunga | B39: =Buku_Besar!$L$57 -> 2200000
A40: Keuntungan Penjualan Aset | B40: =Buku_Besar!$L$58 -> 2000000
A41: Pendapatan Lain-lain | B41: =Buku_Besar!$L$59 -> 150000
A42: Kerugian Penjualan Aset | B42: =Buku_Besar!$K$88 -> 1000000
A43: Laba Sebelum Pajak | B43: =B38+B39+B40+B41-B42 -> 142800000
A44: Beban Pajak Penghasilan | B44: =Buku_Besar!$K$83 -> 8000000
A45: Laba Bersih | B45: =B43-B44 -> 134800000

Sheet Perubahan_Ekuitas
A1: LAPORAN PERUBAHAN EKUITAS – PT SINAR NIAGA INDONESIA
A2: Untuk periode yang berakhir 31 Januari 2027
A4: Keterangan | B4: Jumlah (Rp)
A5: Saldo laba awal | B5: 0
A6: Setoran modal | B6: =Buku_Besar!$P$49 -> 1730000000
A7: Laba bersih | B7: =Laba_Rugi!$B$45 -> 134800000
A8: (-) Dividen | B8: =Buku_Besar!$O$50 -> 0
A9: Saldo laba akhir | B9: =B5+B6+B7-B8 -> 1864800000

Sheet Posisi_Keuangan
A1: LAPORAN POSISI KEUANGAN – PT SINAR NIAGA INDONESIA
A2: Per 31 Januari 2027 | Saldo setelah penutupan
A4: Column1 | B4: Column2 | C4: Column3 | D4: Column4 | E4: Column5
A5: ASET | B5: Jumlah (Rp) | D5: LIABILITAS & EKUITAS | E5: Jumlah (Rp)
A6: Bank | B6: =IF(Buku_Besar!$O$4>0,Buku_Besar!$O$4,-Buku_Besar!$P$4) -> 1403427000 | D6: Utang Usaha | E6: =IF(Buku_Besar!$P$30>0,Buku_Besar!$P$30,-Buku_Besar!$O$30) -> 148400000
A7: Kas Kecil | B7: =IF(Buku_Besar!$O$5>0,Buku_Besar!$O$5,-Buku_Besar!$P$5) -> 37850000 | D7: Utang Gaji | E7: =IF(Buku_Besar!$P$31>0,Buku_Besar!$P$31,-Buku_Besar!$O$31) -> 5000000
A8: Piutang Usaha | B8: =IF(Buku_Besar!$O$6>0,Buku_Besar!$O$6,-Buku_Besar!$P$6) -> 116140000 | D8: Utang Bonus | E8: =IF(Buku_Besar!$P$32>0,Buku_Besar!$P$32,-Buku_Besar!$O$32) -> 7500000
A9: Piutang Karyawan | B9: =IF(Buku_Besar!$O$7>0,Buku_Besar!$O$7,-Buku_Besar!$P$7) -> 3000000 | D9: Utang Bunga | E9: =IF(Buku_Besar!$P$33>0,Buku_Besar!$P$33,-Buku_Besar!$O$33) -> 1200000
A10: Penyisihan Piutang Tak Tertagih | B10: =-IF(Buku_Besar!$P$29>0,Buku_Besar!$P$29,-Buku_Besar!$O$29) -> -2500000 | D10: Utang Utilitas | E10: =IF(Buku_Besar!$P$34>0,Buku_Besar!$P$34,-Buku_Besar!$O$34) -> 1800000
A11: Piutang Bunga | B11: =IF(Buku_Besar!$O$8>0,Buku_Besar!$O$8,-Buku_Besar!$P$8) -> 700000 | D11: Utang BPJS | E11: =IF(Buku_Besar!$P$35>0,Buku_Besar!$P$35,-Buku_Besar!$O$35) -> 1500000
A12: Persediaan Barang Dagang | B12: =IF(Buku_Besar!$O$10>0,Buku_Besar!$O$10,-Buku_Besar!$P$10) -> 251800000 | D12: Utang PPN | E12: =IF(Buku_Besar!$P$36>0,Buku_Besar!$P$36,-Buku_Besar!$O$36) -> 0
A13: PPN Masukan | B13: =IF(Buku_Besar!$O$11>0,Buku_Besar!$O$11,-Buku_Besar!$P$11) -> 26158000 | D13: Utang PPh 21 | E13: =IF(Buku_Besar!$P$37>0,Buku_Besar!$P$37,-Buku_Besar!$O$37) -> 0
A14: PPh 22 Dibayar di Muka | B14: =IF(Buku_Besar!$O$12>0,Buku_Besar!$O$12,-Buku_Besar!$P$12) -> 2625000 | D14: Utang PPh 22 | E14: =IF(Buku_Besar!$P$38>0,Buku_Besar!$P$38,-Buku_Besar!$O$38) -> 0
A15: Sewa Dibayar di Muka | B15: =IF(Buku_Besar!$O$15>0,Buku_Besar!$O$15,-Buku_Besar!$P$15) -> 18000000 | D15: Utang PPh 23 | E15: =IF(Buku_Besar!$P$39>0,Buku_Besar!$P$39,-Buku_Besar!$O$39) -> 50000
A16: Asuransi Dibayar di Muka | B16: =IF(Buku_Besar!$O$16>0,Buku_Besar!$O$16,-Buku_Besar!$P$16) -> 19500000 | D16: Utang PPh Final 4(2) | E16: =IF(Buku_Besar!$P$40>0,Buku_Besar!$P$40,-Buku_Besar!$O$40) -> 0
A17: Iklan Dibayar di Muka | B17: =IF(Buku_Besar!$O$17>0,Buku_Besar!$O$17,-Buku_Besar!$P$17) -> 11000000 | D17: Utang Pajak Penghasilan | E17: =IF(Buku_Besar!$P$41>0,Buku_Besar!$P$41,-Buku_Besar!$O$41) -> 8000000
A18: Perlengkapan | B18: =IF(Buku_Besar!$O$18>0,Buku_Besar!$O$18,-Buku_Besar!$P$18) -> 2800000 | D18: Utang Pajak Daerah | E18: =IF(Buku_Besar!$P$42>0,Buku_Besar!$P$42,-Buku_Besar!$O$42) -> 800000
A19: Uang Muka Pembelian | B19: =IF(Buku_Besar!$O$19>0,Buku_Besar!$O$19,-Buku_Besar!$P$19) -> 0 | D19: Utang Bank Jangka Pendek | E19: =IF(Buku_Besar!$P$43>0,Buku_Besar!$P$43,-Buku_Besar!$O$43) -> 40000000
A20: Software Dibayar di Muka | B20: =IF(Buku_Besar!$O$20>0,Buku_Besar!$O$20,-Buku_Besar!$P$20) -> 4400000 | D20: Utang Bank Jangka Panjang | E20: =IF(Buku_Besar!$P$44>0,Buku_Besar!$P$44,-Buku_Besar!$O$44) -> 380000000
A21: Lisensi Dibayar di Muka | B21: =IF(Buku_Besar!$O$21>0,Buku_Besar!$O$21,-Buku_Besar!$P$21) -> 12000000 | D21: Uang Muka Pelanggan | E21: =IF(Buku_Besar!$P$45>0,Buku_Besar!$P$45,-Buku_Besar!$O$45) -> 0
A22: Peralatan Toko | B22: =IF(Buku_Besar!$O$22>0,Buku_Besar!$O$22,-Buku_Besar!$P$22) -> 145000000 | D22: Utang Dividen | E22: =IF(Buku_Besar!$P$48>0,Buku_Besar!$P$48,-Buku_Besar!$O$48) -> 0
A23: Peralatan Kantor | B23: =IF(Buku_Besar!$O$23>0,Buku_Besar!$O$23,-Buku_Besar!$P$23) -> 60000000 | D23: Utang Beban / Akrual | E23: =IF(Buku_Besar!$P$90>0,Buku_Besar!$P$90,-Buku_Besar!$O$90) -> 12100000
A24: Akumulasi Penyusutan Peralatan Toko | B24: =-IF(Buku_Besar!$P$26>0,Buku_Besar!$P$26,-Buku_Besar!$O$26) -> -1250000 | D24: PPN Keluaran | E24: =IF(Buku_Besar!$P$91>0,Buku_Besar!$P$91,-Buku_Besar!$O$91) -> 0
A25: Akumulasi Penyusutan Peralatan Kantor | B25: =-IF(Buku_Besar!$P$27>0,Buku_Besar!$P$27,-Buku_Besar!$O$27) -> -333333.33 | D25: Total Liabilitas | E25: =SUM(E6:E24) -> 606350000
A26: Kendaraan | B26: =IF(Buku_Besar!$O$24>0,Buku_Besar!$O$24,-Buku_Besar!$P$24) -> 400000000
A27: Akumulasi Penyusutan Kendaraan | B27: =-IF(Buku_Besar!$P$28>0,Buku_Besar!$P$28,-Buku_Besar!$O$28) -> -54166667 | D27: EKUITAS
A28: Total Aset | B28: =SUM(B6:B27) -> 2456150000 | D28: Modal Saham | E28: =IF(Buku_Besar!$P$49>0,Buku_Besar!$P$49,-Buku_Besar!$O$49) -> 1730000000
D29: Saldo Laba | E29: =IF(Buku_Besar!$P$51>0,Buku_Besar!$P$51,-Buku_Besar!$O$51) -> 119800000
D30: Total Ekuitas | E30: =SUM(E28:E29) -> 1849800000
D31: Total Liabilitas + Ekuitas | E31: =E25+E30 -> 2456150000
D33: CHECK NERACA | E33: =IF(ABS(B28-E31)<0.01,"BALANCE","PERIKSA") -> BALANCE

Sheet Arus_Kas
A1: LAPORAN ARUS KAS – METODE LANGSUNG BERBASIS TAG TRANSAKSI
A2: Untuk periode yang berakhir 31 Januari 2027 | Sumber: Arus_Kas_Data
A4: Column1 | B4: Column2 | C4: Column3
A5: Keterangan | B5: Jumlah (Rp) | C5: Catatan
A6: ARUS KAS DARI AKTIVITAS OPERASI
A7: Kas operasi masuk | B7: =SUMIFS(Arus_Kas_Data!$E$4:$E$70,Arus_Kas_Data!$G$4:$G$70,"Operasi") -> 713244000 | C7: Debit kas tagged Operasi
A8: Kas operasi keluar | B8: =SUMIFS(Arus_Kas_Data!$F$4:$F$70,Arus_Kas_Data!$G$4:$G$70,"Operasi") -> 710187000 | C8: Kredit kas tagged Operasi
A9: Kas Bersih Operasi | B9: =B7-B8 -> 3057000
A10: ARUS KAS DARI AKTIVITAS INVESTASI
A11: Kas investasi masuk | B11: =SUMIFS(Arus_Kas_Data!$E$4:$E$70,Arus_Kas_Data!$G$4:$G$70,"Investasi") -> 35320000 | C11: Debit kas tagged Investasi
A12: Kas investasi keluar | B12: =SUMIFS(Arus_Kas_Data!$F$4:$F$70,Arus_Kas_Data!$G$4:$G$70,"Investasi") -> 384100000 | C12: Kredit kas tagged Investasi
A13: Kas Bersih Investasi | B13: =B11-B12 -> -348780000
A14: ARUS KAS DARI AKTIVITAS PENDANAAN
A15: Kas pendanaan masuk | B15: =SUMIFS(Arus_Kas_Data!$E$4:$E$70,Arus_Kas_Data!$G$4:$G$70,"Pendanaan") -> 1750000000 | C15: Debit kas tagged Pendanaan
A16: Kas pendanaan keluar | B16: =SUMIFS(Arus_Kas_Data!$F$4:$F$70,Arus_Kas_Data!$G$4:$G$70,"Pendanaan") -> 73000000 | C16: Kredit kas tagged Pendanaan
A17: Kas Bersih Pendanaan | B17: =B15-B16 -> 1677000000
A18: Kenaikan/(Penurunan) Bersih Kas | B18: =B9+B13+B17 -> 1331277000
A19: Kas dan Kas Kecil Awal | B19: 110000000 | C19: Saldo awal dari Saldo_Awal: Bank Rp100 juta + Kas Kecil Rp10 juta
A20: Kas dan Kas Kecil Akhir | B20: =B18+B19 -> 1441277000 | C20: Harus sama dengan saldo kas & bank setelah penutupan
A21: CHECK CASH | B21: =Buku_Besar!$O$4+Buku_Besar!$O$5 -> 1441277000
B22: =IF(ABS(B20-B21)<0.01,"BALANCE","PERIKSA") -> BALANCE

Sheet CALK
A1: CATATAN ATAS LAPORAN KEUANGAN (CALK) – WORKBOOK LATIHAN
A2: Catatan kebijakan, saldo utama, rekonsiliasi, dan sumber resmi yang digunakan untuk parameter latihan.
A4: No | B4: Catatan | C4: Uraian | D4: Nilai / Formula | E4: Sumber | F4: Keterangan
A5: 1 | B5: Entitas | C5: PT Sinar Niaga Indonesia – perusahaan dagang. | E5: Workbook | F5: Perpetual inventory; accrual basis.
A6: 2 | B6: Periode | C6: 1–31 Januari 2027. | E6: Workbook | F6: Saldo awal berasal dari 31 Desember 2026.
A7: 3 | B7: COA | C7: Chart of Accounts diperluas menjadi 88 akun. | D7: 88 akun | E7: COA | F7: Mencakup AP, AR, payroll, tax, inventory, fixed assets, financing, dan expenses.
A8: 4 | B8: PPN latihan | C8: PPN efektif 11% hanya untuk soal yang eksplisit menyatakan demikian. | E8: Parameter_Latihan | F8: Tarif umum tidak boleh diasumsikan sama untuk semua objek/DPP.
A9: 5 | B9: PPh 23 | C9: Kasus tertentu memakai 2% dari jumlah bruto jasa tertentu. | E9: Parameter_Latihan | F9: Rujukan DJP.
A10: 6 | B10: PPh Final 4(2) | C10: Sewa tanah/bangunan memakai 10% dari jumlah bruto dalam latihan. | E10: Parameter_Latihan | F10: Rujukan DJP.
A11: 7 | B11: PPh 22 | C11: Kasus pemungut tertentu 1,5%; impor API 2,5%. | E11: Parameter_Latihan | F11: Rujukan DJP.
A12: 8 | B12: Persediaan | C12: Perpetual; HPP dicatat saat penjualan. | E12: Workbook | F12: Kartu persediaan terpilih menggunakan FIFO.
A13: 9 | B13: Laba Bersih | C13: Laba bersih periode. | D13: =Laba_Rugi!$B$45 -> 134800000 | E13: Laba_Rugi | F13: Formula-linked.
A14: 10 | B14: Total Aset | C14: Total aset setelah penutupan. | D14: =Posisi_Keuangan!$B$28 -> 2456150000 | E14: Posisi_Keuangan | F14: Harus sama dengan liabilitas + ekuitas.
A15: 11 | B15: Kas Akhir | C15: Bank + Kas Kecil setelah penutupan. | D15: =Arus_Kas!$B$21 -> 1441277000 | E15: Arus_Kas | F15: Harus sama dengan arus kas akhir.
A16: 12 | B16: AP Subledger | C16: Saldo AP vendor invoice-level. | D16: =Rekap_AP!$G$11 -> 148400000 | E16: Rekap_AP | F16: Harus tie dengan Utang Usaha; accruals dipisah.
A17: 13 | B17: AR Subledger | C17: Saldo AR customer-level. | D17: =Rekap_AR!$I$8 -> 116140000 | E17: Rekap_AR | F17: Harus tie dengan Piutang Usaha.
A18: 14 | B18: PPN Net | C18: Posisi PPN Masukan bersih setelah clearing PPN Keluaran. | D18: =Rekonsiliasi_Akun!$B$7 -> 26158000 | E18: Rekonsiliasi_Akun | F18: Dalam latihan tersisa PPN Masukan Rp26.158.000 setelah clearing output.
A19: 15 | B19: Bank Recon | C19: Saldo buku dan bank setelah recon items. | D19: =Rekonsiliasi_Bank!$B$13 -> BALANCE | E19: Rekonsiliasi_Bank | F19: Harus BALANCE.
A20: 16 | B20: Closing | C20: Saldo revenue/expense/dividend ditutup ke equity. | E20: Jurnal_Penutup | F20: Neraca saldo setelah penutupan hanya memuat akun permanen.
A22: 20 | B22: Sumber resmi pajak | C22: PPN / Harmonisasi | D22: https://pajak.go.id/id/pajak-pertambahan-nilai | E22: DJP | F22: Gunakan untuk verifikasi tarif dan ketentuan terbaru.
A23: 21 | B23: Sumber resmi pajak | C23: PPN DPP Nilai Lain | D23: https://stats.pajak.go.id/id/siaran-pers/pemerintah-terbitkan-aturan-dpp-nilai-lain-dan-besaran-tertentu-pajak-pertambahan-nilai | E23: DJP | F23: Rujukan formula 12% × 11/12 untuk objek tertentu.
A24: 22 | B24: Sumber resmi pajak | C24: PPh 23 | D24: https://www.pajak.go.id/id/pph-pasal-23 | E24: DJP | F24: Rujukan objek/tarif PPh23.
A25: 23 | B25: Sumber resmi pajak | C25: PPh Final 4(2) | D25: https://pajak.go.id/id/pph-pasal-4-ayat-2 | E25: DJP | F25: Rujukan sewa tanah/bangunan.
A26: 24 | B26: Sumber resmi pajak | C26: PPh 22 | D26: https://pajak.go.id/pph-pasal-22 | E26: DJP | F26: Rujukan pemungutan pembelian/impor.

Sheet Kamus_Rumus
A1: KAMUS RUMUS & LOGIKA ACCOUNTING WORKBOOK
A4: Konsep | B4: Rumus / Logika | C4: Contoh Penggunaan | D4: Catatan
A5: Saldo akun | B5: Debit total – Kredit total | C5: Buku_Besar | D5: Aset/beban normal debit; liabilitas/ekuitas/pendapatan normal kredit.
A6: Saldo debit | B6: MAX(saldo,0) | C6: Neraca Saldo | D6: Dipakai saat saldo akun positif.
A7: Saldo kredit | B7: MAX(-saldo,0) | C7: Neraca Saldo | D7: Dipakai saat saldo akun negatif.
A8: Penjualan bersih | B8: Penjualan – Retur – Potongan | C8: Laba_Rugi | D8: Contra revenue mengurangi penjualan.
A9: Laba kotor | B9: Penjualan bersih – HPP | C9: Laba_Rugi | D9: Perusahaan dagang.
A10: Laba operasi | B10: Laba kotor – beban operasi | C10: Laba_Rugi | D10: Pendapatan/beban non-operasi dipisahkan.
A11: Piutang bersih | B11: Piutang – Penyisihan | C11: Posisi_Keuangan | D11: Write-off mengurangi piutang & allowance.
A12: AP ending | B12: Opening + invoice – return – payment – discount | C12: Rekap_AP | D12: Subledger supplier-level.
A13: AR ending | B13: Opening + invoice – return/rebate – receipt – discount – write-off | C13: Rekap_AR | D13: Subledger customer-level.
A14: Bank reconciliation | B14: Saldo bank + DIT – checks = saldo buku ± bank-only items | C14: Rekonsiliasi_Bank | D14: Kedua sisi harus sama.
A15: HPP perpetual | B15: Diakui ketika barang terjual | C15: Kunci_Jurnal_80 / Inventory_Kartu | D15: Tidak menunggu akhir periode untuk penjualan normal.
... A20: PPN latihan | B20: 11% × DPP untuk soal yang eksplisit | C20: Jurnal Umum | D20: Parameter latihan, bukan tarif umum.

Sheet Arus_Kas_Data
A1: ARUS KAS DATA – CASH MOVEMENTS DARI 80 JURNAL
A3: Tanggal | B3: No | C3: Counterparty | D3: Cash Account | E3: Kas Masuk | F3: Kas Keluar | G3: Aktivitas | H3: Dokumen | I3: Keterangan | J3: Catatan
A4: 46388 | B4: 1 | C4: Pemegang Saham | D4: Bank | E4: 1500000000 | F4: 0 | G4: Pendanaan | H4: Bukti Setoran Saham | I4: Pemegang saham menyetor modal tunai Rp1.500.000.000 ke rekening bank perusahaan.
A5: 46388 | B5: 2 | C5: Internal | D5: Kas Kecil | E5: 20000000 | F5: 0 | G5: Investasi | H5: Bukti Transfer | I5: Perusahaan memindahkan Rp20.000.000 dari bank ke kas kecil.
A6: 46388 | B6: 2 | C6: Internal | D6: Bank | E6: 0 | F6: 20000000 | G6: Investasi | H6: Bukti Transfer | I6: Perusahaan memindahkan Rp20.000.000 dari bank ke kas kecil.
A7: 46389 | B7: 3 | C7: PT Perkasa Office | D7: Bank | E7: 0 | F7: 66600000 | G7: Investasi | H7: Bukti Bayar | I7: Perusahaan membeli peralatan toko Rp60.000.000 sebelum PPN. PPN latihan efektif 11%.
A8: 46391 | B8: 7 | C8: Ekspedisi Logistik | D8: Bank | E8: 0 | F8: 4000000 | G8: Operasi | H8: Bukti Bayar | I8: Perusahaan membayar ongkos angkut pembelian Rp4.000.000 melalui bank. Ongkos angkut menambah biaya perolehan persediaan.
A9: 46392 | B9: 8 | C9: Pelanggan Umum | D9: Bank | E9: 133200000 | F9: 0 | G9: Operasi | H9: SO-001 | I9: Perusahaan menjual barang secara tunai Rp120.000.000 sebelum PPN. HPP Rp70.000.000.
A10: 46394 | B10: 10 | C10: Pelanggan B | D10: Bank | E10: 80000000 | F10: 0 | G10: Operasi | H10: Bukti Transfer | I10: Pelanggan B membayar piutang Rp80.000.000 melalui bank.
A11: 46395 | B11: 11 | C11: Supplier A | D11: Bank | E11: 0 | F11: 100000000 | G11: Operasi | H11: Bukti Bayar | I11: Perusahaan membayar Utang Usaha kepada Supplier A sebesar Rp100.000.000 melalui bank.
A12: 46395 | B12: 12 | C12: Pelanggan C | D12: Bank | E12: 44440000 | F12: 0 | G12: Operasi | H12: AR-DP-001 | I12: Pelanggan C membayar uang muka Rp44.440.000 melalui bank untuk pesanan barang yang akan dikirim kemudian.
A13: 46397 | B13: 15 | C13: Ekspedisi | D13: Bank | E13: 0 | F13: 2500000 | G13: Operasi | H13: Bukti Bayar | I13: Perusahaan membayar ongkos pengiriman penjualan Rp2.500.000 melalui bank.
A14: 46398 | B14: 16 | C14: Media Nusantara | D14: Bank | E14: 0 | F14: 12000000 | G14: Operasi | H14: Bukti Bayar | I14: Perusahaan membayar kontrak iklan 12 bulan sebesar Rp12.000.000 melalui bank.
A15: 46398 | B15: 17 | C15: PT Properti Sentosa | D15: Bank | E15: 0 | F15: 18000000 | G15: Operasi | H15: Bukti Bayar | I15: Perusahaan membayar sewa toko Rp18.000.000 untuk tiga bulan melalui bank.
... A70: 46418 | B70: 80 | C70: Ekspedisi | D70: Bank | E70: 0 | F70: 1000000 | G70: Operasi | H70: EXP-DEL-002 | I70: Perusahaan melunasi utang Supplier A Rp25.000.000 melalui bank. Pada hari yang sama Pelanggan F membayar piutang Rp40.000.000 dan perusahaan membayar biaya pengiriman penjualan Rp1.000.000.

Sheet Saldo_Awal
A1: SALDO AWAL – NERACA PER 31 DESEMBER 2026
A2: Saldo awal dipakai untuk membuat siklus Januari 2027 realistis, termasuk akumulasi penyusutan, AR, AP, dan pinjaman yang sudah ada.
A3: Kode Akun | B3: Nama Akun | C3: Debit Awal (Rp) | D3: Kredit Awal (Rp) | E3: Sumber | F3: Rincian | G3: Check
A4: 1-001 | B4: Bank | C4: 100000000 | D4: 0 | E4: Opening balance | F4: Per 31 Desember 2026
A5: 1-002 | B5: Kas Kecil | C5: 10000000 | D5: 0 | E5: Opening balance | F5: Per 31 Desember 2026
A6: 1-003 | B6: Piutang Usaha | C6: 60000000 | D6: 0 | E6: Opening balance | F6: Per 31 Desember 2026
A7: 1-004 | B7: Piutang Karyawan | C7: 0 | D7: 0 | E7: Opening balance | F7: Per 31 Desember 2026
A8: 1-005 | B8: Piutang Bunga | C8: 0 | D8: 0 | E8: Opening balance | F8: Per 31 Desember 2026
A9: 1-006 | B9: Piutang Pendapatan | C9: 0 | D9: 0 | E9: Opening balance | F9: Per 31 Desember 2026
A10: 1-007 | B10: Persediaan Barang Dagang | C10: 120000000 | D10: 0 | E10: Opening balance | F10: Per 31 Desember 2026
A11: 1-008 | B11: PPN Masukan | C11: 0 | D11: 0 | E11: Opening balance | F11: Per 31 Desember 2026
A12: 1-009 | B12: PPh 22 Dibayar di Muka | C12: 0 | D12: 0 | E12: Opening balance | F12: Per 31 Desember 2026
A13: 1-010 | B13: PPh 23 Dibayar di Muka | C13: 0 | D13: 0 | E13: Opening balance | F13: Per 31 Desember 2026
A14: 1-011 | B14: PPh Final Dibayar di Muka | C14: 0 | D14: 0 | E14: Opening balance | F14: Per 31 Desember 2026
A15: 1-012 | B15: Sewa Dibayar di Muka | C15: 6000000 | D15: 0 | E15: Opening balance | F15: Per 31 Desember 2026
... A91: 2-021 | B91: PPN Keluaran | C91: 0 | D91: 0 | E91: Opening balance | F91: Per 31 Desember 2026
A92: TOTAL | C92: =SUM(C4:C91) -> 569000000 | D92: =SUM(D4:D91) -> 569000000 | G92: =IF(ABS(C92-D92)<0.01,"BALANCE","PERIKSA") -> BALANCE
